Workbook
Name flt_analyst: 'KPI Dashboard'!$Q$3
Name flt_month: 'KPI Dashboard'!$J$3
Name flt_queue: 'KPI Dashboard'!$M$3

Sheet KPI Dashboard
F3: =MAX(tbl_raw_data[updated_date]) -> 45168 | G3: ="Last Update: "&TEXT(F3,"mmm-dd") -> Last Update: Aug-30 | I3: Month: | J3: AUGUST | L3: Queue Name: | M3: ALL | P3: Analyst Name: | Q3: ALL
S5: Reasons | T5: # of apps | U5: % Contribution | V5: Last 30 days Tarends
S6: Incorrect Details | T6: =IF(AND(flt_queue="ALL",flt_analyst="ALL"),COUNTIFS(tbl_raw_data[updated_month],flt_month,tbl_raw_data[updated_message],S6), IF(AND(flt_queue<>"ALL",flt_analyst<>"ALL"),COUNTIFS(tbl_raw_data[updated_month],flt_month,tbl_raw_data[updated_queue],flt_queue,tbl_raw_data[analyst_name],flt_analyst,tbl_raw_data[updated_message],S6), IF(flt_queue="ALL",COUNTIFS(tbl_raw_data[updated_month],flt_month,tbl_raw_data[analyst_name],flt_analyst,tbl_raw_data[updated_message],S6), IF(flt_analyst="ALL",COUNTIFS(tbl_raw_data[updated_month],flt_month,tbl_raw_data[updated_queue],flt_queue,tbl_raw_data[updated_message],S6))))) -> 127 | U6: =T6/T13 -> 0.079275905
B7: KPI # | C7: KPI Name | D7: Current Vs Pervious | E7: week 4 | F7: week 3 | G7: week 2 | H7: week 1 | I7: See Notes | J7: Trend | K7: ="Month: "&flt_month& "; Queue: "&flt_queue& "; Analyst: "&flt_analyst -> Month: AUGUST; Queue: ALL; Analyst: ALL | S7: Overdue Bill | T7: =IF(AND(flt_queue="ALL",flt_analyst="ALL"),COUNTIFS(tbl_raw_data[updated_month],flt_month,tbl_raw_data[updated_message],S7,tbl_raw_data[updated_outcome],"WITHDRAW"), IF(AND(flt_queue<>"ALL",flt_analyst<>"ALL"),COUNTIFS(tbl_raw_data[updated_month],flt_month,tbl_raw_data[updated_queue],flt_queue,tbl_raw_data[analyst_name],flt_analyst,tbl_raw_data[updated_message],S7,tbl_raw_data[updated_outcome],"WITHDRAW"), IF(flt_queue="ALL",COUNTIFS(tbl_raw_data[updated_month],flt_month,tbl_raw_data[analyst_name],flt_analyst,tbl_raw_data[updated_message],S7,tbl_raw_data[updated_outcome],"WITHDRAW"), IF(flt_analyst="ALL",COUNTIFS(tbl_raw_data[updated_month],flt_month,tbl_raw_data[updated_queue],flt_queue,tbl_raw_data[updated_message],S7,tbl_raw_data[updated_outcome],"WITHDRAW"))))) -> 156 | U7: =T7/$T$13 -> 0.097378277
B8: KPI_1 | C8: % of Applications Approved | D8: =IF(OR(E8="-",F8="-"),"-",IF(E8>F8,settings!J3,IF(E8<F8,settings!J2,IF(E8=F8,#REF!)))) -> ↑ | E8: =IFERROR(IF(AND(flt_queue="ALL",flt_analyst="ALL"),COUNTIFS(tbl_raw_data[updated_month],flt_month,tbl_raw_data[updated_outcome],"APPROVE",tbl_raw_data[week],E7), IF(AND(flt_queue<>"ALL",flt_analyst<>"ALL"),COUNTIFS(tbl_raw_data[updated_month],flt_month,tbl_raw_data[updated_queue],flt_queue,tbl_raw_data[analyst_name],flt_analyst,tbl_raw_data[updated_outcome],"APPROVE",tbl_raw_data[week],E7), IF(flt_queue="ALL",COUNTIFS(tbl_raw_data[updated_month],flt_month,tbl_raw_data[analyst_name],flt_analyst,tbl_raw_data[updated_outcome],"APPROVE",tbl_raw_data[week],E7), IF(flt_analyst="ALL",COUNTIFS(tbl_raw_data[updated_month],flt_month,tbl_raw_data[updated_queue],flt_queue,tbl_raw_data[updated_outcome],"APPROVE",tbl_raw_data[week],E7))))) / IF(AND(flt_queue="ALL",flt_analyst="ALL"),COUNTIFS(tbl_raw_data[updated_month],flt_month,tbl_raw_data[week],E7), IF(AND(flt_queue<>"ALL",flt_analyst<>"ALL"),COUNTIFS(tbl_raw_data[updated_month],flt_month,tbl_raw_data[updated_queue],flt_queue,tbl_raw_data[analyst_name],flt_analyst,tbl_raw_data[week],E7), IF(flt_queue="ALL",COUNTIFS(tbl_raw_data[updated_month],flt_month,tbl_raw_data[analyst_name],flt_analyst,tbl_raw_data[week],E7), IF(flt_analyst="ALL",COUNTIFS(tbl_raw_data[updated_month],flt_month,tbl_raw_data[updated_queue],flt_queue,tbl_raw_data[week],E7))))),"-") -> 0.57015458 | F8: =IFERROR(IF(AND(flt_queue="ALL",flt_analyst="ALL"),COUNTIFS(tbl_raw_data[updated_month],flt_month,tbl_raw_data[updated_outcome],"APPROVE",tbl_raw_data[week],F7), IF(AND(flt_queue<>"ALL",flt_analyst<>"ALL"),COUNTIFS(tbl_raw_data[updated_month],flt_month,tbl_raw_data[updated_queue],flt_queue,tbl_raw_data[analyst_name],flt_analyst,tbl_raw_data[updated_outcome],"APPROVE",tbl_raw_data[week],F7), IF(flt_queue="ALL",COUNTIFS(tbl_raw_data[updated_month],flt_month,tbl_raw_data[analyst_name],flt_analyst,tbl_raw_data[updated_outcome],"APPROVE",tbl_raw_data[week],F7), IF(flt_analyst="ALL",COUNTIFS(tbl_raw_data[updated_month],flt_month,tbl_raw_data[updated_queue],flt_queue,tbl_raw_data[updated_outcome],"APPROVE",tbl_raw_data[week],F7))))) / IF(AND(flt_queue="ALL",flt_analyst="ALL"),COUNTIFS(tbl_raw_data[updated_month],flt_month,tbl_raw_data[week],F7), IF(AND(flt_queue<>"ALL",flt_analyst<>"ALL"),COUNTIFS(tbl_raw_data[updated_month],flt_month,tbl_raw_data[updated_queue],flt_queue,tbl_raw_data[analyst_name],flt_analyst,tbl_raw_data[week],F7), IF(flt_queue="ALL",COUNTIFS(tbl_raw_data[updated_month],flt_month,tbl_raw_data[analyst_name],flt_analyst,tbl_raw_data[week],F7), IF(flt_analyst="ALL",COUNTIFS(tbl_raw_data[updated_month],flt_month,tbl_raw_data[updated_queue],flt_queue,tbl_raw_data[week],F7))))),"-") -> 0.53585197 | G8: =IFERROR(IF(AND(flt_queue="ALL",flt_analyst="ALL"),COUNTIFS(tbl_raw_data[updated_month],flt_month,tbl_raw_data[updated_outcome],"APPROVE",tbl_raw_data[week],G7), IF(AND(flt_queue<>"ALL",flt_analyst<>"ALL"),COUNTIFS(tbl_raw_data[updated_month],flt_month,tbl_raw_data[updated_queue],flt_queue,tbl_raw_data[analyst_name],flt_analyst,tbl_raw_data[updated_outcome],"APPROVE",tbl_raw_data[week],G7), IF(flt_queue="ALL",COUNTIFS(tbl_raw_data[updated_month],flt_month,tbl_raw_data[analyst_name],flt_analyst,tbl_raw_data[updated_outcome],"APPROVE",tbl_raw_data[week],G7), IF(flt_analyst="ALL",COUNTIFS(tbl_raw_data[updated_month],flt_month,tbl_raw_data[updated_queue],flt_queue,tbl_raw_data[updated_outcome],"APPROVE",tbl_raw_data[week],G7))))) / IF(AND(flt_queue="ALL",flt_analyst="ALL"),COUNTIFS(tbl_raw_data[updated_month],flt_month,tbl_raw_data[week],G7), IF(AND(flt_queue<>"ALL",flt_analyst<>"ALL"),COUNTIFS(tbl_raw_data[updated_month],flt_month,tbl_raw_data[updated_queue],flt_queue,tbl_raw_data[analyst_name],flt_analyst,tbl_raw_data[week],G7), IF(flt_queue="ALL",COUNTIFS(tbl_raw_data[updated_month],flt_month,tbl_raw_data[analyst_name],flt_analyst,tbl_raw_data[week],G7), IF(flt_analyst="ALL",COUNTIFS(tbl_raw_data[updated_month],flt_month,tbl_raw_data[updated_queue],flt_queue,tbl_raw_data[week],G7))))),"-") -> 0.54039216 | H8: =IFERROR(IF(AND(flt_queue="ALL",flt_analyst="ALL"),COUNTIFS(tbl_raw_data[updated_month],flt_month,tbl_raw_data[updated_outcome],"APPROVE",tbl_raw_data[week],H7), IF(AND(flt_queue<>"ALL",flt_analyst<>"ALL"),COUNTIFS(tbl_raw_data[updated_month],flt_month,tbl_raw_data[updated_queue],flt_queue,tbl_raw_data[analyst_name],flt_analyst,tbl_raw_data[updated_outcome],"APPROVE",tbl_raw_data[week],H7), IF(flt_queue="ALL",COUNTIFS(tbl_raw_data[updated_month],flt_month,tbl_raw_data[analyst_name],flt_analyst,tbl_raw_data[updated_outcome],"APPROVE",tbl_raw_data[week],H7), IF(flt_analyst="ALL",COUNTIFS(tbl_raw_data[updated_month],flt_month,tbl_raw_data[updated_queue],flt_queue,tbl_raw_data[updated_outcome],"APPROVE",tbl_raw_data[week],H7))))) / IF(AND(flt_queue="ALL",flt_analyst="ALL"),COUNTIFS(tbl_raw_data[updated_month],flt_month,tbl_raw_data[week],H7), IF(AND(flt_queue<>"ALL",flt_analyst<>"ALL"),COUNTIFS(tbl_raw_data[updated_month],flt_month,tbl_raw_data[updated_queue],flt_queue,tbl_raw_data[analyst_name],flt_analyst,tbl_raw_data[week],H7), IF(flt_queue="ALL",COUNTIFS(tbl_raw_data[updated_month],flt_month,tbl_raw_data[analyst_name],flt_analyst,tbl_raw_data[week],H7), IF(flt_analyst="ALL",COUNTIFS(tbl_raw_data[updated_month],flt_month,tbl_raw_data[updated_queue],flt_queue,tbl_raw_data[week],H7))))),"-") -> 0.59728507 | I8: R: <75% A: 75%-85% G: >85% | K8: =IF(AND(flt_queue="ALL",flt_analyst="ALL"),COUNTIFS(tbl_raw_data[updated_month],flt_month,tbl_raw_data[updated_outcome],"APPROVE"), IF(AND(flt_queue<>"ALL",flt_analyst<>"ALL"),COUNTIFS(tbl_raw_data[updated_month],flt_month,tbl_raw_data[updated_queue],flt_queue,tbl_raw_data[analyst_name],flt_analyst,tbl_raw_data[updated_outcome],"APPROVE"), IF(flt_queue="ALL",COUNTIFS(tbl_raw_data[updated_month],flt_month,tbl_raw_data[analyst_name],flt_analyst,tbl_raw_data[updated_outcome],"APPROVE"), IF(flt_analyst="ALL",COUNTIFS(tbl_raw_data[updated_month],flt_month,tbl_raw_data[updated_queue],flt_queue,tbl_raw_data[updated_outcome],"APPROVE"))))) / IF(AND(flt_queue="ALL",flt_analyst="ALL"),COUNTIFS(tbl_raw_data[updated_month],flt_month), IF(AND(flt_queue<>"ALL",flt_analyst<>"ALL"),COUNTIFS(tbl_raw_data[updated_month],flt_month,tbl_raw_data[updated_queue],flt_queue,tbl_raw_data[analyst_name],flt_analyst), IF(flt_queue="ALL",COUNTIFS(tbl_raw_data[updated_month],flt_month,tbl_raw_data[analyst_name],flt_analyst), IF(flt_analyst="ALL",COUNTIFS(tbl_raw_data[updated_month],flt_month,tbl_raw_data[updated_queue],flt_queue))))) -> 0.56182796 | S8: Incomplete Details | T8: =IF(AND(flt_queue="ALL",flt_analyst="ALL"),COUNTIFS(tbl_raw_data[updated_month],flt_month,tbl_raw_data[updated_message],S8,tbl_raw_data[updated_outcome],"WITHDRAW"), IF(AND(flt_queue<>"ALL",flt_analyst<>"ALL"),COUNTIFS(tbl_raw_data[updated_month],flt_month,tbl_raw_data[updated_queue],flt_queue,tbl_raw_data[analyst_name],flt_analyst,tbl_raw_data[updated_message],S8,tbl_raw_data[updated_outcome],"WITHDRAW"), IF(flt_queue="ALL",COUNTIFS(tbl_raw_data[updated_month],flt_month,tbl_raw_data[analyst_name],flt_analyst,tbl_raw_data[updated_message],S8,tbl_raw_data[updated_outcome],"WITHDRAW"), IF(flt_analyst="ALL",COUNTIFS(tbl_raw_data[updated_month],flt_month,tbl_raw_data[updated_queue],flt_queue,tbl_raw_data[updated_message],S8,tbl_raw_data[updated_outcome],"WITHDRAW"))))) -> 841 | U8: =T8/$T$13 -> 0.52496879
B9: KPI_2 | C9: % of Applications Declined | D9: =IF(OR(E9="-",F9="-"),"-",IF(E9<F9,settings!J3,IF(E9>F9,settings!J2,IF(E9=F9,#REF!)))) -> ↑ | E9: =IFERROR(IF(AND(flt_queue="ALL",flt_analyst="ALL"),COUNTIFS(tbl_raw_data[updated_month],flt_month,tbl_raw_data[updated_outcome],"DECLINE",tbl_raw_data[week],E7), IF(AND(flt_queue<>"ALL",flt_analyst<>"ALL"),COUNTIFS(tbl_raw_data[updated_month],flt_month,tbl_raw_data[updated_queue],flt_queue,tbl_raw_data[analyst_name],flt_analyst,tbl_raw_data[updated_outcome],"DECLINE",tbl_raw_data[week],E7), IF(flt_queue="ALL",COUNTIFS(tbl_raw_data[updated_month],flt_month,tbl_raw_data[analyst_name],flt_analyst,tbl_raw_data[updated_outcome],"DECLINE",tbl_raw_data[week],E7), IF(flt_analyst="ALL",COUNTIFS(tbl_raw_data[updated_month],flt_month,tbl_raw_data[updated_queue],flt_queue,tbl_raw_data[updated_outcome],"DECLINE",tbl_raw_data[week],E7))))) / IF(AND(flt_queue="ALL",flt_analyst="ALL"),COUNTIFS(tbl_raw_data[updated_month],flt_month,tbl_raw_data[week],E7), IF(AND(flt_queue<>"ALL",flt_analyst<>"ALL"),COUNTIFS(tbl_raw_data[updated_month],flt_month,tbl_raw_data[updated_queue],flt_queue,tbl_raw_data[analyst_name],flt_analyst,tbl_raw_data[week],E7), IF(flt_queue="ALL",COUNTIFS(tbl_raw_data[updated_month],flt_month,tbl_raw_data[analyst_name],flt_analyst,tbl_raw_data[week],E7), IF(flt_analyst="ALL",COUNTIFS(tbl_raw_data[updated_month],flt_month,tbl_raw_data[updated_queue],flt_queue,tbl_raw_data[week],E7))))),"-") -> 0.13317479 | F9: =IFERROR(IF(AND(flt_queue="ALL",flt_analyst="ALL"),COUNTIFS(tbl_raw_data[updated_month],flt_month,tbl_raw_data[updated_outcome],"DECLINE",tbl_raw_data[week],F7), IF(AND(flt_queue<>"ALL",flt_analyst<>"ALL"),COUNTIFS(tbl_raw_data[updated_month],flt_month,tbl_raw_data[updated_queue],flt_queue,tbl_raw_data[analyst_name],flt_analyst,tbl_raw_data[updated_outcome],"DECLINE",tbl_raw_data[week],F7), IF(flt_queue="ALL",COUNTIFS(tbl_raw_data[updated_month],flt_month,tbl_raw_data[analyst_name],flt_analyst,tbl_raw_data[updated_outcome],"DECLINE",tbl_raw_data[week],F7), IF(flt_analyst="ALL",COUNTIFS(tbl_raw_data[updated_month],flt_month,tbl_raw_data[updated_queue],flt_queue,tbl_raw_data[updated_outcome],"DECLINE",tbl_raw_data[week],F7))))) / IF(AND(flt_queue="ALL",flt_analyst="ALL"),COUNTIFS(tbl_raw_data[updated_month],flt_month,tbl_raw_data[week],F7), IF(AND(flt_queue<>"ALL",flt_analyst<>"ALL"),COUNTIFS(tbl_raw_data[updated_month],flt_month,tbl_raw_data[updated_queue],flt_queue,tbl_raw_data[analyst_name],flt_analyst,tbl_raw_data[week],F7), IF(flt_queue="ALL",COUNTIFS(tbl_raw_data[updated_month],flt_month,tbl_raw_data[analyst_name],flt_analyst,tbl_raw_data[week],F7), IF(flt_analyst="ALL",COUNTIFS(tbl_raw_data[updated_month],flt_month,tbl_raw_data[updated_queue],flt_queue,tbl_raw_data[week],F7))))),"-") -> 0.15343099 | G9: =IFERROR(IF(AND(flt_queue="ALL",flt_analyst="ALL"),COUNTIFS(tbl_raw_data[updated_month],flt_month,tbl_raw_data[updated_outcome],"DECLINE",tbl_raw_data[week],G7), IF(AND(flt_queue<>"ALL",flt_analyst<>"ALL"),COUNTIFS(tbl_raw_data[updated_month],flt_month,tbl_raw_data[updated_queue],flt_queue,tbl_raw_data[analyst_name],flt_analyst,tbl_raw_data[updated_outcome],"DECLINE",tbl_raw_data[week],G7), IF(flt_queue="ALL",COUNTIFS(tbl_raw_data[updated_month],flt_month,tbl_raw_data[analyst_name],flt_analyst,tbl_raw_data[updated_outcome],"DECLINE",tbl_raw_data[week],G7), IF(flt_analyst="ALL",COUNTIFS(tbl_raw_data[updated_month],flt_month,tbl_raw_data[updated_queue],flt_queue,tbl_raw_data[updated_outcome],"DECLINE",tbl_raw_data[week],G7))))) / IF(AND(flt_queue="ALL",flt_analyst="ALL"),COUNTIFS(tbl_raw_data[updated_month],flt_month,tbl_raw_data[week],G7), IF(AND(flt_queue<>"ALL",flt_analyst<>"ALL"),COUNTIFS(tbl_raw_data[updated_month],flt_month,tbl_raw_data[updated_queue],flt_queue,tbl_raw_data[analyst_name],flt_analyst,tbl_raw_data[week],G7), IF(flt_queue="ALL",COUNTIFS(tbl_raw_data[updated_month],flt_month,tbl_raw_data[analyst_name],flt_analyst,tbl_raw_data[week],G7), IF(flt_analyst="ALL",COUNTIFS(tbl_raw_data[updated_month],flt_month,tbl_raw_data[updated_queue],flt_queue,tbl_raw_data[week],G7))))),"-") -> 0.12 | H9: =IFERROR(IF(AND(flt_queue="ALL",flt_analyst="ALL"),COUNTIFS(tbl_raw_data[updated_month],flt_month,tbl_raw_data[updated_outcome],"DECLINE",tbl_raw_data[week],H7), IF(AND(flt_queue<>"ALL",flt_analyst<>"ALL"),COUNTIFS(tbl_raw_data[updated_month],flt_month,tbl_raw_data[updated_queue],flt_queue,tbl_raw_data[analyst_name],flt_analyst,tbl_raw_data[updated_outcome],"DECLINE",tbl_raw_data[week],H7), IF(flt_queue="ALL",COUNTIFS(tbl_raw_data[updated_month],flt_month,tbl_raw_data[analyst_name],flt_analyst,tbl_raw_data[updated_outcome],"DECLINE",tbl_raw_data[week],H7), IF(flt_analyst="ALL",COUNTIFS(tbl_raw_data[updated_month],flt_month,tbl_raw_data[updated_queue],flt_queue,tbl_raw_data[updated_outcome],"DECLINE",tbl_raw_data[week],H7))))) / IF(AND(flt_queue="ALL",flt_analyst="ALL"),COUNTIFS(tbl_raw_data[updated_month],flt_month,tbl_raw_data[week],H7), IF(AND(flt_queue<>"ALL",flt_analyst<>"ALL"),COUNTIFS(tbl_raw_data[updated_month],flt_month,tbl_raw_data[updated_queue],flt_queue,tbl_raw_data[analyst_name],flt_analyst,tbl_raw_data[week],H7), IF(flt_queue="ALL",COUNTIFS(tbl_raw_data[updated_month],flt_month,tbl_raw_data[analyst_name],flt_analyst,tbl_raw_data[week],H7), IF(flt_analyst="ALL",COUNTIFS(tbl_raw_data[updated_month],flt_month,tbl_raw_data[updated_queue],flt_queue,tbl_raw_data[week],H7))))),"-") -> 0.10708899 | I9: R: >20% A: 10%-20% G: <10% | K9: =IF(AND(flt_queue="ALL",flt_analyst="ALL"),COUNTIFS(tbl_raw_data[updated_month],flt_month,tbl_raw_data[updated_outcome],"DECLINE"), IF(AND(flt_queue<>"ALL",flt_analyst<>"ALL"),COUNTIFS(tbl_raw_data[updated_month],flt_month,tbl_raw_data[updated_queue],flt_queue,tbl_raw_data[analyst_name],flt_analyst,tbl_raw_data[updated_outcome],"DECLINE"), IF(flt_queue="ALL",COUNTIFS(tbl_raw_data[updated_month],flt_month,tbl_raw_data[analyst_name],flt_analyst,tbl_raw_data[updated_outcome],"DECLINE"), IF(flt_analyst="ALL",COUNTIFS(tbl_raw_data[updated_month],flt_month,tbl_raw_data[updated_queue],flt_queue,tbl_raw_data[updated_outcome],"DECLINE"))))) / IF(AND(flt_queue="ALL",flt_analyst="ALL"),COUNTIFS(tbl_raw_data[updated_month],flt_month), IF(AND(flt_queue<>"ALL",flt_analyst<>"ALL"),COUNTIFS(tbl_raw_data[updated_month],flt_month,tbl_raw_data[updated_queue],flt_queue,tbl_raw_data[analyst_name],flt_analyst), IF(flt_queue="ALL",COUNTIFS(tbl_raw_data[updated_month],flt_month,tbl_raw_data[analyst_name],flt_analyst), IF(flt_analyst="ALL",COUNTIFS(tbl_raw_data[updated_month],flt_month,tbl_raw_data[updated_queue],flt_queue))))) -> 0.12867384 | S9: Incorrect Queue | T9: =IF(AND(flt_queue="ALL",flt_analyst="ALL"),COUNTIFS(tbl_raw_data[updated_month],flt_month,tbl_raw_data[updated_message],S9,tbl_raw_data[updated_outcome],"WITHDRAW"), IF(AND(flt_queue<>"ALL",flt_analyst<>"ALL"),COUNTIFS(tbl_raw_data[updated_month],flt_month,tbl_raw_data[updated_queue],flt_queue,tbl_raw_data[analyst_name],flt_analyst,tbl_raw_data[updated_message],S9,tbl_raw_data[updated_outcome],"WITHDRAW"), IF(flt_queue="ALL",COUNTIFS(tbl_raw_data[updated_month],flt_month,tbl_raw_data[analyst_name],flt_analyst,tbl_raw_data[updated_message],S9,tbl_raw_data[updated_outcome],"WITHDRAW"), IF(flt_analyst="ALL",COUNTIFS(tbl_raw_data[updated_month],flt_month,tbl_raw_data[updated_queue],flt_queue,tbl_raw_data[updated_message],S9,tbl_raw_data[updated_outcome],"WITHDRAW"))))) -> 185 | U9: =T9/$T$13 -> 0.11548065 | Y9: \,
B10: KPI_3 | C10: % of Applications Withdrawn | D10: =IF(OR(E10="-",F10="-"),"-",IF(E10>F10,settings!J2,IF(E10<F10,settings!J3,IF(E10=F10,#REF!)))) -> ↑ | E10: =IFERROR(IF(AND(flt_queue="ALL",flt_analyst="ALL"),COUNTIFS(tbl_raw_data[updated_month],flt_month,tbl_raw_data[updated_outcome],"WITHDRAW",tbl_raw_data[week],E7), IF(AND(flt_queue<>"ALL",flt_analyst<>"ALL"),COUNTIFS(tbl_raw_data[updated_month],flt_month,tbl_raw_data[updated_queue],flt_queue,tbl_raw_data[analyst_name],flt_analyst,tbl_raw_data[updated_outcome],"WITHDRAW",tbl_raw_data[week],E7), IF(flt_queue="ALL",COUNTIFS(tbl_raw_data[updated_month],flt_month,tbl_raw_data[analyst_name],flt_analyst,tbl_raw_data[updated_outcome],"WITHDRAW",tbl_raw_data[week],E7), IF(flt_analyst="ALL",COUNTIFS(tbl_raw_data[updated_month],flt_month,tbl_raw_data[updated_queue],flt_queue,tbl_raw_data[updated_outcome],"WITHDRAW",tbl_raw_data[week],E7))))) / IF(AND(flt_queue="ALL",flt_analyst="ALL"),COUNTIFS(tbl_raw_data[updated_month],flt_month,tbl_raw_data[week],E7), IF(AND(flt_queue<>"ALL",flt_analyst<>"ALL"),COUNTIFS(tbl_raw_data[updated_month],flt_month,tbl_raw_data[updated_queue],flt_queue,tbl_raw_data[analyst_name],flt_analyst,tbl_raw_data[week],E7), IF(flt_queue="ALL",COUNTIFS(tbl_raw_data[updated_month],flt_month,tbl_raw_data[analyst_name],flt_analyst,tbl_raw_data[week],E7), IF(flt_analyst="ALL",COUNTIFS(tbl_raw_data[updated_month],flt_month,tbl_raw_data[updated_queue],flt_queue,tbl_raw_data[week],E7))))),"-") -> 0.29667063 | F10: =IFERROR(IF(AND(flt_queue="ALL",flt_analyst="ALL"),COUNTIFS(tbl_raw_data[updated_month],flt_month,tbl_raw_data[updated_outcome],"WITHDRAW",tbl_raw_data[week],F7), IF(AND(flt_queue<>"ALL",flt_analyst<>"ALL"),COUNTIFS(tbl_raw_data[updated_month],flt_month,tbl_raw_data[updated_queue],flt_queue,tbl_raw_data[analyst_name],flt_analyst,tbl_raw_data[updated_outcome],"WITHDRAW",tbl_raw_data[week],F7), IF(flt_queue="ALL",COUNTIFS(tbl_raw_data[updated_month],flt_month,tbl_raw_data[analyst_name],flt_analyst,tbl_raw_data[updated_outcome],"WITHDRAW",tbl_raw_data[week],F7), IF(flt_analyst="ALL",COUNTIFS(tbl_raw_data[updated_month],flt_month,tbl_raw_data[updated_queue],flt_queue,tbl_raw_data[updated_outcome],"WITHDRAW",tbl_raw_data[week],F7))))) / IF(AND(flt_queue="ALL",flt_analyst="ALL"),COUNTIFS(tbl_raw_data[updated_month],flt_month,tbl_raw_data[week],F7), IF(AND(flt_queue<>"ALL",flt_analyst<>"ALL"),COUNTIFS(tbl_raw_data[updated_month],flt_month,tbl_raw_data[updated_queue],flt_queue,tbl_raw_data[analyst_name],flt_analyst,tbl_raw_data[week],F7), IF(flt_queue="ALL",COUNTIFS(tbl_raw_data[updated_month],flt_month,tbl_raw_data[analyst_name],flt_analyst,tbl_raw_data[week],F7), IF(flt_analyst="ALL",COUNTIFS(tbl_raw_data[updated_month],flt_month,tbl_raw_data[updated_queue],flt_queue,tbl_raw_data[week],F7))))),"-") -> 0.31071704 | G10: =IFERROR(IF(AND(flt_queue="ALL",flt_analyst="ALL"),COUNTIFS(tbl_raw_data[updated_month],flt_month,tbl_raw_data[updated_outcome],"WITHDRAW",tbl_raw_data[week],G7), IF(AND(flt_queue<>"ALL",flt_analyst<>"ALL"),COUNTIFS(tbl_raw_data[updated_month],flt_month,tbl_raw_data[updated_queue],flt_queue,tbl_raw_data[analyst_name],flt_analyst,tbl_raw_data[updated_outcome],"WITHDRAW",tbl_raw_data[week],G7), IF(flt_queue="ALL",COUNTIFS(tbl_raw_data[updated_month],flt_month,tbl_raw_data[analyst_name],flt_analyst,tbl_raw_data[updated_outcome],"WITHDRAW",tbl_raw_data[week],G7), IF(flt_analyst="ALL",COUNTIFS(tbl_raw_data[updated_month],flt_month,tbl_raw_data[updated_queue],flt_queue,tbl_raw_data[updated_outcome],"WITHDRAW",tbl_raw_data[week],G7))))) / IF(AND(flt_queue="ALL",flt_analyst="ALL"),COUNTIFS(tbl_raw_data[updated_month],flt_month,tbl_raw_data[week],G7), IF(AND(flt_queue<>"ALL",flt_analyst<>"ALL"),COUNTIFS(tbl_raw_data[updated_month],flt_month,tbl_raw_data[updated_queue],flt_queue,tbl_raw_data[analyst_name],flt_analyst,tbl_raw_data[week],G7), IF(flt_queue="ALL",COUNTIFS(tbl_raw_data[updated_month],flt_month,tbl_raw_data[analyst_name],flt_analyst,tbl_raw_data[week],G7), IF(flt_analyst="ALL",COUNTIFS(tbl_raw_data[updated_month],flt_month,tbl_raw_data[updated_queue],flt_queue,tbl_raw_data[week],G7))))),"-") -> 0.33960784 | H10: =IFERROR(IF(AND(flt_queue="ALL",flt_analyst="ALL"),COUNTIFS(tbl_raw_data[updated_month],flt_month,tbl_raw_data[updated_outcome],"WITHDRAW",tbl_raw_data[week],H7), IF(AND(flt_queue<>"ALL",flt_analyst<>"ALL"),COUNTIFS(tbl_raw_data[updated_month],flt_month,tbl_raw_data[updated_queue],flt_queue,tbl_raw_data[analyst_name],flt_analyst,tbl_raw_data[updated_outcome],"WITHDRAW",tbl_raw_data[week],H7), IF(flt_queue="ALL",COUNTIFS(tbl_raw_data[updated_month],flt_month,tbl_raw_data[analyst_name],flt_analyst,tbl_raw_data[updated_outcome],"WITHDRAW",tbl_raw_data[week],H7), IF(flt_analyst="ALL",COUNTIFS(tbl_raw_data[updated_month],flt_month,tbl_raw_data[updated_queue],flt_queue,tbl_raw_data[updated_outcome],"WITHDRAW",tbl_raw_data[week],H7))))) / IF(AND(flt_queue="ALL",flt_analyst="ALL"),COUNTIFS(tbl_raw_data[updated_month],flt_month,tbl_raw_data[week],H7), IF(AND(flt_queue<>"ALL",flt_analyst<>"ALL"),COUNTIFS(tbl_raw_data[updated_month],flt_month,tbl_raw_data[updated_queue],flt_queue,tbl_raw_data[analyst_name],flt_analyst,tbl_raw_data[week],H7), IF(flt_queue="ALL",COUNTIFS(tbl_raw_data[updated_month],flt_month,tbl_raw_data[analyst_name],flt_analyst,tbl_raw_data[week],H7), IF(flt_analyst="ALL",COUNTIFS(tbl_raw_data[updated_month],flt_month,tbl_raw_data[updated_queue],flt_queue,tbl_raw_data[week],H7))))),"-") -> 0.29562594 | I10: R: >20% A: 10%-20% G: <10% | K10: =IF(AND(flt_queue="ALL",flt_analyst="ALL"),COUNTIFS(tbl_raw_data[updated_month],flt_month,tbl_raw_data[updated_outcome],"WITHDRAW"), IF(AND(flt_queue<>"ALL",flt_analyst<>"ALL"),COUNTIFS(tbl_raw_data[updated_month],flt_month,tbl_raw_data[updated_queue],flt_queue,tbl_raw_data[analyst_name],flt_analyst,tbl_raw_data[updated_outcome],"WITHDRAW"), IF(flt_queue="ALL",COUNTIFS(tbl_raw_data[updated_month],flt_month,tbl_raw_data[analyst_name],flt_analyst,tbl_raw_data[updated_outcome],"WITHDRAW"), IF(flt_analyst="ALL",COUNTIFS(tbl_raw_data[updated_month],flt_month,tbl_raw_data[updated_queue],flt_queue,tbl_raw_data[updated_outcome],"WITHDRAW"))))) / IF(AND(flt_queue="ALL",flt_analyst="ALL"),COUNTIFS(tbl_raw_data[updated_month],flt_month), IF(AND(flt_queue<>"ALL",flt_analyst<>"ALL"),COUNTIFS(tbl_raw_data[updated_month],flt_month,tbl_raw_data[updated_queue],flt_queue,tbl_raw_data[analyst_name],flt_analyst), IF(flt_queue="ALL",COUNTIFS(tbl_raw_data[updated_month],flt_month,tbl_raw_data[analyst_name],flt_analyst), IF(flt_analyst="ALL",COUNTIFS(tbl_raw_data[updated_month],flt_month,tbl_raw_data[updated_queue],flt_queue))))) -> 0.30949821 | S10: System Error | T10: =IF(AND(flt_queue="ALL",flt_analyst="ALL"),COUNTIFS(tbl_raw_data[updated_month],flt_month,tbl_raw_data[updated_message],S10,tbl_raw_data[updated_outcome],"WITHDRAW"), IF(AND(flt_queue<>"ALL",flt_analyst<>"ALL"),COUNTIFS(tbl_raw_data[updated_month],flt_month,tbl_raw_data[updated_queue],flt_queue,tbl_raw_data[analyst_name],flt_analyst,tbl_raw_data[updated_message],S10,tbl_raw_data[updated_outcome],"WITHDRAW"), IF(flt_queue="ALL",COUNTIFS(tbl_raw_data[updated_month],flt_month,tbl_raw_data[analyst_name],flt_analyst,tbl_raw_data[updated_message],S10,tbl_raw_data[updated_outcome],"WITHDRAW"), IF(flt_analyst="ALL",COUNTIFS(tbl_raw_data[updated_month],flt_month,tbl_raw_data[updated_queue],flt_queue,tbl_raw_data[updated_message],S10,tbl_raw_data[updated_outcome],"WITHDRAW"))))) -> 13 | U10: =T10/$T$13 -> 0.0081148564
B11: KPI_4 | C11: % of Applications within SLA (Service Level Agreement) | D11: =IF(OR(E11="-",F11="-"),"-",IF(E11>F11,settings!J3,IF(E11<F11,settings!J2,IF(E11=F11,#REF!)))) -> ↓ | E11: =IFERROR(IF(AND(flt_queue="ALL",flt_analyst="ALL"),COUNTIFS(tbl_raw_data[updated_month],flt_month,tbl_raw_data[sla_met_not_met],"SLA_MET",tbl_raw_data[week],E7), IF(AND(flt_queue<>"ALL",flt_analyst<>"ALL"),COUNTIFS(tbl_raw_data[updated_month],flt_month,tbl_raw_data[updated_queue],flt_queue,tbl_raw_data[analyst_name],flt_analyst,tbl_raw_data[sla_met_not_met],"SLA_MET",tbl_raw_data[week],E7), IF(flt_queue="ALL",COUNTIFS(tbl_raw_data[updated_month],flt_month,tbl_raw_data[analyst_name],flt_analyst,tbl_raw_data[sla_met_not_met],"SLA_MET",tbl_raw_data[week],E7), IF(flt_analyst="ALL",COUNTIFS(tbl_raw_data[updated_month],flt_month,tbl_raw_data[updated_queue],flt_queue,tbl_raw_data[sla_met_not_met],"SLA_MET",tbl_raw_data[week],E7))))) / IF(AND(flt_queue="ALL",flt_analyst="ALL"),COUNTIFS(tbl_raw_data[updated_month],flt_month,tbl_raw_data[week],E7), IF(AND(flt_queue<>"ALL",flt_analyst<>"ALL"),COUNTIFS(tbl_raw_data[updated_month],flt_month,tbl_raw_data[updated_queue],flt_queue,tbl_raw_data[analyst_name],flt_analyst,tbl_raw_data[week],E7), IF(flt_queue="ALL",COUNTIFS(tbl_raw_data[updated_month],flt_month,tbl_raw_data[analyst_name],flt_analyst,tbl_raw_data[week],E7), IF(flt_analyst="ALL",COUNTIFS(tbl_raw_data[updated_month],flt_month,tbl_raw_data[updated_queue],flt_queue,tbl_raw_data[week],E7))))),"-") -> 0.85315101 | F11: =IFERROR(IF(AND(flt_queue="ALL",flt_analyst="ALL"),COUNTIFS(tbl_raw_data[updated_month],flt_month,tbl_raw_data[sla_met_not_met],"SLA_MET",tbl_raw_data[week],F7), IF(AND(flt_queue<>"ALL",flt_analyst<>"ALL"),COUNTIFS(tbl_raw_data[updated_month],flt_month,tbl_raw_data[updated_queue],flt_queue,tbl_raw_data[analyst_name],flt_analyst,tbl_raw_data[sla_met_not_met],"SLA_MET",tbl_raw_data[week],F7), IF(flt_queue="ALL",COUNTIFS(tbl_raw_data[updated_month],flt_month,tbl_raw_data[analyst_name],flt_analyst,tbl_raw_data[sla_met_not_met],"SLA_MET",tbl_raw_data[week],F7), IF(flt_analyst="ALL",COUNTIFS(tbl_raw_data[updated_month],flt_month,tbl_raw_data[updated_queue],flt_queue,tbl_raw_data[sla_met_not_met],"SLA_MET",tbl_raw_data[week],F7))))) / IF(AND(flt_queue="ALL",flt_analyst="ALL"),COUNTIFS(tbl_raw_data[updated_month],flt_month,tbl_raw_data[week],F7), IF(AND(flt_queue<>"ALL",flt_analyst<>"ALL"),COUNTIFS(tbl_raw_data[updated_month],flt_month,tbl_raw_data[updated_queue],flt_queue,tbl_raw_data[analyst_name],flt_analyst,tbl_raw_data[week],F7), IF(flt_queue="ALL",COUNTIFS(tbl_raw_data[updated_month],flt_month,tbl_raw_data[analyst_name],flt_analyst,tbl_raw_data[week],F7), IF(flt_analyst="ALL",COUNTIFS(tbl_raw_data[updated_month],flt_month,tbl_raw_data[updated_queue],flt_queue,tbl_raw_data[week],F7))))),"-") -> 0.88511951 | G11: =IFERROR(IF(AND(flt_queue="ALL",flt_analyst="ALL"),COUNTIFS(tbl_raw_data[updated_month],flt_month,tbl_raw_data[sla_met_not_met],"SLA_MET",tbl_raw_data[week],G7), IF(AND(flt_queue<>"ALL",flt_analyst<>"ALL"),COUNTIFS(tbl_raw_data[updated_month],flt_month,tbl_raw_data[updated_queue],flt_queue,tbl_raw_data[analyst_name],flt_analyst,tbl_raw_data[sla_met_not_met],"SLA_MET",tbl_raw_data[week],G7), IF(flt_queue="ALL",COUNTIFS(tbl_raw_data[updated_month],flt_month,tbl_raw_data[analyst_name],flt_analyst,tbl_raw_data[sla_met_not_met],"SLA_MET",tbl_raw_data[week],G7), IF(flt_analyst="ALL",COUNTIFS(tbl_raw_data[updated_month],flt_month,tbl_raw_data[updated_queue],flt_queue,tbl_raw_data[sla_met_not_met],"SLA_MET",tbl_raw_data[week],G7))))) / IF(AND(flt_queue="ALL",flt_analyst="ALL"),COUNTIFS(tbl_raw_data[updated_month],flt_month,tbl_raw_data[week],G7), IF(AND(flt_queue<>"ALL",flt_analyst<>"ALL"),COUNTIFS(tbl_raw_data[updated_month],flt_month,tbl_raw_data[updated_queue],flt_queue,tbl_raw_data[analyst_name],flt_analyst,tbl_raw_data[week],G7), IF(flt_queue="ALL",COUNTIFS(tbl_raw_data[updated_month],flt_month,tbl_raw_data[analyst_name],flt_analyst,tbl_raw_data[week],G7), IF(flt_analyst="ALL",COUNTIFS(tbl_raw_data[updated_month],flt_month,tbl_raw_data[updated_queue],flt_queue,tbl_raw_data[week],G7))))),"-") -> 0.89803922 | H11: =IFERROR(IF(AND(flt_queue="ALL",flt_analyst="ALL"),COUNTIFS(tbl_raw_data[updated_month],flt_month,tbl_raw_data[sla_met_not_met],"SLA_MET",tbl_raw_data[week],H7), IF(AND(flt_queue<>"ALL",flt_analyst<>"ALL"),COUNTIFS(tbl_raw_data[updated_month],flt_month,tbl_raw_data[updated_queue],flt_queue,tbl_raw_data[analyst_name],flt_analyst,tbl_raw_data[sla_met_not_met],"SLA_MET",tbl_raw_data[week],H7), IF(flt_queue="ALL",COUNTIFS(tbl_raw_data[updated_month],flt_month,tbl_raw_data[analyst_name],flt_analyst,tbl_raw_data[sla_met_not_met],"SLA_MET",tbl_raw_data[week],H7), IF(flt_analyst="ALL",COUNTIFS(tbl_raw_data[updated_month],flt_month,tbl_raw_data[updated_queue],flt_queue,tbl_raw_data[sla_met_not_met],"SLA_MET",tbl_raw_data[week],H7))))) / IF(AND(flt_queue="ALL",flt_analyst="ALL"),COUNTIFS(tbl_raw_data[updated_month],flt_month,tbl_raw_data[week],H7), IF(AND(flt_queue<>"ALL",flt_analyst<>"ALL"),COUNTIFS(tbl_raw_data[updated_month],flt_month,tbl_raw_data[updated_queue],flt_queue,tbl_raw_data[analyst_name],flt_analyst,tbl_raw_data[week],H7), IF(flt_queue="ALL",COUNTIFS(tbl_raw_data[updated_month],flt_month,tbl_raw_data[analyst_name],flt_analyst,tbl_raw_data[week],H7), IF(flt_analyst="ALL",COUNTIFS(tbl_raw_data[updated_month],flt_month,tbl_raw_data[updated_queue],flt_queue,tbl_raw_data[week],H7))))),"-") -> 0.90422323 | I11: R: <80% A: 80%-90% G: >90% | S11: Duplicate Application | T11: =IF(AND(flt_queue="ALL",flt_analyst="ALL"),COUNTIFS(tbl_raw_data[updated_month],flt_month,tbl_raw_data[updated_message],S11,tbl_raw_data[updated_outcome],"WITHDRAW"), IF(AND(flt_queue<>"ALL",flt_analyst<>"ALL"),COUNTIFS(tbl_raw_data[updated_month],flt_month,tbl_raw_data[updated_queue],flt_queue,tbl_raw_data[analyst_name],flt_analyst,tbl_raw_data[updated_message],S11,tbl_raw_data[updated_outcome],"WITHDRAW"), IF(flt_queue="ALL",COUNTIFS(tbl_raw_data[updated_month],flt_month,tbl_raw_data[analyst_name],flt_analyst,tbl_raw_data[updated_message],S11,tbl_raw_data[updated_outcome],"WITHDRAW"), IF(flt_analyst="ALL",COUNTIFS(tbl_raw_data[updated_month],flt_month,tbl_raw_data[updated_queue],flt_queue,tbl_raw_data[updated_message],S11,tbl_raw_data[updated_outcome],"WITHDRAW"))))) -> 34 | U11: =T11/$T$13 -> 0.021223471
B12: KPI_5 | C12: Average handling Time(in min) | D12: =IF(OR(E12="-",F12="-"),"-",IF(E12>F12,settings!J2,IF(E12<F12,settings!J3,IF(E12=F12,settings!J4)))) -> ↑ | E12: =IFERROR(IF(AND(flt_queue="ALL",flt_analyst="ALL"),SUMIFS(tbl_raw_data[time_taken_in_min],tbl_raw_data[updated_month],flt_month,tbl_raw_data[week],E7), IF(AND(flt_queue<>"ALL",flt_analyst<>"ALL"),SUMIFS(tbl_raw_data[time_taken_in_min],tbl_raw_data[updated_month],flt_month,tbl_raw_data[updated_queue],flt_queue,tbl_raw_data[analyst_name],flt_analyst,tbl_raw_data[week],E7), IF(flt_queue="ALL",SUMIFS(tbl_raw_data[time_taken_in_min],tbl_raw_data[updated_month],flt_month,tbl_raw_data[analyst_name],flt_analyst,tbl_raw_data[week],E7), IF(flt_analyst="ALL",SUMIFS(tbl_raw_data[time_taken_in_min],tbl_raw_data[updated_month],flt_month,tbl_raw_data[updated_queue],flt_queue,tbl_raw_data[week],E7))))) / IF(AND(flt_queue="ALL",flt_analyst="ALL"),COUNTIFS(tbl_raw_data[updated_month],flt_month,tbl_raw_data[week],E7), IF(AND(flt_queue<>"ALL",flt_analyst<>"ALL"),COUNTIFS(tbl_raw_data[updated_month],flt_month,tbl_raw_data[updated_queue],flt_queue,tbl_raw_data[analyst_name],flt_analyst,tbl_raw_data[week],E7), IF(flt_queue="ALL",COUNTIFS(tbl_raw_data[updated_month],flt_month,tbl_raw_data[analyst_name],flt_analyst,tbl_raw_data[week],E7), IF(flt_analyst="ALL",COUNTIFS(tbl_raw_data[updated_month],flt_month,tbl_raw_data[updated_queue],flt_queue,tbl_raw_data[week],E7))))),"-") -> 19.627299 | F12: =IFERROR(IF(AND(flt_queue="ALL",flt_analyst="ALL"),SUMIFS(tbl_raw_data[time_taken_in_min],tbl_raw_data[updated_month],flt_month,tbl_raw_data[week],F7), IF(AND(flt_queue<>"ALL",flt_analyst<>"ALL"),SUMIFS(tbl_raw_data[time_taken_in_min],tbl_raw_data[updated_month],flt_month,tbl_raw_data[updated_queue],flt_queue,tbl_raw_data[analyst_name],flt_analyst,tbl_raw_data[week],F7), IF(flt_queue="ALL",SUMIFS(tbl_raw_data[time_taken_in_min],tbl_raw_data[updated_month],flt_month,tbl_raw_data[analyst_name],flt_analyst,tbl_raw_data[week],F7), IF(flt_analyst="ALL",SUMIFS(tbl_raw_data[time_taken_in_min],tbl_raw_data[updated_month],flt_month,tbl_raw_data[updated_queue],flt_queue,tbl_raw_data[week],F7))))) / IF(AND(flt_queue="ALL",flt_analyst="ALL"),COUNTIFS(tbl_raw_data[updated_month],flt_month,tbl_raw_data[week],F7), IF(AND(flt_queue<>"ALL",flt_analyst<>"ALL"),COUNTIFS(tbl_raw_data[updated_month],flt_month,tbl_raw_data[updated_queue],flt_queue,tbl_raw_data[analyst_name],flt_analyst,tbl_raw_data[week],F7), IF(flt_queue="ALL",COUNTIFS(tbl_raw_data[updated_month],flt_month,tbl_raw_data[analyst_name],flt_analyst,tbl_raw_data[week],F7), IF(flt_analyst="ALL",COUNTIFS(tbl_raw_data[updated_month],flt_month,tbl_raw_data[updated_queue],flt_queue,tbl_raw_data[week],F7))))),"-") -> 22.687844 | G12: =IFERROR(IF(AND(flt_queue="ALL",flt_analyst="ALL"),SUMIFS(tbl_raw_data[time_taken_in_min],tbl_raw_data[updated_month],flt_month,tbl_raw_data[week],G7), IF(AND(flt_queue<>"ALL",flt_analyst<>"ALL"),SUMIFS(tbl_raw_data[time_taken_in_min],tbl_raw_data[updated_month],flt_month,tbl_raw_data[updated_queue],flt_queue,tbl_raw_data[analyst_name],flt_analyst,tbl_raw_data[week],G7), IF(flt_queue="ALL",SUMIFS(tbl_raw_data[time_taken_in_min],tbl_raw_data[updated_month],flt_month,tbl_raw_data[analyst_name],flt_analyst,tbl_raw_data[week],G7), IF(flt_analyst="ALL",SUMIFS(tbl_raw_data[time_taken_in_min],tbl_raw_data[updated_month],flt_month,tbl_raw_data[updated_queue],flt_queue,tbl_raw_data[week],G7))))) / IF(AND(flt_queue="ALL",flt_analyst="ALL"),COUNTIFS(tbl_raw_data[updated_month],flt_month,tbl_raw_data[week],G7), IF(AND(flt_queue<>"ALL",flt_analyst<>"ALL"),COUNTIFS(tbl_raw_data[updated_month],flt_month,tbl_raw_data[updated_queue],flt_queue,tbl_raw_data[analyst_name],flt_analyst,tbl_raw_data[week],G7), IF(flt_queue="ALL",COUNTIFS(tbl_raw_data[updated_month],flt_month,tbl_raw_data[analyst_name],flt_analyst,tbl_raw_data[week],G7), IF(flt_analyst="ALL",COUNTIFS(tbl_raw_data[updated_month],flt_month,tbl_raw_data[updated_queue],flt_queue,tbl_raw_data[week],G7))))),"-") -> 25.036183 | H12: =IFERROR(IF(AND(flt_queue="ALL",flt_analyst="ALL"),SUMIFS(tbl_raw_data[time_taken_in_min],tbl_raw_data[updated_month],flt_month,tbl_raw_data[week],H7), IF(AND(flt_queue<>"ALL",flt_analyst<>"ALL"),SUMIFS(tbl_raw_data[time_taken_in_min],tbl_raw_data[updated_month],flt_month,tbl_raw_data[updated_queue],flt_queue,tbl_raw_data[analyst_name],flt_analyst,tbl_raw_data[week],H7), IF(flt_queue="ALL",SUMIFS(tbl_raw_data[time_taken_in_min],tbl_raw_data[updated_month],flt_month,tbl_raw_data[analyst_name],flt_analyst,tbl_raw_data[week],H7), IF(flt_analyst="ALL",SUMIFS(tbl_raw_data[time_taken_in_min],tbl_raw_data[updated_month],flt_month,tbl_raw_data[updated_queue],flt_queue,tbl_raw_data[week],H7))))) / IF(AND(flt_queue="ALL",flt_analyst="ALL"),COUNTIFS(tbl_raw_data[updated_month],flt_month,tbl_raw_data[week],H7), IF(AND(flt_queue<>"ALL",flt_analyst<>"ALL"),COUNTIFS(tbl_raw_data[updated_month],flt_month,tbl_raw_data[updated_queue],flt_queue,tbl_raw_data[analyst_name],flt_analyst,tbl_raw_data[week],H7), IF(flt_queue="ALL",COUNTIFS(tbl_raw_data[updated_month],flt_month,tbl_raw_data[analyst_name],flt_analyst,tbl_raw_data[week],H7), IF(flt_analyst="ALL",COUNTIFS(tbl_raw_data[updated_month],flt_month,tbl_raw_data[updated_queue],flt_queue,tbl_raw_data[week],H7))))),"-") -> 19.166051 | I12: R: >25 A: 20-25 G: <20 | S12: Reason Unknown | T12: =IF(AND(flt_queue="ALL",flt_analyst="ALL"),COUNTIFS(tbl_raw_data[updated_month],flt_month,tbl_raw_data[updated_message],S12,tbl_raw_data[updated_outcome],"WITHDRAW"), IF(AND(flt_queue<>"ALL",flt_analyst<>"ALL"),COUNTIFS(tbl_raw_data[updated_month],flt_month,tbl_raw_data[updated_queue],flt_queue,tbl_raw_data[analyst_name],flt_analyst,tbl_raw_data[updated_message],S12,tbl_raw_data[updated_outcome],"WITHDRAW"), IF(flt_queue="ALL",COUNTIFS(tbl_raw_data[updated_month],flt_month,tbl_raw_data[analyst_name],flt_analyst,tbl_raw_data[updated_message],S12,tbl_raw_data[updated_outcome],"WITHDRAW"), IF(flt_analyst="ALL",COUNTIFS(tbl_raw_data[updated_month],flt_month,tbl_raw_data[updated_queue],flt_queue,tbl_raw_data[updated_message],S12,tbl_raw_data[updated_outcome],"WITHDRAW"))))) -> 373 | U12: =T12/$T$13 -> 0.23283396
B13: KPI_6 | C13: # of Applications Handled | D13: =IF(OR(E13=0,F13=0),"-",IF(E13>F13,settings!J3,IF(E13<F13,settings!J2,IF(E13=F13,settings!J4)))) -> ↑ | E13: =IF(AND(flt_queue="ALL",flt_analyst="ALL"),COUNTIFS(tbl_raw_data[updated_month],flt_month,tbl_raw_data[week],E7), IF(AND(flt_queue<>"ALL",flt_analyst<>"ALL"),COUNTIFS(tbl_raw_data[updated_month],flt_month,tbl_raw_data[updated_queue],flt_queue,tbl_raw_data[analyst_name],flt_analyst,tbl_raw_data[week],E7), IF(flt_queue="ALL",COUNTIFS(tbl_raw_data[updated_month],flt_month,tbl_raw_data[analyst_name],flt_analyst,tbl_raw_data[week],E7), IF(flt_analyst="ALL",COUNTIFS(tbl_raw_data[updated_month],flt_month,tbl_raw_data[updated_queue],flt_queue,tbl_raw_data[week],E7))))) -> 1682 | F13: =IF(AND(flt_queue="ALL",flt_analyst="ALL"),COUNTIFS(tbl_raw_data[updated_month],flt_month,tbl_raw_data[week],F7), IF(AND(flt_queue<>"ALL",flt_analyst<>"ALL"),COUNTIFS(tbl_raw_data[updated_month],flt_month,tbl_raw_data[updated_queue],flt_queue,tbl_raw_data[analyst_name],flt_analyst,tbl_raw_data[week],F7), IF(flt_queue="ALL",COUNTIFS(tbl_raw_data[updated_month],flt_month,tbl_raw_data[analyst_name],flt_analyst,tbl_raw_data[week],F7), IF(flt_analyst="ALL",COUNTIFS(tbl_raw_data[updated_month],flt_month,tbl_raw_data[updated_queue],flt_queue,tbl_raw_data[week],F7))))) -> 1297 | G13: =IF(AND(flt_queue="ALL",flt_analyst="ALL"),COUNTIFS(tbl_raw_data[updated_month],flt_month,tbl_raw_data[week],G7), IF(AND(flt_queue<>"ALL",flt_analyst<>"ALL"),COUNTIFS(tbl_raw_data[updated_month],flt_month,tbl_raw_data[updated_queue],flt_queue,tbl_raw_data[analyst_name],flt_analyst,tbl_raw_data[week],G7), IF(flt_queue="ALL",COUNTIFS(tbl_raw_data[updated_month],flt_month,tbl_raw_data[analyst_name],flt_analyst,tbl_raw_data[week],G7), IF(flt_analyst="ALL",COUNTIFS(tbl_raw_data[updated_month],flt_month,tbl_raw_data[updated_queue],flt_queue,tbl_raw_data[week],G7))))) -> 1275 | H13: =IF(AND(flt_queue="ALL",flt_analyst="ALL"),COUNTIFS(tbl_raw_data[updated_month],flt_month,tbl_raw_data[week],H7), IF(AND(flt_queue<>"ALL",flt_analyst<>"ALL"),COUNTIFS(tbl_raw_data[updated_month],flt_month,tbl_raw_data[updated_queue],flt_queue,tbl_raw_data[analyst_name],flt_analyst,tbl_raw_data[week],H7), IF(flt_queue="ALL",COUNTIFS(tbl_raw_data[updated_month],flt_month,tbl_raw_data[analyst_name],flt_analyst,tbl_raw_data[week],H7), IF(flt_analyst="ALL",COUNTIFS(tbl_raw_data[updated_month],flt_month,tbl_raw_data[updated_queue],flt_queue,tbl_raw_data[week],H7))))) -> 1326 | I13: See Notes (1) | K13: =IF(AND(flt_queue="ALL",flt_analyst="ALL"),COUNTIFS(tbl_raw_data[updated_month],flt_month), IF(AND(flt_queue<>"ALL",flt_analyst<>"ALL"),COUNTIFS(tbl_raw_data[updated_month],flt_month,tbl_raw_data[updated_queue],flt_queue,tbl_raw_data[analyst_name],flt_analyst), IF(flt_queue="ALL",COUNTIFS(tbl_raw_data[updated_month],flt_month,tbl_raw_data[analyst_name],flt_analyst), IF(flt_analyst="ALL",COUNTIFS(tbl_raw_data[updated_month],flt_month,tbl_raw_data[updated_queue],flt_queue))))) -> 5580 | S13: Total | T13: =SUM(T7:T12) -> 1602
S16: Notes:
S17: (1) Thresholds are Not Applicable as they can be different at the Team Level & Analyst Level. Data bars are added to help compare the values between weeks. The higher the value, the longer the bar.
S18: (2) Top 40 (by Rank) Reasons are marked in Light Red Background with Red Font.
S19: (3) Applications Data is available for analysis only from 29th July.

Sheet raw_data
A1: Application_ID | B1: Date Tagged | C1: Date Actioned | D1: Outcome | E1: Queue Name | F1: Analyst | G1: Message | H1: updated_message | I1: time_taken | J1: time_taken_in_min | K1: updated_date | L1: updated_month | M1: week | N1: analyst_name | O1: updated_outcome | P1: updated_queue | Q1: sla_met_not_met
A2: 1 | B2: 45137.004 | C2: 45137.392 | D2: Approve | E2: Consumer Post Bureau | F2: QMascarenhas | H2: =IF(OR(ISNUMBER(SEARCH("duplicate",G2)), ISNUMBER(SEARCH("previously",G2)), ISNUMBER(SEARCH("previously approved",G2))), "Duplicate Application", IF(OR(ISNUMBER(SEARCH("incorrect",G2)), ISNUMBER(SEARCH("remove", G2))), "Incorrect Details", IF(ISNUMBER(SEARCH("incomplete",G2)), "Incomplete Details", IF(ISNUMBER(SEARCH("overdue",G2)), "Overdue Bill", IF(OR(ISNUMBER(SEARCH("resubmit as", G2)), ISNUMBER(SEARCH("re-submit as", G2))), "Incorrect Queue", IF(OR(ISNUMBER(SEARCH("100",G2)), ISNUMBER(SEARCH("correct", G2)), ISNUMBER(SEARCH("email", G2)), ISNUMBER(SEARCH("please submit", G2)), ISNUMBER(SEARCH("please resubmit",G2)), ISNUMBER(SEARCH("please re-submit", G2)), ISNUMBER(SEARCH("please send", G2))), "Incomplete Details", IF(ISNUMBER(SEARCH("error", G2)), "System Error", "Reason Unknown"))))))) -> Reason Unknown | I2: =(tbl_raw_data[[#This Row],[Date Actioned]])-(tbl_raw_data[[#This Row],[Date Tagged]]) -> 0.388125 | J2: =HOUR(tbl_raw_data[[#This Row],[time_taken]])*60+MINUTE(tbl_raw_data[[#This Row],[time_taken]])+SECOND(tbl_raw_data[[#This Row],[time_taken]])/60 -> 558.9 | K2: =DATE(YEAR(tbl_raw_data[[#This Row],[Date Actioned]]),MONTH(tbl_raw_data[[#This Row],[Date Actioned]]),DAY(tbl_raw_data[[#This Row],[Date Actioned]])) -> 45137 | L2: =UPPER(TEXT(tbl_raw_data[[#This Row],[updated_date]],"MMMM")) -> JULY | M2: ="WEEK "&IF(ROUNDUP(DAY(tbl_raw_data[[#This Row],[updated_date]])/7,0)=5,4,ROUNDUP(DAY(tbl_raw_data[[#This Row],[updated_date]])/7,0)) -> WEEK 4 | N2: =UPPER(VLOOKUP(tbl_raw_data[[#This Row],[Analyst]],settings!$A$1:$B$15,2,0)) -> QUADIR | O2: =TRIM(UPPER(tbl_raw_data[[#This Row],[Outcome]])) -> APPROVE | P2: =TRIM(UPPER(tbl_raw_data[[#This Row],[Queue Name]])) -> CONSUMER POST BUREAU | Q2: =IF(tbl_raw_data[[#This Row],[time_taken_in_min]]<=settings!$D$2,"SLA_MET","SLA_NOT_MET") -> SLA_NOT_MET
A3: 2 | B3: 45137.387 | C3: 45137.397 | D3: APPROVE | E3: Consumer Existing | F3: NBhatia | G3: Conditionally Approved, if the Customer goes on Direct Debit mode of Payment and pays off the outstanding balance due for $129.29 | H3: =IF(OR(ISNUMBER(SEARCH("duplicate",G3)), ISNUMBER(SEARCH("previously",G3)), ISNUMBER(SEARCH("previously approved",G3))), "Duplicate Application", IF(OR(ISNUMBER(SEARCH("incorrect",G3)), ISNUMBER(SEARCH("remove", G3))), "Incorrect Details", IF(ISNUMBER(SEARCH("incomplete",G3)), "Incomplete Details", IF(ISNUMBER(SEARCH("overdue",G3)), "Overdue Bill", IF(OR(ISNUMBER(SEARCH("resubmit as", G3)), ISNUMBER(SEARCH("re-submit as", G3))), "Incorrect Queue", IF(OR(ISNUMBER(SEARCH("100",G3)), ISNUMBER(SEARCH("correct", G3)), ISNUMBER(SEARCH("email", G3)), ISNUMBER(SEARCH("please submit", G3)), ISNUMBER(SEARCH("please resubmit",G3)), ISNUMBER(SEARCH("please re-submit", G3)), ISNUMBER(SEARCH("please send", G3))), "Incomplete Details", IF(ISNUMBER(SEARCH("error", G3)), "System Error", "Reason Unknown"))))))) -> Reason Unknown | I3: =(tbl_raw_data[[#This Row],[Date Actioned]])-(tbl_raw_data[[#This Row],[Date Tagged]]) -> 0.010150463 | J3: =HOUR(tbl_raw_data[[#This Row],[time_taken]])*60+MINUTE(tbl_raw_data[[#This Row],[time_taken]])+SECOND(tbl_raw_data[[#This Row],[time_taken]])/60 -> 14.616667 | K3: =DATE(YEAR(tbl_raw_data[[#This Row],[Date Actioned]]),MONTH(tbl_raw_data[[#This Row],[Date Actioned]]),DAY(tbl_raw_data[[#This Row],[Date Actioned]])) -> 45137 | L3: =UPPER(TEXT(tbl_raw_data[[#This Row],[updated_date]],"MMMM")) -> JULY | M3: ="WEEK "&IF(ROUNDUP(DAY(tbl_raw_data[[#This Row],[updated_date]])/7,0)=5,4,ROUNDUP(DAY(tbl_raw_data[[#This Row],[updated_date]])/7,0)) -> WEEK 4 | N3: =UPPER(VLOOKUP(tbl_raw_data[[#This Row],[Analyst]],settings!$A$1:$B$15,2,0)) -> NITESH | O3: =TRIM(UPPER(tbl_raw_data[[#This Row],[Outcome]])) -> APPROVE | P3: =TRIM(UPPER(tbl_raw_data[[#This Row],[Queue Name]])) -> CONSUMER EXISTING | Q3: =IF(tbl_raw_data[[#This Row],[time_taken_in_min]]<=settings!$D$2,"SLA_MET","SLA_NOT_MET") -> SLA_MET
A4: 3 | B4: 45137.395 | C4: 45137.407 | D4: APPROVE | E4: Consumer Existing | F4: CDcosta | G4: Approve | H4: =IF(OR(ISNUMBER(SEARCH("duplicate",G4)), ISNUMBER(SEARCH("previously",G4)), ISNUMBER(SEARCH("previously approved",G4))), "Duplicate Application", IF(OR(ISNUMBER(SEARCH("incorrect",G4)), ISNUMBER(SEARCH("remove", G4))), "Incorrect Details", IF(ISNUMBER(SEARCH("incomplete",G4)), "Incomplete Details", IF(ISNUMBER(SEARCH("overdue",G4)), "Overdue Bill", IF(OR(ISNUMBER(SEARCH("resubmit as", G4)), ISNUMBER(SEARCH("re-submit as", G4))), "Incorrect Queue", IF(OR(ISNUMBER(SEARCH("100",G4)), ISNUMBER(SEARCH("correct", G4)), ISNUMBER(SEARCH("email", G4)), ISNUMBER(SEARCH("please submit", G4)), ISNUMBER(SEARCH("please resubmit",G4)), ISNUMBER(SEARCH("please re-submit", G4)), ISNUMBER(SEARCH("please send", G4))), "Incomplete Details", IF(ISNUMBER(SEARCH("error", G4)), "System Error", "Reason Unknown"))))))) -> Reason Unknown | I4: =(tbl_raw_data[[#This Row],[Date Actioned]])-(tbl_raw_data[[#This Row],[Date Tagged]]) -> 0.011759259 | J4: =HOUR(tbl_raw_data[[#This Row],[time_taken]])*60+MINUTE(tbl_raw_data[[#This Row],[time_taken]])+SECOND(tbl_raw_data[[#This Row],[time_taken]])/60 -> 16.933333 | K4: =DATE(YEAR(tbl_raw_data[[#This Row],[Date Actioned]]),MONTH(tbl_raw_data[[#This Row],[Date Actioned]]),DAY(tbl_raw_data[[#This Row],[Date Actioned]])) -> 45137 | L4: =UPPER(TEXT(tbl_raw_data[[#This Row],[updated_date]],"MMMM")) -> JULY | M4: ="WEEK "&IF(ROUNDUP(DAY(tbl_raw_data[[#This Row],[updated_date]])/7,0)=5,4,ROUNDUP(DAY(tbl_raw_data[[#This Row],[updated_date]])/7,0)) -> WEEK 4 | N4: =UPPER(VLOOKUP(tbl_raw_data[[#This Row],[Analyst]],settings!$A$1:$B$15,2,0)) -> CAMROON | O4: =TRIM(UPPER(tbl_raw_data[[#This Row],[Outcome]])) -> APPROVE | P4: =TRIM(UPPER(tbl_raw_data[[#This Row],[Queue Name]])) -> CONSUMER EXISTING | Q4: =IF(tbl_raw_data[[#This Row],[time_taken_in_min]]<=settings!$D$2,"SLA_MET","SLA_NOT_MET") -> SLA_MET
A5: 4 | B5: 45137.401 | C5: 45137.409 | D5: Approve | E5: Consumer Existing | F5: QMascarenhas | H5: =IF(OR(ISNUMBER(SEARCH("duplicate",G5)), ISNUMBER(SEARCH("previously",G5)), ISNUMBER(SEARCH("previously approved",G5))), "Duplicate Application", IF(OR(ISNUMBER(SEARCH("incorrect",G5)), ISNUMBER(SEARCH("remove", G5))), "Incorrect Details", IF(ISNUMBER(SEARCH("incomplete",G5)), "Incomplete Details", IF(ISNUMBER(SEARCH("overdue",G5)), "Overdue Bill", IF(OR(ISNUMBER(SEARCH("resubmit as", G5)), ISNUMBER(SEARCH("re-submit as", G5))), "Incorrect Queue", IF(OR(ISNUMBER(SEARCH("100",G5)), ISNUMBER(SEARCH("correct", G5)), ISNUMBER(SEARCH("email", G5)), ISNUMBER(SEARCH("please submit", G5)), ISNUMBER(SEARCH("please resubmit",G5)), ISNUMBER(SEARCH("please re-submit", G5)), ISNUMBER(SEARCH("please send", G5))), "Incomplete Details", IF(ISNUMBER(SEARCH("error", G5)), "System Error", "Reason Unknown"))))))) -> Reason Unknown | I5: =(tbl_raw_data[[#This Row],[Date Actioned]])-(tbl_raw_data[[#This Row],[Date Tagged]]) -> 0.0085532407 | J5: =HOUR(tbl_raw_data[[#This Row],[time_taken]])*60+MINUTE(tbl_raw_data[[#This Row],[time_taken]])+SECOND(tbl_raw_data[[#This Row],[time_taken]])/60 -> 12.316667 | K5: =DATE(YEAR(tbl_raw_data[[#This Row],[Date Actioned]]),MONTH(tbl_raw_data[[#This Row],[Date Actioned]]),DAY(tbl_raw_data[[#This Row],[Date Actioned]])) -> 45137 | L5: =UPPER(TEXT(tbl_raw_data[[#This Row],[updated_date]],"MMMM")) -> JULY | M5: ="WEEK "&IF(ROUNDUP(DAY(tbl_raw_data[[#This Row],[updated_date]])/7,0)=5,4,ROUNDUP(DAY(tbl_raw_data[[#This Row],[updated_date]])/7,0)) -> WEEK 4 | N5: =UPPER(VLOOKUP(tbl_raw_data[[#This Row],[Analyst]],settings!$A$1:$B$15,2,0)) -> QUADIR | O5: =TRIM(UPPER(tbl_raw_data[[#This Row],[Outcome]])) -> APPROVE | P5: =TRIM(UPPER(tbl_raw_data[[#This Row],[Queue Name]])) -> CONSUMER EXISTING | Q5: =IF(tbl_raw_data[[#This Row],[time_taken_in_min]]<=settings!$D$2,"SLA_MET","SLA_NOT_MET") -> SLA_MET
A6: 5 | B6: 45137.403 | C6: 45137.415 | D6: APPROVE | E6: Consumer Existing | F6: CDcosta | G6: Approve | H6: =IF(OR(ISNUMBER(SEARCH("duplicate",G6)), ISNUMBER(SEARCH("previously",G6)), ISNUMBER(SEARCH("previously approved",G6))), "Duplicate Application", IF(OR(ISNUMBER(SEARCH("incorrect",G6)), ISNUMBER(SEARCH("remove", G6))), "Incorrect Details", IF(ISNUMBER(SEARCH("incomplete",G6)), "Incomplete Details", IF(ISNUMBER(SEARCH("overdue",G6)), "Overdue Bill", IF(OR(ISNUMBER(SEARCH("resubmit as", G6)), ISNUMBER(SEARCH("re-submit as", G6))), "Incorrect Queue", IF(OR(ISNUMBER(SEARCH("100",G6)), ISNUMBER(SEARCH("correct", G6)), ISNUMBER(SEARCH("email", G6)), ISNUMBER(SEARCH("please submit", G6)), ISNUMBER(SEARCH("please resubmit",G6)), ISNUMBER(SEARCH("please re-submit", G6)), ISNUMBER(SEARCH("please send", G6))), "Incomplete Details", IF(ISNUMBER(SEARCH("error", G6)), "System Error", "Reason Unknown"))))))) -> Reason Unknown | I6: =(tbl_raw_data[[#This Row],[Date Actioned]])-(tbl_raw_data[[#This Row],[Date Tagged]]) -> 0.011944444 | J6: =HOUR(tbl_raw_data[[#This Row],[time_taken]])*60+MINUTE(tbl_raw_data[[#This Row],[time_taken]])+SECOND(tbl_raw_data[[#This Row],[time_taken]])/60 -> 17.2 | K6: =DATE(YEAR(tbl_raw_data[[#This Row],[Date Actioned]]),MONTH(tbl_raw_data[[#This Row],[Date Actioned]]),DAY(tbl_raw_data[[#This Row],[Date Actioned]])) -> 45137 | L6: =UPPER(TEXT(tbl_raw_data[[#This Row],[updated_date]],"MMMM")) -> JULY | M6: ="WEEK "&IF(ROUNDUP(DAY(tbl_raw_data[[#This Row],[updated_date]])/7,0)=5,4,ROUNDUP(DAY(tbl_raw_data[[#This Row],[updated_date]])/7,0)) -> WEEK 4 | N6: =UPPER(VLOOKUP(tbl_raw_data[[#This Row],[Analyst]],settings!$A$1:$B$15,2,0)) -> CAMROON | O6: =TRIM(UPPER(tbl_raw_data[[#This Row],[Outcome]])) -> APPROVE | P6: =TRIM(UPPER(tbl_raw_data[[#This Row],[Queue Name]])) -> CONSUMER EXISTING | Q6: =IF(tbl_raw_data[[#This Row],[time_taken_in_min]]<=settings!$D$2,"SLA_MET","SLA_NOT_MET") -> SLA_MET
A7: 6 | B7: 45137.406 | C7: 45137.414 | D7: Approve | E7: Consumer Post Bureau | F7: QMascarenhas | H7: =IF(OR(ISNUMBER(SEARCH("duplicate",G7)), ISNUMBER(SEARCH("previously",G7)), ISNUMBER(SEARCH("previously approved",G7))), "Duplicate Application", IF(OR(ISNUMBER(SEARCH("incorrect",G7)), ISNUMBER(SEARCH("remove", G7))), "Incorrect Details", IF(ISNUMBER(SEARCH("incomplete",G7)), "Incomplete Details", IF(ISNUMBER(SEARCH("overdue",G7)), "Overdue Bill", IF(OR(ISNUMBER(SEARCH("resubmit as", G7)), ISNUMBER(SEARCH("re-submit as", G7))), "Incorrect Queue", IF(OR(ISNUMBER(SEARCH("100",G7)), ISNUMBER(SEARCH("correct", G7)), ISNUMBER(SEARCH("email", G7)), ISNUMBER(SEARCH("please submit", G7)), ISNUMBER(SEARCH("please resubmit",G7)), ISNUMBER(SEARCH("please re-submit", G7)), ISNUMBER(SEARCH("please send", G7))), "Incomplete Details", IF(ISNUMBER(SEARCH("error", G7)), "System Error", "Reason Unknown"))))))) -> Reason Unknown | I7: =(tbl_raw_data[[#This Row],[Date Actioned]])-(tbl_raw_data[[#This Row],[Date Tagged]]) -> 0.0082175926 | J7: =HOUR(tbl_raw_data[[#This Row],[time_taken]])*60+MINUTE(tbl_raw_data[[#This Row],[time_taken]])+SECOND(tbl_raw_data[[#This Row],[time_taken]])/60 -> 11.833333 | K7: =DATE(YEAR(tbl_raw_data[[#This Row],[Date Actioned]]),MONTH(tbl_raw_data[[#This Row],[Date Actioned]]),DAY(tbl_raw_data[[#This Row],[Date Actioned]])) -> 45137 | L7: =UPPER(TEXT(tbl_raw_data[[#This Row],[updated_date]],"MMMM")) -> JULY | M7: ="WEEK "&IF(ROUNDUP(DAY(tbl_raw_data[[#This Row],[updated_date]])/7,0)=5,4,ROUNDUP(DAY(tbl_raw_data[[#This Row],[updated_date]])/7,0)) -> WEEK 4 | N7: =UPPER(VLOOKUP(tbl_raw_data[[#This Row],[Analyst]],settings!$A$1:$B$15,2,0)) -> QUADIR | O7: =TRIM(UPPER(tbl_raw_data[[#This Row],[Outcome]])) -> APPROVE | P7: =TRIM(UPPER(tbl_raw_data[[#This Row],[Queue Name]])) -> CONSUMER POST BUREAU | Q7: =IF(tbl_raw_data[[#This Row],[time_taken_in_min]]<=settings!$D$2,"SLA_MET","SLA_NOT_MET") -> SLA_MET
A8: 7 | B8: 45137.419 | C8: 45137.428 | D8: Approve | E8: Consumer Existing | F8: QMascarenhas | H8: =IF(OR(ISNUMBER(SEARCH("duplicate",G8)), ISNUMBER(SEARCH("previously",G8)), ISNUMBER(SEARCH("previously approved",G8))), "Duplicate Application", IF(OR(ISNUMBER(SEARCH("incorrect",G8)), ISNUMBER(SEARCH("remove", G8))), "Incorrect Details", IF(ISNUMBER(SEARCH("incomplete",G8)), "Incomplete Details", IF(ISNUMBER(SEARCH("overdue",G8)), "Overdue Bill", IF(OR(ISNUMBER(SEARCH("resubmit as", G8)), ISNUMBER(SEARCH("re-submit as", G8))), "Incorrect Queue", IF(OR(ISNUMBER(SEARCH("100",G8)), ISNUMBER(SEARCH("correct", G8)), ISNUMBER(SEARCH("email", G8)), ISNUMBER(SEARCH("please submit", G8)), ISNUMBER(SEARCH("please resubmit",G8)), ISNUMBER(SEARCH("please re-submit", G8)), ISNUMBER(SEARCH("please send", G8))), "Incomplete Details", IF(ISNUMBER(SEARCH("error", G8)), "System Error", "Reason Unknown"))))))) -> Reason Unknown | I8: =(tbl_raw_data[[#This Row],[Date Actioned]])-(tbl_raw_data[[#This Row],[Date Tagged]]) -> 0.0092824074 | J8: =HOUR(tbl_raw_data[[#This Row],[time_taken]])*60+MINUTE(tbl_raw_data[[#This Row],[time_taken]])+SECOND(tbl_raw_data[[#This Row],[time_taken]])/60 -> 13.366667 | K8: =DATE(YEAR(tbl_raw_data[[#This Row],[Date Actioned]]),MONTH(tbl_raw_data[[#This Row],[Date Actioned]]),DAY(tbl_raw_data[[#This Row],[Date Actioned]])) -> 45137 | L8: =UPPER(TEXT(tbl_raw_data[[#This Row],[updated_date]],"MMMM")) -> JULY | M8: ="WEEK "&IF(ROUNDUP(DAY(tbl_raw_data[[#This Row],[updated_date]])/7,0)=5,4,ROUNDUP(DAY(tbl_raw_data[[#This Row],[updated_date]])/7,0)) -> WEEK 4 | N8: =UPPER(VLOOKUP(tbl_raw_data[[#This Row],[Analyst]],settings!$A$1:$B$15,2,0)) -> QUADIR | O8: =TRIM(UPPER(tbl_raw_data[[#This Row],[Outcome]])) -> APPROVE | P8: =TRIM(UPPER(tbl_raw_data[[#This Row],[Queue Name]])) -> CONSUMER EXISTING | Q8: =IF(tbl_raw_data[[#This Row],[time_taken_in_min]]<=settings!$D$2,"SLA_MET","SLA_NOT_MET") -> SLA_MET
A9: 8 | B9: 45137.434 | C9: 45137.443 | D9: APPROVE | E9: Consumer Post Bureau | F9: CDcosta | G9: Approved for 1 handset and 1 MBB | H9: =IF(OR(ISNUMBER(SEARCH("duplicate",G9)), ISNUMBER(SEARCH("previously",G9)), ISNUMBER(SEARCH("previously approved",G9))), "Duplicate Application", IF(OR(ISNUMBER(SEARCH("incorrect",G9)), ISNUMBER(SEARCH("remove", G9))), "Incorrect Details", IF(ISNUMBER(SEARCH("incomplete",G9)), "Incomplete Details", IF(ISNUMBER(SEARCH("overdue",G9)), "Overdue Bill", IF(OR(ISNUMBER(SEARCH("resubmit as", G9)), ISNUMBER(SEARCH("re-submit as", G9))), "Incorrect Queue", IF(OR(ISNUMBER(SEARCH("100",G9)), ISNUMBER(SEARCH("correct", G9)), ISNUMBER(SEARCH("email", G9)), ISNUMBER(SEARCH("please submit", G9)), ISNUMBER(SEARCH("please resubmit",G9)), ISNUMBER(SEARCH("please re-submit", G9)), ISNUMBER(SEARCH("please send", G9))), "Incomplete Details", IF(ISNUMBER(SEARCH("error", G9)), "System Error", "Reason Unknown"))))))) -> Reason Unknown | I9: =(tbl_raw_data[[#This Row],[Date Actioned]])-(tbl_raw_data[[#This Row],[Date Tagged]]) -> 0.0090509259 | J9: =HOUR(tbl_raw_data[[#This Row],[time_taken]])*60+MINUTE(tbl_raw_data[[#This Row],[time_taken]])+SECOND(tbl_raw_data[[#This Row],[time_taken]])/60 -> 13.033333 | K9: =DATE(YEAR(tbl_raw_data[[#This Row],[Date Actioned]]),MONTH(tbl_raw_data[[#This Row],[Date Actioned]]),DAY(tbl_raw_data[[#This Row],[Date Actioned]])) -> 45137 | L9: =UPPER(TEXT(tbl_raw_data[[#This Row],[updated_date]],"MMMM")) -> JULY | M9: ="WEEK "&IF(ROUNDUP(DAY(tbl_raw_data[[#This Row],[updated_date]])/7,0)=5,4,ROUNDUP(DAY(tbl_raw_data[[#This Row],[updated_date]])/7,0)) -> WEEK 4 | N9: =UPPER(VLOOKUP(tbl_raw_data[[#This Row],[Analyst]],settings!$A$1:$B$15,2,0)) -> CAMROON | O9: =TRIM(UPPER(tbl_raw_data[[#This Row],[Outcome]])) -> APPROVE | P9: =TRIM(UPPER(tbl_raw_data[[#This Row],[Queue Name]])) -> CONSUMER POST BUREAU | Q9: =IF(tbl_raw_data[[#This Row],[time_taken_in_min]]<=settings!$D$2,"SLA_MET","SLA_NOT_MET") -> SLA_MET
A10: 9 | B10: 45137.437 | C10: 45137.443 | D10: APPROVE | E10: Consumer Existing | F10: MDcruz | G10: Approve | H10: =IF(OR(ISNUMBER(SEARCH("duplicate",G10)), ISNUMBER(SEARCH("previously",G10)), ISNUMBER(SEARCH("previously approved",G10))), "Duplicate Application", IF(OR(ISNUMBER(SEARCH("incorrect",G10)), ISNUMBER(SEARCH("remove", G10))), "Incorrect Details", IF(ISNUMBER(SEARCH("incomplete",G10)), "Incomplete Details", IF(ISNUMBER(SEARCH("overdue",G10)), "Overdue Bill", IF(OR(ISNUMBER(SEARCH("resubmit as", G10)), ISNUMBER(SEARCH("re-submit as", G10))), "Incorrect Queue", IF(OR(ISNUMBER(SEARCH("100",G10)), ISNUMBER(SEARCH("correct", G10)), ISNUMBER(SEARCH("email", G10)), ISNUMBER(SEARCH("please submit", G10)), ISNUMBER(SEARCH("please resubmit",G10)), ISNUMBER(SEARCH("please re-submit", G10)), ISNUMBER(SEARCH("please send", G10))), "Incomplete Details", IF(ISNUMBER(SEARCH("error", G10)), "System Error", "Reason Unknown"))))))) -> Reason Unknown | I10: =(tbl_raw_data[[#This Row],[Date Actioned]])-(tbl_raw_data[[#This Row],[Date Tagged]]) -> 0.0063657407 | J10: =HOUR(tbl_raw_data[[#This Row],[time_taken]])*60+MINUTE(tbl_raw_data[[#This Row],[time_taken]])+SECOND(tbl_raw_data[[#This Row],[time_taken]])/60 -> 9.1666667 | K10: =DATE(YEAR(tbl_raw_data[[#This Row],[Date Actioned]]),MONTH(tbl_raw_data[[#This Row],[Date Actioned]]),DAY(tbl_raw_data[[#This Row],[Date Actioned]])) -> 45137 | L10: =UPPER(TEXT(tbl_raw_data[[#This Row],[updated_date]],"MMMM")) -> JULY | M10: ="WEEK "&IF(ROUNDUP(DAY(tbl_raw_data[[#This Row],[updated_date]])/7,0)=5,4,ROUNDUP(DAY(tbl_raw_data[[#This Row],[updated_date]])/7,0)) -> WEEK 4 | N10: =UPPER(VLOOKUP(tbl_raw_data[[#This Row],[Analyst]],settings!$A$1:$B$15,2,0)) -> MERCEDES | O10: =TRIM(UPPER(tbl_raw_data[[#This Row],[Outcome]])) -> APPROVE | P10: =TRIM(UPPER(tbl_raw_data[[#This Row],[Queue Name]])) -> CONSUMER EXISTING | Q10: =IF(tbl_raw_data[[#This Row],[time_taken_in_min]]<=settings!$D$2,"SLA_MET","SLA_NOT_MET") -> SLA_MET
A11: 10 | B11: 45137.444 | C11: 45137.449 | D11: APPROVE | E11: Consumer Pre Bureau | F11: MDcruz | G11: Approve | H11: =IF(OR(ISNUMBER(SEARCH("duplicate",G11)), ISNUMBER(SEARCH("previously",G11)), ISNUMBER(SEARCH("previously approved",G11))), "Duplicate Application", IF(OR(ISNUMBER(SEARCH("incorrect",G11)), ISNUMBER(SEARCH("remove", G11))), "Incorrect Details", IF(ISNUMBER(SEARCH("incomplete",G11)), "Incomplete Details", IF(ISNUMBER(SEARCH("overdue",G11)), "Overdue Bill", IF(OR(ISNUMBER(SEARCH("resubmit as", G11)), ISNUMBER(SEARCH("re-submit as", G11))), "Incorrect Queue", IF(OR(ISNUMBER(SEARCH("100",G11)), ISNUMBER(SEARCH("correct", G11)), ISNUMBER(SEARCH("email", G11)), ISNUMBER(SEARCH("please submit", G11)), ISNUMBER(SEARCH("please resubmit",G11)), ISNUMBER(SEARCH("please re-submit", G11)), ISNUMBER(SEARCH("please send", G11))), "Incomplete Details", IF(ISNUMBER(SEARCH("error", G11)), "System Error", "Reason Unknown"))))))) -> Reason Unknown | I11: =(tbl_raw_data[[#This Row],[Date Actioned]])-(tbl_raw_data[[#This Row],[Date Tagged]]) -> 0.0047800926 | J11: =HOUR(tbl_raw_data[[#This Row],[time_taken]])*60+MINUTE(tbl_raw_data[[#This Row],[time_taken]])+SECOND(tbl_raw_data[[#This Row],[time_taken]])/60 -> 6.8833333 | K11: =DATE(YEAR(tbl_raw_data[[#This Row],[Date Actioned]]),MONTH(tbl_raw_data[[#This Row],[Date Actioned]]),DAY(tbl_raw_data[[#This Row],[Date Actioned]])) -> 45137 | L11: =UPPER(TEXT(tbl_raw_data[[#This Row],[updated_date]],"MMMM")) -> JULY | M11: ="WEEK "&IF(ROUNDUP(DAY(tbl_raw_data[[#This Row],[updated_date]])/7,0)=5,4,ROUNDUP(DAY(tbl_raw_data[[#This Row],[updated_date]])/7,0)) -> WEEK 4 | N11: =UPPER(VLOOKUP(tbl_raw_data[[#This Row],[Analyst]],settings!$A$1:$B$15,2,0)) -> MERCEDES | O11: =TRIM(UPPER(tbl_raw_data[[#This Row],[Outcome]])) -> APPROVE | P11: =TRIM(UPPER(tbl_raw_data[[#This Row],[Queue Name]])) -> CONSUMER PRE BUREAU | Q11: =IF(tbl_raw_data[[#This Row],[time_taken_in_min]]<=settings!$D$2,"SLA_MET","SLA_NOT_MET") -> SLA_MET
A12: 11 | B12: 45137.445 | C12: 45137.45 | D12: Approve | E12: Consumer Existing | F12: QMascarenhas | H12: =IF(OR(ISNUMBER(SEARCH("duplicate",G12)), ISNUMBER(SEARCH("previously",G12)), ISNUMBER(SEARCH("previously approved",G12))), "Duplicate Application", IF(OR(ISNUMBER(SEARCH("incorrect",G12)), ISNUMBER(SEARCH("remove", G12))), "Incorrect Details", IF(ISNUMBER(SEARCH("incomplete",G12)), "Incomplete Details", IF(ISNUMBER(SEARCH("overdue",G12)), "Overdue Bill", IF(OR(ISNUMBER(SEARCH("resubmit as", G12)), ISNUMBER(SEARCH("re-submit as", G12))), "Incorrect Queue", IF(OR(ISNUMBER(SEARCH("100",G12)), ISNUMBER(SEARCH("correct", G12)), ISNUMBER(SEARCH("email", G12)), ISNUMBER(SEARCH("please submit", G12)), ISNUMBER(SEARCH("please resubmit",G12)), ISNUMBER(SEARCH("please re-submit", G12)), ISNUMBER(SEARCH("please send", G12))), "Incomplete Details", IF(ISNUMBER(SEARCH("error", G12)), "System Error", "Reason Unknown"))))))) -> Reason Unknown | I12: =(tbl_raw_data[[#This Row],[Date Actioned]])-(tbl_raw_data[[#This Row],[Date Tagged]]) -> 0.0050810185 | J12: =HOUR(tbl_raw_data[[#This Row],[time_taken]])*60+MINUTE(tbl_raw_data[[#This Row],[time_taken]])+SECOND(tbl_raw_data[[#This Row],[time_taken]])/60 -> 7.3166667 | K12: =DATE(YEAR(tbl_raw_data[[#This Row],[Date Actioned]]),MONTH(tbl_raw_data[[#This Row],[Date Actioned]]),DAY(tbl_raw_data[[#This Row],[Date Actioned]])) -> 45137 | L12: =UPPER(TEXT(tbl_raw_data[[#This Row],[updated_date]],"MMMM")) -> JULY | M12: ="WEEK "&IF(ROUNDUP(DAY(tbl_raw_data[[#This Row],[updated_date]])/7,0)=5,4,ROUNDUP(DAY(tbl_raw_data[[#This Row],[updated_date]])/7,0)) -> WEEK 4 | N12: =UPPER(VLOOKUP(tbl_raw_data[[#This Row],[Analyst]],settings!$A$1:$B$15,2,0)) -> QUADIR | O12: =TRIM(UPPER(tbl_raw_data[[#This Row],[Outcome]])) -> APPROVE | P12: =TRIM(UPPER(tbl_raw_data[[#This Row],[Queue Name]])) -> CONSUMER EXISTING | Q12: =IF(tbl_raw_data[[#This Row],[time_taken_in_min]]<=settings!$D$2,"SLA_MET","SLA_NOT_MET") -> SLA_MET
A13: 12 | B13: 45137.445 | C13: 45137.455 | D13: APPROVE | E13: Consumer Post Bureau | F13: NVaid | G13: Approved for 1 handset and 1 MBB | H13: =IF(OR(ISNUMBER(SEARCH("duplicate",G13)), ISNUMBER(SEARCH("previously",G13)), ISNUMBER(SEARCH("previously approved",G13))), "Duplicate Application", IF(OR(ISNUMBER(SEARCH("incorrect",G13)), ISNUMBER(SEARCH("remove", G13))), "Incorrect Details", IF(ISNUMBER(SEARCH("incomplete",G13)), "Incomplete Details", IF(ISNUMBER(SEARCH("overdue",G13)), "Overdue Bill", IF(OR(ISNUMBER(SEARCH("resubmit as", G13)), ISNUMBER(SEARCH("re-submit as", G13))), "Incorrect Queue", IF(OR(ISNUMBER(SEARCH("100",G13)), ISNUMBER(SEARCH("correct", G13)), ISNUMBER(SEARCH("email", G13)), ISNUMBER(SEARCH("please submit", G13)), ISNUMBER(SEARCH("please resubmit",G13)), ISNUMBER(SEARCH("please re-submit", G13)), ISNUMBER(SEARCH("please send", G13))), "Incomplete Details", IF(ISNUMBER(SEARCH("error", G13)), "System Error", "Reason Unknown"))))))) -> Reason Unknown | I13: =(tbl_raw_data[[#This Row],[Date Actioned]])-(tbl_raw_data[[#This Row],[Date Tagged]]) -> 0.0098726852 | J13: =HOUR(tbl_raw_data[[#This Row],[time_taken]])*60+MINUTE(tbl_raw_data[[#This Row],[time_taken]])+SECOND(tbl_raw_data[[#This Row],[time_taken]])/60 -> 14.216667 | K13: =DATE(YEAR(tbl_raw_data[[#This Row],[Date Actioned]]),MONTH(tbl_raw_data[[#This Row],[Date Actioned]]),DAY(tbl_raw_data[[#This Row],[Date Actioned]])) -> 45137 | L13: =UPPER(TEXT(tbl_raw_data[[#This Row],[updated_date]],"MMMM")) -> JULY | M13: ="WEEK "&IF(ROUNDUP(DAY(tbl_raw_data[[#This Row],[updated_date]])/7,0)=5,4,ROUNDUP(DAY(tbl_raw_data[[#This Row],[updated_date]])/7,0)) -> WEEK 4 | N13: =UPPER(VLOOKUP(tbl_raw_data[[#This Row],[Analyst]],settings!$A$1:$B$15,2,0)) -> NAVED | O13: =TRIM(UPPER(tbl_raw_data[[#This Row],[Outcome]])) -> APPROVE | P13: =TRIM(UPPER(tbl_raw_data[[#This Row],[Queue Name]])) -> CONSUMER POST BUREAU | Q13: =IF(tbl_raw_data[[#This Row],[time_taken_in_min]]<=settings!$D$2,"SLA_MET","SLA_NOT_MET") -> SLA_MET
A14: 13 | B14: 45137.455 | C14: 45137.463 | D14: APPROVE | E14: Consumer Pre Bureau | F14: NVaid | G14: Direct debit to bank account or credit card mandatory | H14: =IF(OR(ISNUMBER(SEARCH("duplicate",G14)), ISNUMBER(SEARCH("previously",G14)), ISNUMBER(SEARCH("previously approved",G14))), "Duplicate Application", IF(OR(ISNUMBER(SEARCH("incorrect",G14)), ISNUMBER(SEARCH("remove", G14))), "Incorrect Details", IF(ISNUMBER(SEARCH("incomplete",G14)), "Incomplete Details", IF(ISNUMBER(SEARCH("overdue",G14)), "Overdue Bill", IF(OR(ISNUMBER(SEARCH("resubmit as", G14)), ISNUMBER(SEARCH("re-submit as", G14))), "Incorrect Queue", IF(OR(ISNUMBER(SEARCH("100",G14)), ISNUMBER(SEARCH("correct", G14)), ISNUMBER(SEARCH("email", G14)), ISNUMBER(SEARCH("please submit", G14)), ISNUMBER(SEARCH("please resubmit",G14)), ISNUMBER(SEARCH("please re-submit", G14)), ISNUMBER(SEARCH("please send", G14))), "Incomplete Details", IF(ISNUMBER(SEARCH("error", G14)), "System Error", "Reason Unknown"))))))) -> Reason Unknown | I14: =(tbl_raw_data[[#This Row],[Date Actioned]])-(tbl_raw_data[[#This Row],[Date Tagged]]) -> 0.0078935185 | J14: =HOUR(tbl_raw_data[[#This Row],[time_taken]])*60+MINUTE(tbl_raw_data[[#This Row],[time_taken]])+SECOND(tbl_raw_data[[#This Row],[time_taken]])/60 -> 11.366667 | K14: =DATE(YEAR(tbl_raw_data[[#This Row],[Date Actioned]]),MONTH(tbl_raw_data[[#This Row],[Date Actioned]]),DAY(tbl_raw_data[[#This Row],[Date Actioned]])) -> 45137 | L14: =UPPER(TEXT(tbl_raw_data[[#This Row],[updated_date]],"MMMM")) -> JULY | M14: ="WEEK "&IF(ROUNDUP(DAY(tbl_raw_data[[#This Row],[updated_date]])/7,0)=5,4,ROUNDUP(DAY(tbl_raw_data[[#This Row],[updated_date]])/7,0)) -> WEEK 4 | N14: =UPPER(VLOOKUP(tbl_raw_data[[#This Row],[Analyst]],settings!$A$1:$B$15,2,0)) -> NAVED | O14: =TRIM(UPPER(tbl_raw_data[[#This Row],[Outcome]])) -> APPROVE | P14: =TRIM(UPPER(tbl_raw_data[[#This Row],[Queue Name]])) -> CONSUMER PRE BUREAU | Q14: =IF(tbl_raw_data[[#This Row],[time_taken_in_min]]<=settings!$D$2,"SLA_MET","SLA_NOT_MET") -> SLA_MET
A15: 14 | B15: 45137.457 | C15: 45137.46 | D15: Approve | E15: Consumer Existing | F15: MDcruz | H15: =IF(OR(ISNUMBER(SEARCH("duplicate",G15)), ISNUMBER(SEARCH("previously",G15)), ISNUMBER(SEARCH("previously approved",G15))), "Duplicate Application", IF(OR(ISNUMBER(SEARCH("incorrect",G15)), ISNUMBER(SEARCH("remove", G15))), "Incorrect Details", IF(ISNUMBER(SEARCH("incomplete",G15)), "Incomplete Details", IF(ISNUMBER(SEARCH("overdue",G15)), "Overdue Bill", IF(OR(ISNUMBER(SEARCH("resubmit as", G15)), ISNUMBER(SEARCH("re-submit as", G15))), "Incorrect Queue", IF(OR(ISNUMBER(SEARCH("100",G15)), ISNUMBER(SEARCH("correct", G15)), ISNUMBER(SEARCH("email", G15)), ISNUMBER(SEARCH("please submit", G15)), ISNUMBER(SEARCH("please resubmit",G15)), ISNUMBER(SEARCH("please re-submit", G15)), ISNUMBER(SEARCH("please send", G15))), "Incomplete Details", IF(ISNUMBER(SEARCH("error", G15)), "System Error", "Reason Unknown"))))))) -> Reason Unknown | I15: =(tbl_raw_data[[#This Row],[Date Actioned]])-(tbl_raw_data[[#This Row],[Date Tagged]]) -> 0.0032060185 | J15: =HOUR(tbl_raw_data[[#This Row],[time_taken]])*60+MINUTE(tbl_raw_data[[#This Row],[time_taken]])+SECOND(tbl_raw_data[[#This Row],[time_taken]])/60 -> 4.6166667 | K15: =DATE(YEAR(tbl_raw_data[[#This Row],[Date Actioned]]),MONTH(tbl_raw_data[[#This Row],[Date Actioned]]),DAY(tbl_raw_data[[#This Row],[Date Actioned]])) -> 45137 | L15: =UPPER(TEXT(tbl_raw_data[[#This Row],[updated_date]],"MMMM")) -> JULY | M15: ="WEEK "&IF(ROUNDUP(DAY(tbl_raw_data[[#This Row],[updated_date]])/7,0)=5,4,ROUNDUP(DAY(tbl_raw_data[[#This Row],[updated_date]])/7,0)) -> WEEK 4 | N15: =UPPER(VLOOKUP(tbl_raw_data[[#This Row],[Analyst]],settings!$A$1:$B$15,2,0)) -> MERCEDES | O15: =TRIM(UPPER(tbl_raw_data[[#This Row],[Outcome]])) -> APPROVE | P15: =TRIM(UPPER(tbl_raw_data[[#This Row],[Queue Name]])) -> CONSUMER EXISTING | Q15: =IF(tbl_raw_data[[#This Row],[time_taken_in_min]]<=settings!$D$2,"SLA_MET","SLA_NOT_MET") -> SLA_MET
A16: 15 | B16: 45137.459 | C16: 45137.466 | D16: Approve | E16: Consumer Existing | F16: MDcruz | H16: =IF(OR(ISNUMBER(SEARCH("duplicate",G16)), ISNUMBER(SEARCH("previously",G16)), ISNUMBER(SEARCH("previously approved",G16))), "Duplicate Application", IF(OR(ISNUMBER(SEARCH("incorrect",G16)), ISNUMBER(SEARCH("remove", G16))), "Incorrect Details", IF(ISNUMBER(SEARCH("incomplete",G16)), "Incomplete Details", IF(ISNUMBER(SEARCH("overdue",G16)), "Overdue Bill", IF(OR(ISNUMBER(SEARCH("resubmit as", G16)), ISNUMBER(SEARCH("re-submit as", G16))), "Incorrect Queue", IF(OR(ISNUMBER(SEARCH("100",G16)), ISNUMBER(SEARCH("correct", G16)), ISNUMBER(SEARCH("email", G16)), ISNUMBER(SEARCH("please submit", G16)), ISNUMBER(SEARCH("please resubmit",G16)), ISNUMBER(SEARCH("please re-submit", G16)), ISNUMBER(SEARCH("please send", G16))), "Incomplete Details", IF(ISNUMBER(SEARCH("error", G16)), "System Error", "Reason Unknown"))))))) -> Reason Unknown | I16: =(tbl_raw_data[[#This Row],[Date Actioned]])-(tbl_raw_data[[#This Row],[Date Tagged]]) -> 0.0064351852 | J16: =HOUR(tbl_raw_data[[#This Row],[time_taken]])*60+MINUTE(tbl_raw_data[[#This Row],[time_taken]])+SECOND(tbl_raw_data[[#This Row],[time_taken]])/60 -> 9.2666667 | K16: =DATE(YEAR(tbl_raw_data[[#This Row],[Date Actioned]]),MONTH(tbl_raw_data[[#This Row],[Date Actioned]]),DAY(tbl_raw_data[[#This Row],[Date Actioned]])) -> 45137 | L16: =UPPER(TEXT(tbl_raw_data[[#This Row],[updated_date]],"MMMM")) -> JULY | M16: ="WEEK "&IF(ROUNDUP(DAY(tbl_raw_data[[#This Row],[updated_date]])/7,0)=5,4,ROUNDUP(DAY(tbl_raw_data[[#This Row],[updated_date]])/7,0)) -> WEEK 4 | N16: =UPPER(VLOOKUP(tbl_raw_data[[#This Row],[Analyst]],settings!$A$1:$B$15,2,0)) -> MERCEDES | O16: =TRIM(UPPER(tbl_raw_data[[#This Row],[Outcome]])) -> APPROVE | P16: =TRIM(UPPER(tbl_raw_data[[#This Row],[Queue Name]])) -> CONSUMER EXISTING | Q16: =IF(tbl_raw_data[[#This Row],[time_taken_in_min]]<=settings!$D$2,"SLA_MET","SLA_NOT_MET") -> SLA_MET
A17: 16 | B17: 45137.461 | C17: 45137.466 | D17: APPROVE | E17: Consumer Pre Bureau | F17: CDcosta | G17: Approved for 1 handset and 1 MBB | H17: =IF(OR(ISNUMBER(SEARCH("duplicate",G17)), ISNUMBER(SEARCH("previously",G17)), ISNUMBER(SEARCH("previously approved",G17))), "Duplicate Application", IF(OR(ISNUMBER(SEARCH("incorrect",G17)), ISNUMBER(SEARCH("remove", G17))), "Incorrect Details", IF(ISNUMBER(SEARCH("incomplete",G17)), "Incomplete Details", IF(ISNUMBER(SEARCH("overdue",G17)), "Overdue Bill", IF(OR(ISNUMBER(SEARCH("resubmit as", G17)), ISNUMBER(SEARCH("re-submit as", G17))), "Incorrect Queue", IF(OR(ISNUMBER(SEARCH("100",G17)), ISNUMBER(SEARCH("correct", G17)), ISNUMBER(SEARCH("email", G17)), ISNUMBER(SEARCH("please submit", G17)), ISNUMBER(SEARCH("please resubmit",G17)), ISNUMBER(SEARCH("please re-submit", G17)), ISNUMBER(SEARCH("please send", G17))), "Incomplete Details", IF(ISNUMBER(SEARCH("error", G17)), "System Error", "Reason Unknown"))))))) -> Reason Unknown | I17: =(tbl_raw_data[[#This Row],[Date Actioned]])-(tbl_raw_data[[#This Row],[Date Tagged]]) -> 0.0050115741 | J17: =HOUR(tbl_raw_data[[#This Row],[time_taken]])*60+MINUTE(tbl_raw_data[[#This Row],[time_taken]])+SECOND(tbl_raw_data[[#This Row],[time_taken]])/60 -> 7.2166667 | K17: =DATE(YEAR(tbl_raw_data[[#This Row],[Date Actioned]]),MONTH(tbl_raw_data[[#This Row],[Date Actioned]]),DAY(tbl_raw_data[[#This Row],[Date Actioned]])) -> 45137 | L17: =UPPER(TEXT(tbl_raw_data[[#This Row],[updated_date]],"MMMM")) -> JULY | M17: ="WEEK "&IF(ROUNDUP(DAY(tbl_raw_data[[#This Row],[updated_date]])/7,0)=5,4,ROUNDUP(DAY(tbl_raw_data[[#This Row],[updated_date]])/7,0)) -> WEEK 4 | N17: =UPPER(VLOOKUP(tbl_raw_data[[#This Row],[Analyst]],settings!$A$1:$B$15,2,0)) -> CAMROON | O17: =TRIM(UPPER(tbl_raw_data[[#This Row],[Outcome]])) -> APPROVE | P17: =TRIM(UPPER(tbl_raw_data[[#This Row],[Queue Name]])) -> CONSUMER PRE BUREAU | Q17: =IF(tbl_raw_data[[#This Row],[time_taken_in_min]]<=settings!$D$2,"SLA_MET","SLA_NOT_MET") -> SLA_MET
A18: 17 | B18: 45137.464 | C18: 45137.471 | D18: APPROVE | E18: Consumer Pre Bureau | F18: CDcosta | G18: Approved for 1 handset and 1 MBB | H18: =IF(OR(ISNUMBER(SEARCH("duplicate",G18)), ISNUMBER(SEARCH("previously",G18)), ISNUMBER(SEARCH("previously approved",G18))), "Duplicate Application", IF(OR(ISNUMBER(SEARCH("incorrect",G18)), ISNUMBER(SEARCH("remove", G18))), "Incorrect Details", IF(ISNUMBER(SEARCH("incomplete",G18)), "Incomplete Details", IF(ISNUMBER(SEARCH("overdue",G18)), "Overdue Bill", IF(OR(ISNUMBER(SEARCH("resubmit as", G18)), ISNUMBER(SEARCH("re-submit as", G18))), "Incorrect Queue", IF(OR(ISNUMBER(SEARCH("100",G18)), ISNUMBER(SEARCH("correct", G18)), ISNUMBER(SEARCH("email", G18)), ISNUMBER(SEARCH("please submit", G18)), ISNUMBER(SEARCH("please resubmit",G18)), ISNUMBER(SEARCH("please re-submit", G18)), ISNUMBER(SEARCH("please send", G18))), "Incomplete Details", IF(ISNUMBER(SEARCH("error", G18)), "System Error", "Reason Unknown"))))))) -> Reason Unknown | I18: =(tbl_raw_data[[#This Row],[Date Actioned]])-(tbl_raw_data[[#This Row],[Date Tagged]]) -> 0.0069675926 | J18: =HOUR(tbl_raw_data[[#This Row],[time_taken]])*60+MINUTE(tbl_raw_data[[#This Row],[time_taken]])+SECOND(tbl_raw_data[[#This Row],[time_taken]])/60 -> 10.033333 | K18: =DATE(YEAR(tbl_raw_data[[#This Row],[Date Actioned]]),MONTH(tbl_raw_data[[#This Row],[Date Actioned]]),DAY(tbl_raw_data[[#This Row],[Date Actioned]])) -> 45137 | L18: =UPPER(TEXT(tbl_raw_data[[#This Row],[updated_date]],"MMMM")) -> JULY | M18: ="WEEK "&IF(ROUNDUP(DAY(tbl_raw_data[[#This Row],[updated_date]])/7,0)=5,4,ROUNDUP(DAY(tbl_raw_data[[#This Row],[updated_date]])/7,0)) -> WEEK 4 | N18: =UPPER(VLOOKUP(tbl_raw_data[[#This Row],[Analyst]],settings!$A$1:$B$15,2,0)) -> CAMROON | O18: =TRIM(UPPER(tbl_raw_data[[#This Row],[Outcome]])) -> APPROVE | P18: =TRIM(UPPER(tbl_raw_data[[#This Row],[Queue Name]])) -> CONSUMER PRE BUREAU | Q18: =IF(tbl_raw_data[[#This Row],[time_taken_in_min]]<=settings!$D$2,"SLA_MET","SLA_NOT_MET") -> SLA_MET
A19: 18 | B19: 45137.465 | C19: 45137.469 | D19: Approve | E19: Consumer Post Bureau | F19: SSyed | H19: =IF(OR(ISNUMBER(SEARCH("duplicate",G19)), ISNUMBER(SEARCH("previously",G19)), ISNUMBER(SEARCH("previously approved",G19))), "Duplicate Application", IF(OR(ISNUMBER(SEARCH("incorrect",G19)), ISNUMBER(SEARCH("remove", G19))), "Incorrect Details", IF(ISNUMBER(SEARCH("incomplete",G19)), "Incomplete Details", IF(ISNUMBER(SEARCH("overdue",G19)), "Overdue Bill", IF(OR(ISNUMBER(SEARCH("resubmit as", G19)), ISNUMBER(SEARCH("re-submit as", G19))), "Incorrect Queue", IF(OR(ISNUMBER(SEARCH("100",G19)), ISNUMBER(SEARCH("correct", G19)), ISNUMBER(SEARCH("email", G19)), ISNUMBER(SEARCH("please submit", G19)), ISNUMBER(SEARCH("please resubmit",G19)), ISNUMBER(SEARCH("please re-submit", G19)), ISNUMBER(SEARCH("please send", G19))), "Incomplete Details", IF(ISNUMBER(SEARCH("error", G19)), "System Error", "Reason Unknown"))))))) -> Reason Unknown | I19: =(tbl_raw_data[[#This Row],[Date Actioned]])-(tbl_raw_data[[#This Row],[Date Tagged]]) -> 0.0041666667 | J19: =HOUR(tbl_raw_data[[#This Row],[time_taken]])*60+MINUTE(tbl_raw_data[[#This Row],[time_taken]])+SECOND(tbl_raw_data[[#This Row],[time_taken]])/60 -> 6 | K19: =DATE(YEAR(tbl_raw_data[[#This Row],[Date Actioned]]),MONTH(tbl_raw_data[[#This Row],[Date Actioned]]),DAY(tbl_raw_data[[#This Row],[Date Actioned]])) -> 45137 | L19: =UPPER(TEXT(tbl_raw_data[[#This Row],[updated_date]],"MMMM")) -> JULY | M19: ="WEEK "&IF(ROUNDUP(DAY(tbl_raw_data[[#This Row],[updated_date]])/7,0)=5,4,ROUNDUP(DAY(tbl_raw_data[[#This Row],[updated_date]])/7,0)) -> WEEK 4 | N19: =UPPER(VLOOKUP(tbl_raw_data[[#This Row],[Analyst]],settings!$A$1:$B$15,2,0)) -> SHAHID | O19: =TRIM(UPPER(tbl_raw_data[[#This Row],[Outcome]])) -> APPROVE | P19: =TRIM(UPPER(tbl_raw_data[[#This Row],[Queue Name]])) -> CONSUMER POST BUREAU | Q19: =IF(tbl_raw_data[[#This Row],[time_taken_in_min]]<=settings!$D$2,"SLA_MET","SLA_NOT_MET") -> SLA_MET
A20: 19 | B20: 45137.469 | C20: 45137.473 | D20: APPROVE | E20: Consumer Existing | F20: MDcruz | G20: Approve | H20: =IF(OR(ISNUMBER(SEARCH("duplicate",G20)), ISNUMBER(SEARCH("previously",G20)), ISNUMBER(SEARCH("previously approved",G20))), "Duplicate Application", IF(OR(ISNUMBER(SEARCH("incorrect",G20)), ISNUMBER(SEARCH("remove", G20))), "Incorrect Details", IF(ISNUMBER(SEARCH("incomplete",G20)), "Incomplete Details", IF(ISNUMBER(SEARCH("overdue",G20)), "Overdue Bill", IF(OR(ISNUMBER(SEARCH("resubmit as", G20)), ISNUMBER(SEARCH("re-submit as", G20))), "Incorrect Queue", IF(OR(ISNUMBER(SEARCH("100",G20)), ISNUMBER(SEARCH("correct", G20)), ISNUMBER(SEARCH("email", G20)), ISNUMBER(SEARCH("please submit", G20)), ISNUMBER(SEARCH("please resubmit",G20)), ISNUMBER(SEARCH("please re-submit", G20)), ISNUMBER(SEARCH("please send", G20))), "Incomplete Details", IF(ISNUMBER(SEARCH("error", G20)), "System Error", "Reason Unknown"))))))) -> Reason Unknown | I20: =(tbl_raw_data[[#This Row],[Date Actioned]])-(tbl_raw_data[[#This Row],[Date Tagged]]) -> 0.0036458333 | J20: =HOUR(tbl_raw_data[[#This Row],[time_taken]])*60+MINUTE(tbl_raw_data[[#This Row],[time_taken]])+SECOND(tbl_raw_data[[#This Row],[time_taken]])/60 -> 5.25 | K20: =DATE(YEAR(tbl_raw_data[[#This Row],[Date Actioned]]),MONTH(tbl_raw_data[[#This Row],[Date Actioned]]),DAY(tbl_raw_data[[#This Row],[Date Actioned]])) -> 45137 | L20: =UPPER(TEXT(tbl_raw_data[[#This Row],[updated_date]],"MMMM")) -> JULY | M20: ="WEEK "&IF(ROUNDUP(DAY(tbl_raw_data[[#This Row],[updated_date]])/7,0)=5,4,ROUNDUP(DAY(tbl_raw_data[[#This Row],[updated_date]])/7,0)) -> WEEK 4 | N20: =UPPER(VLOOKUP(tbl_raw_data[[#This Row],[Analyst]],settings!$A$1:$B$15,2,0)) -> MERCEDES | O20: =TRIM(UPPER(tbl_raw_data[[#This Row],[Outcome]])) -> APPROVE | P20: =TRIM(UPPER(tbl_raw_data[[#This Row],[Queue Name]])) -> CONSUMER EXISTING | Q20: =IF(tbl_raw_data[[#This Row],[time_taken_in_min]]<=settings!$D$2,"SLA_MET","SLA_NOT_MET") -> SLA_MET
A21: 20 | B21: 45137.479 | C21: 45137.483 | D21: APPROVE | E21: Consumer Existing | F21: RBose | G21: Approved only with outright purchase of handset or USIM only | H21: =IF(OR(ISNUMBER(SEARCH("duplicate",G21)), ISNUMBER(SEARCH("previously",G21)), ISNUMBER(SEARCH("previously approved",G21))), "Duplicate Application", IF(OR(ISNUMBER(SEARCH("incorrect",G21)), ISNUMBER(SEARCH("remove", G21))), "Incorrect Details", IF(ISNUMBER(SEARCH("incomplete",G21)), "Incomplete Details", IF(ISNUMBER(SEARCH("overdue",G21)), "Overdue Bill", IF(OR(ISNUMBER(SEARCH("resubmit as", G21)), ISNUMBER(SEARCH("re-submit as", G21))), "Incorrect Queue", IF(OR(ISNUMBER(SEARCH("100",G21)), ISNUMBER(SEARCH("correct", G21)), ISNUMBER(SEARCH("email", G21)), ISNUMBER(SEARCH("please submit", G21)), ISNUMBER(SEARCH("please resubmit",G21)), ISNUMBER(SEARCH("please re-submit", G21)), ISNUMBER(SEARCH("please send", G21))), "Incomplete Details", IF(ISNUMBER(SEARCH("error", G21)), "System Error", "Reason Unknown"))))))) -> Reason Unknown | I21: =(tbl_raw_data[[#This Row],[Date Actioned]])-(tbl_raw_data[[#This Row],[Date Tagged]]) -> 0.0040393519 | J21: =HOUR(tbl_raw_data[[#This Row],[time_taken]])*60+MINUTE(tbl_raw_data[[#This Row],[time_taken]])+SECOND(tbl_raw_data[[#This Row],[time_taken]])/60 -> 5.8166667 | K21: =DATE(YEAR(tbl_raw_data[[#This Row],[Date Actioned]]),MONTH(tbl_raw_data[[#This Row],[Date Actioned]]),DAY(tbl_raw_data[[#This Row],[Date Actioned]])) -> 45137 | L21: =UPPER(TEXT(tbl_raw_data[[#This Row],[updated_date]],"MMMM")) -> JULY | M21: ="WEEK "&IF(ROUNDUP(DAY(tbl_raw_data[[#This Row],[updated_date]])/7,0)=5,4,ROUNDUP(DAY(tbl_raw_data[[#This Row],[updated_date]])/7,0)) -> WEEK 4 | N21: =UPPER(VLOOKUP(tbl_raw_data[[#This Row],[Analyst]],settings!$A$1:$B$15,2,0)) -> ROHAN | O21: =TRIM(UPPER(tbl_raw_data[[#This Row],[Outcome]])) -> APPROVE | P21: =TRIM(UPPER(tbl_raw_data[[#This Row],[Queue Name]])) -> CONSUMER EXISTING | Q21: =IF(tbl_raw_data[[#This Row],[time_taken_in_min]]<=settings!$D$2,"SLA_MET","SLA_NOT_MET") -> SLA_MET
A22: 21 | B22: 45137.479 | C22: 45137.489 | D22: Approve | E22: Consumer Post Bureau | F22: MDcruz | H22: =IF(OR(ISNUMBER(SEARCH("duplicate",G22)), ISNUMBER(SEARCH("previously",G22)), ISNUMBER(SEARCH("previously approved",G22))), "Duplicate Application", IF(OR(ISNUMBER(SEARCH("incorrect",G22)), ISNUMBER(SEARCH("remove", G22))), "Incorrect Details", IF(ISNUMBER(SEARCH("incomplete",G22)), "Incomplete Details", IF(ISNUMBER(SEARCH("overdue",G22)), "Overdue Bill", IF(OR(ISNUMBER(SEARCH("resubmit as", G22)), ISNUMBER(SEARCH("re-submit as", G22))), "Incorrect Queue", IF(OR(ISNUMBER(SEARCH("100",G22)), ISNUMBER(SEARCH("correct", G22)), ISNUMBER(SEARCH("email", G22)), ISNUMBER(SEARCH("please submit", G22)), ISNUMBER(SEARCH("please resubmit",G22)), ISNUMBER(SEARCH("please re-submit", G22)), ISNUMBER(SEARCH("please send", G22))), "Incomplete Details", IF(ISNUMBER(SEARCH("error", G22)), "System Error", "Reason Unknown"))))))) -> Reason Unknown | I22: =(tbl_raw_data[[#This Row],[Date Actioned]])-(tbl_raw_data[[#This Row],[Date Tagged]]) -> 0.010474537 | J22: =HOUR(tbl_raw_data[[#This Row],[time_taken]])*60+MINUTE(tbl_raw_data[[#This Row],[time_taken]])+SECOND(tbl_raw_data[[#This Row],[time_taken]])/60 -> 15.083333 | K22: =DATE(YEAR(tbl_raw_data[[#This Row],[Date Actioned]]),MONTH(tbl_raw_data[[#This Row],[Date Actioned]]),DAY(tbl_raw_data[[#This Row],[Date Actioned]])) -> 45137 | L22: =UPPER(TEXT(tbl_raw_data[[#This Row],[updated_date]],"MMMM")) -> JULY | M22: ="WEEK "&IF(ROUNDUP(DAY(tbl_raw_data[[#This Row],[updated_date]])/7,0)=5,4,ROUNDUP(DAY(tbl_raw_data[[#This Row],[updated_date]])/7,0)) -> WEEK 4 | N22: =UPPER(VLOOKUP(tbl_raw_data[[#This Row],[Analyst]],settings!$A$1:$B$15,2,0)) -> MERCEDES | O22: =TRIM(UPPER(tbl_raw_data[[#This Row],[Outcome]])) -> APPROVE | P22: =TRIM(UPPER(tbl_raw_data[[#This Row],[Queue Name]])) -> CONSUMER POST BUREAU | Q22: =IF(tbl_raw_data[[#This Row],[time_taken_in_min]]<=settings!$D$2,"SLA_MET","SLA_NOT_MET") -> SLA_MET
A23: 22 | B23: 45137.479 | C23: 45137.482 | D23: APPROVE | E23: Consumer Existing | F23: QMascarenhas | G23: Approve | H23: =IF(OR(ISNUMBER(SEARCH("duplicate",G23)), ISNUMBER(SEARCH("previously",G23)), ISNUMBER(SEARCH("previously approved",G23))), "Duplicate Application", IF(OR(ISNUMBER(SEARCH("incorrect",G23)), ISNUMBER(SEARCH("remove", G23))), "Incorrect Details", IF(ISNUMBER(SEARCH("incomplete",G23)), "Incomplete Details", IF(ISNUMBER(SEARCH("overdue",G23)), "Overdue Bill", IF(OR(ISNUMBER(SEARCH("resubmit as", G23)), ISNUMBER(SEARCH("re-submit as", G23))), "Incorrect Queue", IF(OR(ISNUMBER(SEARCH("100",G23)), ISNUMBER(SEARCH("correct", G23)), ISNUMBER(SEARCH("email", G23)), ISNUMBER(SEARCH("please submit", G23)), ISNUMBER(SEARCH("please resubmit",G23)), ISNUMBER(SEARCH("please re-submit", G23)), ISNUMBER(SEARCH("please send", G23))), "Incomplete Details", IF(ISNUMBER(SEARCH("error", G23)), "System Error", "Reason Unknown"))))))) -> Reason Unknown | I23: =(tbl_raw_data[[#This Row],[Date Actioned]])-(tbl_raw_data[[#This Row],[Date Tagged]]) -> 0.0030902778 | J23: =HOUR(tbl_raw_data[[#This Row],[time_taken]])*60+MINUTE(tbl_raw_data[[#This Row],[time_taken]])+SECOND(tbl_raw_data[[#This Row],[time_taken]])/60 -> 4.45 | K23: =DATE(YEAR(tbl_raw_data[[#This Row],[Date Actioned]]),MONTH(tbl_raw_data[[#This Row],[Date Actioned]]),DAY(tbl_raw_data[[#This Row],[Date Actioned]])) -> 45137 | L23: =UPPER(TEXT(tbl_raw_data[[#This Row],[updated_date]],"MMMM")) -> JULY | M23: ="WEEK "&IF(ROUNDUP(DAY(tbl_raw_data[[#This Row],[updated_date]])/7,0)=5,4,ROUNDUP(DAY(tbl_raw_data[[#This Row],[updated_date]])/7,0)) -> WEEK 4 | N23: =UPPER(VLOOKUP(tbl_raw_data[[#This Row],[Analyst]],settings!$A$1:$B$15,2,0)) -> QUADIR | O23: =TRIM(UPPER(tbl_raw_data[[#This Row],[Outcome]])) -> APPROVE | P23: =TRIM(UPPER(tbl_raw_data[[#This Row],[Queue Name]])) -> CONSUMER EXISTING | Q23: =IF(tbl_raw_data[[#This Row],[time_taken_in_min]]<=settings!$D$2,"SLA_MET","SLA_NOT_MET") -> SLA_MET
A24: 23 | B24: 45137.486 | C24: 45137.5 | D24: APPROVE | E24: Consumer Post Bureau | F24: SBambaras | G24: Approved for 1 handset and 1 MBB | H24: =IF(OR(ISNUMBER(SEARCH("duplicate",G24)), ISNUMBER(SEARCH("previously",G24)), ISNUMBER(SEARCH("previously approved",G24))), "Duplicate Application", IF(OR(ISNUMBER(SEARCH("incorrect",G24)), ISNUMBER(SEARCH("remove", G24))), "Incorrect Details", IF(ISNUMBER(SEARCH("incomplete",G24)), "Incomplete Details", IF(ISNUMBER(SEARCH("overdue",G24)), "Overdue Bill", IF(OR(ISNUMBER(SEARCH("resubmit as", G24)), ISNUMBER(SEARCH("re-submit as", G24))), "Incorrect Queue", IF(OR(ISNUMBER(SEARCH("100",G24)), ISNUMBER(SEARCH("correct", G24)), ISNUMBER(SEARCH("email", G24)), ISNUMBER(SEARCH("please submit", G24)), ISNUMBER(SEARCH("please resubmit",G24)), ISNUMBER(SEARCH("please re-submit", G24)), ISNUMBER(SEARCH("please send", G24))), "Incomplete Details", IF(ISNUMBER(SEARCH("error", G24)), "System Error", "Reason Unknown"))))))) -> Reason Unknown | I24: =(tbl_raw_data[[#This Row],[Date Actioned]])-(tbl_raw_data[[#This Row],[Date Tagged]]) -> 0.014733796 | J24: =HOUR(tbl_raw_data[[#This Row],[time_taken]])*60+MINUTE(tbl_raw_data[[#This Row],[time_taken]])+SECOND(tbl_raw_data[[#This Row],[time_taken]])/60 -> 21.216667 | K24: =DATE(YEAR(tbl_raw_data[[#This Row],[Date Actioned]]),MONTH(tbl_raw_data[[#This Row],[Date Actioned]]),DAY(tbl_raw_data[[#This Row],[Date Actioned]])) -> 45137 | L24: =UPPER(TEXT(tbl_raw_data[[#This Row],[updated_date]],"MMMM")) -> JULY | M24: ="WEEK "&IF(ROUNDUP(DAY(tbl_raw_data[[#This Row],[updated_date]])/7,0)=5,4,ROUNDUP(DAY(tbl_raw_data[[#This Row],[updated_date]])/7,0)) -> WEEK 4 | N24: =UPPER(VLOOKUP(tbl_raw_data[[#This Row],[Analyst]],settings!$A$1:$B$15,2,0)) -> SAM | O24: =TRIM(UPPER(tbl_raw_data[[#This Row],[Outcome]])) -> APPROVE | P24: =TRIM(UPPER(tbl_raw_data[[#This Row],[Queue Name]])) -> CONSUMER POST BUREAU | Q24: =IF(tbl_raw_data[[#This Row],[time_taken_in_min]]<=settings!$D$2,"SLA_MET","SLA_NOT_MET") -> SLA_NOT_MET
A25: 24 | B25: 45137.486 | C25: 45137.489 | D25: APPROVE | E25: Consumer Existing | F25: AAkhundpur | G25: Approve | H25: =IF(OR(ISNUMBER(SEARCH("duplicate",G25)), ISNUMBER(SEARCH("previously",G25)), ISNUMBER(SEARCH("previously approved",G25))), "Duplicate Application", IF(OR(ISNUMBER(SEARCH("incorrect",G25)), ISNUMBER(SEARCH("remove", G25))), "Incorrect Details", IF(ISNUMBER(SEARCH("incomplete",G25)), "Incomplete Details", IF(ISNUMBER(SEARCH("overdue",G25)), "Overdue Bill", IF(OR(ISNUMBER(SEARCH("resubmit as", G25)), ISNUMBER(SEARCH("re-submit as", G25))), "Incorrect Queue", IF(OR(ISNUMBER(SEARCH("100",G25)), ISNUMBER(SEARCH("correct", G25)), ISNUMBER(SEARCH("email", G25)), ISNUMBER(SEARCH("please submit", G25)), ISNUMBER(SEARCH("please resubmit",G25)), ISNUMBER(SEARCH("please re-submit", G25)), ISNUMBER(SEARCH("please send", G25))), "Incomplete Details", IF(ISNUMBER(SEARCH("error", G25)), "System Error", "Reason Unknown"))))))) -> Reason Unknown | I25: =(tbl_raw_data[[#This Row],[Date Actioned]])-(tbl_raw_data[[#This Row],[Date Tagged]]) -> 0.0034722222 | J25: =HOUR(tbl_raw_data[[#This Row],[time_taken]])*60+MINUTE(tbl_raw_data[[#This Row],[time_taken]])+SECOND(tbl_raw_data[[#This Row],[time_taken]])/60 -> 5 | K25: =DATE(YEAR(tbl_raw_data[[#This Row],[Date Actioned]]),MONTH(tbl_raw_data[[#This Row],[Date Actioned]]),DAY(tbl_raw_data[[#This Row],[Date Actioned]])) -> 45137 | L25: =UPPER(TEXT(tbl_raw_data[[#This Row],[updated_date]],"MMMM")) -> JULY | M25: ="WEEK "&IF(ROUNDUP(DAY(tbl_raw_data[[#This Row],[updated_date]])/7,0)=5,4,ROUNDUP(DAY(tbl_raw_data[[#This Row],[updated_date]])/7,0)) -> WEEK 4 | N25: =UPPER(VLOOKUP(tbl_raw_data[[#This Row],[Analyst]],settings!$A$1:$B$15,2,0)) -> ASIF | O25: =TRIM(UPPER(tbl_raw_data[[#This Row],[Outcome]])) -> APPROVE | P25: =TRIM(UPPER(tbl_raw_data[[#This Row],[Queue Name]])) -> CONSUMER EXISTING | Q25: =IF(tbl_raw_data[[#This Row],[time_taken_in_min]]<=settings!$D$2,"SLA_MET","SLA_NOT_MET") -> SLA_MET
A26: 25 | B26: 45137.486 | C26: 45137.49 | D26: APPROVE | E26: Consumer Pre Bureau | F26: QMascarenhas | G26: Approved for 1 handset and 1 MBB | H26: =IF(OR(ISNUMBER(SEARCH("duplicate",G26)), ISNUMBER(SEARCH("previously",G26)), ISNUMBER(SEARCH("previously approved",G26))), "Duplicate Application", IF(OR(ISNUMBER(SEARCH("incorrect",G26)), ISNUMBER(SEARCH("remove", G26))), "Incorrect Details", IF(ISNUMBER(SEARCH("incomplete",G26)), "Incomplete Details", IF(ISNUMBER(SEARCH("overdue",G26)), "Overdue Bill", IF(OR(ISNUMBER(SEARCH("resubmit as", G26)), ISNUMBER(SEARCH("re-submit as", G26))), "Incorrect Queue", IF(OR(ISNUMBER(SEARCH("100",G26)), ISNUMBER(SEARCH("correct", G26)), ISNUMBER(SEARCH("email", G26)), ISNUMBER(SEARCH("please submit", G26)), ISNUMBER(SEARCH("please resubmit",G26)), ISNUMBER(SEARCH("please re-submit", G26)), ISNUMBER(SEARCH("please send", G26))), "Incomplete Details", IF(ISNUMBER(SEARCH("error", G26)), "System Error", "Reason Unknown"))))))) -> Reason Unknown | I26: =(tbl_raw_data[[#This Row],[Date Actioned]])-(tbl_raw_data[[#This Row],[Date Tagged]]) -> 0.0031018518 | J26: =HOUR(tbl_raw_data[[#This Row],[time_taken]])*60+MINUTE(tbl_raw_data[[#This Row],[time_taken]])+SECOND(tbl_raw_data[[#This Row],[time_taken]])/60 -> 4.4666667 | K26: =DATE(YEAR(tbl_raw_data[[#This Row],[Date Actioned]]),MONTH(tbl_raw_data[[#This Row],[Date Actioned]]),DAY(tbl_raw_data[[#This Row],[Date Actioned]])) -> 45137 | L26: =UPPER(TEXT(tbl_raw_data[[#This Row],[updated_date]],"MMMM")) -> JULY | M26: ="WEEK "&IF(ROUNDUP(DAY(tbl_raw_data[[#This Row],[updated_date]])/7,0)=5,4,ROUNDUP(DAY(tbl_raw_data[[#This Row],[updated_date]])/7,0)) -> WEEK 4 | N26: =UPPER(VLOOKUP(tbl_raw_data[[#This Row],[Analyst]],settings!$A$1:$B$15,2,0)) -> QUADIR | O26: =TRIM(UPPER(tbl_raw_data[[#This Row],[Outcome]])) -> APPROVE | P26: =TRIM(UPPER(tbl_raw_data[[#This Row],[Queue Name]])) -> CONSUMER PRE BUREAU | Q26: =IF(tbl_raw_data[[#This Row],[time_taken_in_min]]<=settings!$D$2,"SLA_MET","SLA_NOT_MET") -> SLA_MET
A27: 26 | B27: 45137.487 | C27: 45137.494 | D27: APPROVE | E27: Consumer Pre Bureau | F27: NVaid | G27: Approve | H27: =IF(OR(ISNUMBER(SEARCH("duplicate",G27)), ISNUMBER(SEARCH("previously",G27)), ISNUMBER(SEARCH("previously approved",G27))), "Duplicate Application", IF(OR(ISNUMBER(SEARCH("incorrect",G27)), ISNUMBER(SEARCH("remove", G27))), "Incorrect Details", IF(ISNUMBER(SEARCH("incomplete",G27)), "Incomplete Details", IF(ISNUMBER(SEARCH("overdue",G27)), "Overdue Bill", IF(OR(ISNUMBER(SEARCH("resubmit as", G27)), ISNUMBER(SEARCH("re-submit as", G27))), "Incorrect Queue", IF(OR(ISNUMBER(SEARCH("100",G27)), ISNUMBER(SEARCH("correct", G27)), ISNUMBER(SEARCH("email", G27)), ISNUMBER(SEARCH("please submit", G27)), ISNUMBER(SEARCH("please resubmit",G27)), ISNUMBER(SEARCH("please re-submit", G27)), ISNUMBER(SEARCH("please send", G27))), "Incomplete Details", IF(ISNUMBER(SEARCH("error", G27)), "System Error", "Reason Unknown"))))))) -> Reason Unknown | I27: =(tbl_raw_data[[#This Row],[Date Actioned]])-(tbl_raw_data[[#This Row],[Date Tagged]]) -> 0.007337963 | J27: =HOUR(tbl_raw_data[[#This Row],[time_taken]])*60+MINUTE(tbl_raw_data[[#This Row],[time_taken]])+SECOND(tbl_raw_data[[#This Row],[time_taken]])/60 -> 10.566667 | K27: =DATE(YEAR(tbl_raw_data[[#This Row],[Date Actioned]]),MONTH(tbl_raw_data[[#This Row],[Date Actioned]]),DAY(tbl_raw_data[[#This Row],[Date Actioned]])) -> 45137 | L27: =UPPER(TEXT(tbl_raw_data[[#This Row],[updated_date]],"MMMM")) -> JULY | M27: ="WEEK "&IF(ROUNDUP(DAY(tbl_raw_data[[#This Row],[updated_date]])/7,0)=5,4,ROUNDUP(DAY(tbl_raw_data[[#This Row],[updated_date]])/7,0)) -> WEEK 4 | N27: =UPPER(VLOOKUP(tbl_raw_data[[#This Row],[Analyst]],settings!$A$1:$B$15,2,0)) -> NAVED | O27: =TRIM(UPPER(tbl_raw_data[[#This Row],[Outcome]])) -> APPROVE | P27: =TRIM(UPPER(tbl_raw_data[[#This Row],[Queue Name]])) -> CONSUMER PRE BUREAU | Q27: =IF(tbl_raw_data[[#This Row],[time_taken_in_min]]<=settings!$D$2,"SLA_MET","SLA_NOT_MET") -> SLA_MET
A28: 27 | B28: 45137.491 | C28: 45137.5 | D28: APPROVE | E28: Consumer Existing | F28: QMascarenhas | G28: Approve | H28: =IF(OR(ISNUMBER(SEARCH("duplicate",G28)), ISNUMBER(SEARCH("previously",G28)), ISNUMBER(SEARCH("previously approved",G28))), "Duplicate Application", IF(OR(ISNUMBER(SEARCH("incorrect",G28)), ISNUMBER(SEARCH("remove", G28))), "Incorrect Details", IF(ISNUMBER(SEARCH("incomplete",G28)), "Incomplete Details", IF(ISNUMBER(SEARCH("overdue",G28)), "Overdue Bill", IF(OR(ISNUMBER(SEARCH("resubmit as", G28)), ISNUMBER(SEARCH("re-submit as", G28))), "Incorrect Queue", IF(OR(ISNUMBER(SEARCH("100",G28)), ISNUMBER(SEARCH("correct", G28)), ISNUMBER(SEARCH("email", G28)), ISNUMBER(SEARCH("please submit", G28)), ISNUMBER(SEARCH("please resubmit",G28)), ISNUMBER(SEARCH("please re-submit", G28)), ISNUMBER(SEARCH("please send", G28))), "Incomplete Details", IF(ISNUMBER(SEARCH("error", G28)), "System Error", "Reason Unknown"))))))) -> Reason Unknown | I28: =(tbl_raw_data[[#This Row],[Date Actioned]])-(tbl_raw_data[[#This Row],[Date Tagged]]) -> 0.0089699074 | J28: =HOUR(tbl_raw_data[[#This Row],[time_taken]])*60+MINUTE(tbl_raw_data[[#This Row],[time_taken]])+SECOND(tbl_raw_data[[#This Row],[time_taken]])/60 -> 12.916667 | K28: =DATE(YEAR(tbl_raw_data[[#This Row],[Date Actioned]]),MONTH(tbl_raw_data[[#This Row],[Date Actioned]]),DAY(tbl_raw_data[[#This Row],[Date Actioned]])) -> 45137 | L28: =UPPER(TEXT(tbl_raw_data[[#This Row],[updated_date]],"MMMM")) -> JULY | M28: ="WEEK "&IF(ROUNDUP(DAY(tbl_raw_data[[#This Row],[updated_date]])/7,0)=5,4,ROUNDUP(DAY(tbl_raw_data[[#This Row],[updated_date]])/7,0)) -> WEEK 4 | N28: =UPPER(VLOOKUP(tbl_raw_data[[#This Row],[Analyst]],settings!$A$1:$B$15,2,0)) -> QUADIR | O28: =TRIM(UPPER(tbl_raw_data[[#This Row],[Outcome]])) -> APPROVE | P28: =TRIM(UPPER(tbl_raw_data[[#This Row],[Queue Name]])) -> CONSUMER EXISTING | Q28: =IF(tbl_raw_data[[#This Row],[time_taken_in_min]]<=settings!$D$2,"SLA_MET","SLA_NOT_MET") -> SLA_MET
A29: 28 | B29: 45137.492 | C29: 45137.504 | D29: APPROVE | E29: Consumer Post Bureau | F29: AAkhundpur | G29: Approve | H29: =IF(OR(ISNUMBER(SEARCH("duplicate",G29)), ISNUMBER(SEARCH("previously",G29)), ISNUMBER(SEARCH("previously approved",G29))), "Duplicate Application", IF(OR(ISNUMBER(SEARCH("incorrect",G29)), ISNUMBER(SEARCH("remove", G29))), "Incorrect Details", IF(ISNUMBER(SEARCH("incomplete",G29)), "Incomplete Details", IF(ISNUMBER(SEARCH("overdue",G29)), "Overdue Bill", IF(OR(ISNUMBER(SEARCH("resubmit as", G29)), ISNUMBER(SEARCH("re-submit as", G29))), "Incorrect Queue", IF(OR(ISNUMBER(SEARCH("100",G29)), ISNUMBER(SEARCH("correct", G29)), ISNUMBER(SEARCH("email", G29)), ISNUMBER(SEARCH("please submit", G29)), ISNUMBER(SEARCH("please resubmit",G29)), ISNUMBER(SEARCH("please re-submit", G29)), ISNUMBER(SEARCH("please send", G29))), "Incomplete Details", IF(ISNUMBER(SEARCH("error", G29)), "System Error", "Reason Unknown"))))))) -> Reason Unknown | I29: =(tbl_raw_data[[#This Row],[Date Actioned]])-(tbl_raw_data[[#This Row],[Date Tagged]]) -> 0.012060185 | J29: =HOUR(tbl_raw_data[[#This Row],[time_taken]])*60+MINUTE(tbl_raw_data[[#This Row],[time_taken]])+SECOND(tbl_raw_data[[#This Row],[time_taken]])/60 -> 17.366667 | K29: =DATE(YEAR(tbl_raw_data[[#This Row],[Date Actioned]]),MONTH(tbl_raw_data[[#This Row],[Date Actioned]]),DAY(tbl_raw_data[[#This Row],[Date Actioned]])) -> 45137 | L29: =UPPER(TEXT(tbl_raw_data[[#This Row],[updated_date]],"MMMM")) -> JULY | M29: ="WEEK "&IF(ROUNDUP(DAY(tbl_raw_data[[#This Row],[updated_date]])/7,0)=5,4,ROUNDUP(DAY(tbl_raw_data[[#This Row],[updated_date]])/7,0)) -> WEEK 4 | N29: =UPPER(VLOOKUP(tbl_raw_data[[#This Row],[Analyst]],settings!$A$1:$B$15,2,0)) -> ASIF | O29: =TRIM(UPPER(tbl_raw_data[[#This Row],[Outcome]])) -> APPROVE | P29: =TRIM(UPPER(tbl_raw_data[[#This Row],[Queue Name]])) -> CONSUMER POST BUREAU | Q29: =IF(tbl_raw_data[[#This Row],[time_taken_in_min]]<=settings!$D$2,"SLA_MET","SLA_NOT_MET") -> SLA_MET
A30: 29 | B30: 45137.497 | C30: 45137.509 | D30: APPROVE | E30: Consumer Existing | F30: NBhatia | G30: Approve | H30: =IF(OR(ISNUMBER(SEARCH("duplicate",G30)), ISNUMBER(SEARCH("previously",G30)), ISNUMBER(SEARCH("previously approved",G30))), "Duplicate Application", IF(OR(ISNUMBER(SEARCH("incorrect",G30)), ISNUMBER(SEARCH("remove", G30))), "Incorrect Details", IF(ISNUMBER(SEARCH("incomplete",G30)), "Incomplete Details", IF(ISNUMBER(SEARCH("overdue",G30)), "Overdue Bill", IF(OR(ISNUMBER(SEARCH("resubmit as", G30)), ISNUMBER(SEARCH("re-submit as", G30))), "Incorrect Queue", IF(OR(ISNUMBER(SEARCH("100",G30)), ISNUMBER(SEARCH("correct", G30)), ISNUMBER(SEARCH("email", G30)), ISNUMBER(SEARCH("please submit", G30)), ISNUMBER(SEARCH("please resubmit",G30)), ISNUMBER(SEARCH("please re-submit", G30)), ISNUMBER(SEARCH("please send", G30))), "Incomplete Details", IF(ISNUMBER(SEARCH("error", G30)), "System Error", "Reason Unknown"))))))) -> Reason Unknown | I30: =(tbl_raw_data[[#This Row],[Date Actioned]])-(tbl_raw_data[[#This Row],[Date Tagged]]) -> 0.011527778 | J30: =HOUR(tbl_raw_data[[#This Row],[time_taken]])*60+MINUTE(tbl_raw_data[[#This Row],[time_taken]])+SECOND(tbl_raw_data[[#This Row],[time_taken]])/60 -> 16.6 | K30: =DATE(YEAR(tbl_raw_data[[#This Row],[Date Actioned]]),MONTH(tbl_raw_data[[#This Row],[Date Actioned]]),DAY(tbl_raw_data[[#This Row],[Date Actioned]])) -> 45137 | L30: =UPPER(TEXT(tbl_raw_data[[#This Row],[updated_date]],"MMMM")) -> JULY | M30: ="WEEK "&IF(ROUNDUP(DAY(tbl_raw_data[[#This Row],[updated_date]])/7,0)=5,4,ROUNDUP(DAY(tbl_raw_data[[#This Row],[updated_date]])/7,0)) -> WEEK 4 | N30: =UPPER(VLOOKUP(tbl_raw_data[[#This Row],[Analyst]],settings!$A$1:$B$15,2,0)) -> NITESH | O30: =TRIM(UPPER(tbl_raw_data[[#This Row],[Outcome]])) -> APPROVE | P30: =TRIM(UPPER(tbl_raw_data[[#This Row],[Queue Name]])) -> CONSUMER EXISTING | Q30: =IF(tbl_raw_data[[#This Row],[time_taken_in_min]]<=settings!$D$2,"SLA_MET","SLA_NOT_MET") -> SLA_MET
A31: 30 | B31: 45137.498 | C31: 45137.506 | D31: APPROVE | E31: Consumer Existing | F31: QMascarenhas | G31: Approve | H31: =IF(OR(ISNUMBER(SEARCH("duplicate",G31)), ISNUMBER(SEARCH("previously",G31)), ISNUMBER(SEARCH("previously approved",G31))), "Duplicate Application", IF(OR(ISNUMBER(SEARCH("incorrect",G31)), ISNUMBER(SEARCH("remove", G31))), "Incorrect Details", IF(ISNUMBER(SEARCH("incomplete",G31)), "Incomplete Details", IF(ISNUMBER(SEARCH("overdue",G31)), "Overdue Bill", IF(OR(ISNUMBER(SEARCH("resubmit as", G31)), ISNUMBER(SEARCH("re-submit as", G31))), "Incorrect Queue", IF(OR(ISNUMBER(SEARCH("100",G31)), ISNUMBER(SEARCH("correct", G31)), ISNUMBER(SEARCH("email", G31)), ISNUMBER(SEARCH("please submit", G31)), ISNUMBER(SEARCH("please resubmit",G31)), ISNUMBER(SEARCH("please re-submit", G31)), ISNUMBER(SEARCH("please send", G31))), "Incomplete Details", IF(ISNUMBER(SEARCH("error", G31)), "System Error", "Reason Unknown"))))))) -> Reason Unknown | I31: =(tbl_raw_data[[#This Row],[Date Actioned]])-(tbl_raw_data[[#This Row],[Date Tagged]]) -> 0.0076851852 | J31: =HOUR(tbl_raw_data[[#This Row],[time_taken]])*60+MINUTE(tbl_raw_data[[#This Row],[time_taken]])+SECOND(tbl_raw_data[[#This Row],[time_taken]])/60 -> 11.066667 | K31: =DATE(YEAR(tbl_raw_data[[#This Row],[Date Actioned]]),MONTH(tbl_raw_data[[#This Row],[Date Actioned]]),DAY(tbl_raw_data[[#This Row],[Date Actioned]])) -> 45137 | L31: =UPPER(TEXT(tbl_raw_data[[#This Row],[updated_date]],"MMMM")) -> JULY | M31: ="WEEK "&IF(ROUNDUP(DAY(tbl_raw_data[[#This Row],[updated_date]])/7,0)=5,4,ROUNDUP(DAY(tbl_raw_data[[#This Row],[updated_date]])/7,0)) -> WEEK 4 | N31: =UPPER(VLOOKUP(tbl_raw_data[[#This Row],[Analyst]],settings!$A$1:$B$15,2,0)) -> QUADIR | O31: =TRIM(UPPER(tbl_raw_data[[#This Row],[Outcome]])) -> APPROVE | P31: =TRIM(UPPER(tbl_raw_data[[#This Row],[Queue Name]])) -> CONSUMER EXISTING | Q31: =IF(tbl_raw_data[[#This Row],[time_taken_in_min]]<=settings!$D$2,"SLA_MET","SLA_NOT_MET") -> SLA_MET
A32: 31 | B32: 45137.507 | C32: 45137.516 | D32: APPROVE | E32: Consumer Existing | F32: SBambaras | G32: Approve | H32: =IF(OR(ISNUMBER(SEARCH("duplicate",G32)), ISNUMBER(SEARCH("previously",G32)), ISNUMBER(SEARCH("previously approved",G32))), "Duplicate Application", IF(OR(ISNUMBER(SEARCH("incorrect",G32)), ISNUMBER(SEARCH("remove", G32))), "Incorrect Details", IF(ISNUMBER(SEARCH("incomplete",G32)), "Incomplete Details", IF(ISNUMBER(SEARCH("overdue",G32)), "Overdue Bill", IF(OR(ISNUMBER(SEARCH("resubmit as", G32)), ISNUMBER(SEARCH("re-submit as", G32))), "Incorrect Queue", IF(OR(ISNUMBER(SEARCH("100",G32)), ISNUMBER(SEARCH("correct", G32)), ISNUMBER(SEARCH("email", G32)), ISNUMBER(SEARCH("please submit", G32)), ISNUMBER(SEARCH("please resubmit",G32)), ISNUMBER(SEARCH("please re-submit", G32)), ISNUMBER(SEARCH("please send", G32))), "Incomplete Details", IF(ISNUMBER(SEARCH("error", G32)), "System Error", "Reason Unknown"))))))) -> Reason Unknown | I32: =(tbl_raw_data[[#This Row],[Date Actioned]])-(tbl_raw_data[[#This Row],[Date Tagged]]) -> 0.008587963 | J32: =HOUR(tbl_raw_data[[#This Row],[time_taken]])*60+MINUTE(tbl_raw_data[[#This Row],[time_taken]])+SECOND(tbl_raw_data[[#This Row],[time_taken]])/60 -> 12.366667 | K32: =DATE(YEAR(tbl_raw_data[[#This Row],[Date Actioned]]),MONTH(tbl_raw_data[[#This Row],[Date Actioned]]),DAY(tbl_raw_data[[#This Row],[Date Actioned]])) -> 45137 | L32: =UPPER(TEXT(tbl_raw_data[[#This Row],[updated_date]],"MMMM")) -> JULY | M32: ="WEEK "&IF(ROUNDUP(DAY(tbl_raw_data[[#This Row],[updated_date]])/7,0)=5,4,ROUNDUP(DAY(tbl_raw_data[[#This Row],[updated_date]])/7,0)) -> WEEK 4 | N32: =UPPER(VLOOKUP(tbl_raw_data[[#This Row],[Analyst]],settings!$A$1:$B$15,2,0)) -> SAM | O32: =TRIM(UPPER(tbl_raw_data[[#This Row],[Outcome]])) -> APPROVE | P32: =TRIM(UPPER(tbl_raw_data[[#This Row],[Queue Name]])) -> CONSUMER EXISTING | Q32: =IF(tbl_raw_data[[#This Row],[time_taken_in_min]]<=settings!$D$2,"SLA_MET","SLA_NOT_MET") -> SLA_MET
A33: 32 | B33: 45137.508 | C33: 45137.512 | D33: APPROVE | E33: Consumer Existing | F33: CDcosta | G33: Approve | H33: =IF(OR(ISNUMBER(SEARCH("duplicate",G33)), ISNUMBER(SEARCH("previously",G33)), ISNUMBER(SEARCH("previously approved",G33))), "Duplicate Application", IF(OR(ISNUMBER(SEARCH("incorrect",G33)), ISNUMBER(SEARCH("remove", G33))), "Incorrect Details", IF(ISNUMBER(SEARCH("incomplete",G33)), "Incomplete Details", IF(ISNUMBER(SEARCH("overdue",G33)), "Overdue Bill", IF(OR(ISNUMBER(SEARCH("resubmit as", G33)), ISNUMBER(SEARCH("re-submit as", G33))), "Incorrect Queue", IF(OR(ISNUMBER(SEARCH("100",G33)), ISNUMBER(SEARCH("correct", G33)), ISNUMBER(SEARCH("email", G33)), ISNUMBER(SEARCH("please submit", G33)), ISNUMBER(SEARCH("please resubmit",G33)), ISNUMBER(SEARCH("please re-submit", G33)), ISNUMBER(SEARCH("please send", G33))), "Incomplete Details", IF(ISNUMBER(SEARCH("error", G33)), "System Error", "Reason Unknown"))))))) -> Reason Unknown | I33: =(tbl_raw_data[[#This Row],[Date Actioned]])-(tbl_raw_data[[#This Row],[Date Tagged]]) -> 0.0034722222 | J33: =HOUR(tbl_raw_data[[#This Row],[time_taken]])*60+MINUTE(tbl_raw_data[[#This Row],[time_taken]])+SECOND(tbl_raw_data[[#This Row],[time_taken]])/60 -> 5 | K33: =DATE(YEAR(tbl_raw_data[[#This Row],[Date Actioned]]),MONTH(tbl_raw_data[[#This Row],[Date Actioned]]),DAY(tbl_raw_data[[#This Row],[Date Actioned]])) -> 45137 | L33: =UPPER(TEXT(tbl_raw_data[[#This Row],[updated_date]],"MMMM")) -> JULY | M33: ="WEEK "&IF(ROUNDUP(DAY(tbl_raw_data[[#This Row],[updated_date]])/7,0)=5,4,ROUNDUP(DAY(tbl_raw_data[[#This Row],[updated_date]])/7,0)) -> WEEK 4 | N33: =UPPER(VLOOKUP(tbl_raw_data[[#This Row],[Analyst]],settings!$A$1:$B$15,2,0)) -> CAMROON | O33: =TRIM(UPPER(tbl_raw_data[[#This Row],[Outcome]])) -> APPROVE | P33: =TRIM(UPPER(tbl_raw_data[[#This Row],[Queue Name]])) -> CONSUMER EXISTING | Q33: =IF(tbl_raw_data[[#This Row],[time_taken_in_min]]<=settings!$D$2,"SLA_MET","SLA_NOT_MET") -> SLA_MET
A34: 33 | B34: 45137.509 | C34: 45137.512 | D34: APPROVE | E34: Consumer Existing | F34: QMascarenhas | G34: Approve | H34: =IF(OR(ISNUMBER(SEARCH("duplicate",G34)), ISNUMBER(SEARCH("previously",G34)), ISNUMBER(SEARCH("previously approved",G34))), "Duplicate Application", IF(OR(ISNUMBER(SEARCH("incorrect",G34)), ISNUMBER(SEARCH("remove", G34))), "Incorrect Details", IF(ISNUMBER(SEARCH("incomplete",G34)), "Incomplete Details", IF(ISNUMBER(SEARCH("overdue",G34)), "Overdue Bill", IF(OR(ISNUMBER(SEARCH("resubmit as", G34)), ISNUMBER(SEARCH("re-submit as", G34))), "Incorrect Queue", IF(OR(ISNUMBER(SEARCH("100",G34)), ISNUMBER(SEARCH("correct", G34)), ISNUMBER(SEARCH("email", G34)), ISNUMBER(SEARCH("please submit", G34)), ISNUMBER(SEARCH("please resubmit",G34)), ISNUMBER(SEARCH("please re-submit", G34)), ISNUMBER(SEARCH("please send", G34))), "Incomplete Details", IF(ISNUMBER(SEARCH("error", G34)), "System Error", "Reason Unknown"))))))) -> Reason Unknown | I34: =(tbl_raw_data[[#This Row],[Date Actioned]])-(tbl_raw_data[[#This Row],[Date Tagged]]) -> 0.0033912037 | J34: =HOUR(tbl_raw_data[[#This Row],[time_taken]])*60+MINUTE(tbl_raw_data[[#This Row],[time_taken]])+SECOND(tbl_raw_data[[#This Row],[time_taken]])/60 -> 4.8833333 | K34: =DATE(YEAR(tbl_raw_data[[#This Row],[Date Actioned]]),MONTH(tbl_raw_data[[#This Row],[Date Actioned]]),DAY(tbl_raw_data[[#This Row],[Date Actioned]])) -> 45137 | L34: =UPPER(TEXT(tbl_raw_data[[#This Row],[updated_date]],"MMMM")) -> JULY | M34: ="WEEK "&IF(ROUNDUP(DAY(tbl_raw_data[[#This Row],[updated_date]])/7,0)=5,4,ROUNDUP(DAY(tbl_raw_data[[#This Row],[updated_date]])/7,0)) -> WEEK 4 | N34: =UPPER(VLOOKUP(tbl_raw_data[[#This Row],[Analyst]],settings!$A$1:$B$15,2,0)) -> QUADIR | O34: =TRIM(UPPER(tbl_raw_data[[#This Row],[Outcome]])) -> APPROVE | P34: =TRIM(UPPER(tbl_raw_data[[#This Row],[Queue Name]])) -> CONSUMER EXISTING | Q34: =IF(tbl_raw_data[[#This Row],[time_taken_in_min]]<=settings!$D$2,"SLA_MET","SLA_NOT_MET") -> SLA_MET
... A54: 53 | B54: 45137.58 | C54: 45137.595 | D54: APPROVE | E54: Consumer Existing | F54: AAkhundpur | G54: Approve | H54: =IF(OR(ISNUMBER(SEARCH("duplicate",G54)), ISNUMBER(SEARCH("previously",G54)), ISNUMBER(SEARCH("previously approved",G54))), "Duplicate Application", IF(OR(ISNUMBER(SEARCH("incorrect",G54)), ISNUMBER(SEARCH("remove", G54))), "Incorrect Details", IF(ISNUMBER(SEARCH("incomplete",G54)), "Incomplete Details", IF(ISNUMBER(SEARCH("overdue",G54)), "Overdue Bill", IF(OR(ISNUMBER(SEARCH("resubmit as", G54)), ISNUMBER(SEARCH("re-submit as", G54))), "Incorrect Queue", IF(OR(ISNUMBER(SEARCH("100",G54)), ISNUMBER(SEARCH("correct", G54)), ISNUMBER(SEARCH("email", G54)), ISNUMBER(SEARCH("please submit", G54)), ISNUMBER(SEARCH("please resubmit",G54)), ISNUMBER(SEARCH("please re-submit", G54)), ISNUMBER(SEARCH("please send", G54))), "Incomplete Details", IF(ISNUMBER(SEARCH("error", G54)), "System Error", "Reason Unknown"))))))) -> Reason Unknown | I54: =(tbl_raw_data[[#This Row],[Date Actioned]])-(tbl_raw_data[[#This Row],[Date Tagged]]) -> 0.014884259 | J54: =HOUR(tbl_raw_data[[#This Row],[time_taken]])*60+MINUTE(tbl_raw_data[[#This Row],[time_taken]])+SECOND(tbl_raw_data[[#This Row],[time_taken]])/60 -> 21.433333 | K54: =DATE(YEAR(tbl_raw_data[[#This Row],[Date Actioned]]),MONTH(tbl_raw_data[[#This Row],[Date Actioned]]),DAY(tbl_raw_data[[#This Row],[Date Actioned]])) -> 45137 | L54: =UPPER(TEXT(tbl_raw_data[[#This Row],[updated_date]],"MMMM")) -> JULY | M54: ="WEEK "&IF(ROUNDUP(DAY(tbl_raw_data[[#This Row],[updated_date]])/7,0)=5,4,ROUNDUP(DAY(tbl_raw_data[[#This Row],[updated_date]])/7,0)) -> WEEK 4 | N54: =UPPER(VLOOKUP(tbl_raw_data[[#This Row],[Analyst]],settings!$A$1:$B$15,2,0)) -> ASIF | O54: =TRIM(UPPER(tbl_raw_data[[#This Row],[Outcome]])) -> APPROVE | P54: =TRIM(UPPER(tbl_raw_data[[#This Row],[Queue Name]])) -> CONSUMER EXISTING | Q54: =IF(tbl_raw_data[[#This Row],[time_taken_in_min]]<=settings!$D$2,"SLA_MET","SLA_NOT_MET") -> SLA_NOT_MET
A55: 54 | B55: 45137.582 | C55: 45137.588 | D55: Approve | E55: Consumer Existing | F55: SSyed | H55: =IF(OR(ISNUMBER(SEARCH("duplicate",G55)), ISNUMBER(SEARCH("previously",G55)), ISNUMBER(SEARCH("previously approved",G55))), "Duplicate Application", IF(OR(ISNUMBER(SEARCH("incorrect",G55)), ISNUMBER(SEARCH("remove", G55))), "Incorrect Details", IF(ISNUMBER(SEARCH("incomplete",G55)), "Incomplete Details", IF(ISNUMBER(SEARCH("overdue",G55)), "Overdue Bill", IF(OR(ISNUMBER(SEARCH("resubmit as", G55)), ISNUMBER(SEARCH("re-submit as", G55))), "Incorrect Queue", IF(OR(ISNUMBER(SEARCH("100",G55)), ISNUMBER(SEARCH("correct", G55)), ISNUMBER(SEARCH("email", G55)), ISNUMBER(SEARCH("please submit", G55)), ISNUMBER(SEARCH("please resubmit",G55)), ISNUMBER(SEARCH("please re-submit", G55)), ISNUMBER(SEARCH("please send", G55))), "Incomplete Details", IF(ISNUMBER(SEARCH("error", G55)), "System Error", "Reason Unknown"))))))) -> Reason Unknown | I55: =(tbl_raw_data[[#This Row],[Date Actioned]])-(tbl_raw_data[[#This Row],[Date Tagged]]) -> 0.0052662037 | J55: =HOUR(tbl_raw_data[[#This Row],[time_taken]])*60+MINUTE(tbl_raw_data[[#This Row],[time_taken]])+SECOND(tbl_raw_data[[#This Row],[time_taken]])/60 -> 7.5833333 | K55: =DATE(YEAR(tbl_raw_data[[#This Row],[Date Actioned]]),MONTH(tbl_raw_data[[#This Row],[Date Actioned]]),DAY(tbl_raw_data[[#This Row],[Date Actioned]])) -> 45137 | L55: =UPPER(TEXT(tbl_raw_data[[#This Row],[updated_date]],"MMMM")) -> JULY | M55: ="WEEK "&IF(ROUNDUP(DAY(tbl_raw_data[[#This Row],[updated_date]])/7,0)=5,4,ROUNDUP(DAY(tbl_raw_data[[#This Row],[updated_date]])/7,0)) -> WEEK 4 | N55: =UPPER(VLOOKUP(tbl_raw_data[[#This Row],[Analyst]],settings!$A$1:$B$15,2,0)) -> SHAHID | O55: =TRIM(UPPER(tbl_raw_data[[#This Row],[Outcome]])) -> APPROVE | P55: =TRIM(UPPER(tbl_raw_data[[#This Row],[Queue Name]])) -> CONSUMER EXISTING | Q55: =IF(tbl_raw_data[[#This Row],[time_taken_in_min]]<=settings!$D$2,"SLA_MET","SLA_NOT_MET") -> SLA_MET
A56: 55 | B56: 45137.583 | C56: 45137.595 | D56: Approve | E56: Consumer Post Bureau | F56: SSyed | H56: =IF(OR(ISNUMBER(SEARCH("duplicate",G56)), ISNUMBER(SEARCH("previously",G56)), ISNUMBER(SEARCH("previously approved",G56))), "Duplicate Application", IF(OR(ISNUMBER(SEARCH("incorrect",G56)), ISNUMBER(SEARCH("remove", G56))), "Incorrect Details", IF(ISNUMBER(SEARCH("incomplete",G56)), "Incomplete Details", IF(ISNUMBER(SEARCH("overdue",G56)), "Overdue Bill", IF(OR(ISNUMBER(SEARCH("resubmit as", G56)), ISNUMBER(SEARCH("re-submit as", G56))), "Incorrect Queue", IF(OR(ISNUMBER(SEARCH("100",G56)), ISNUMBER(SEARCH("correct", G56)), ISNUMBER(SEARCH("email", G56)), ISNUMBER(SEARCH("please submit", G56)), ISNUMBER(SEARCH("please resubmit",G56)), ISNUMBER(SEARCH("please re-submit", G56)), ISNUMBER(SEARCH("please send", G56))), "Incomplete Details", IF(ISNUMBER(SEARCH("error", G56)), "System Error", "Reason Unknown"))))))) -> Reason Unknown | I56: =(tbl_raw_data[[#This Row],[Date Actioned]])-(tbl_raw_data[[#This Row],[Date Tagged]]) -> 0.011793981 | J56: =HOUR(tbl_raw_data[[#This Row],[time_taken]])*60+MINUTE(tbl_raw_data[[#This Row],[time_taken]])+SECOND(tbl_raw_data[[#This Row],[time_taken]])/60 -> 16.983333 | K56: =DATE(YEAR(tbl_raw_data[[#This Row],[Date Actioned]]),MONTH(tbl_raw_data[[#This Row],[Date Actioned]]),DAY(tbl_raw_data[[#This Row],[Date Actioned]])) -> 45137 | L56: =UPPER(TEXT(tbl_raw_data[[#This Row],[updated_date]],"MMMM")) -> JULY | M56: ="WEEK "&IF(ROUNDUP(DAY(tbl_raw_data[[#This Row],[updated_date]])/7,0)=5,4,ROUNDUP(DAY(tbl_raw_data[[#This Row],[updated_date]])/7,0)) -> WEEK 4 | N56: =UPPER(VLOOKUP(tbl_raw_data[[#This Row],[Analyst]],settings!$A$1:$B$15,2,0)) -> SHAHID | O56: =TRIM(UPPER(tbl_raw_data[[#This Row],[Outcome]])) -> APPROVE | P56: =TRIM(UPPER(tbl_raw_data[[#This Row],[Queue Name]])) -> CONSUMER POST BUREAU | Q56: =IF(tbl_raw_data[[#This Row],[time_taken_in_min]]<=settings!$D$2,"SLA_MET","SLA_NOT_MET") -> SLA_MET
A57: 56 | B57: 45137.586 | C57: 45137.598 | D57: APPROVE | E57: Consumer Existing | F57: NVaid | G57: Approve | H57: =IF(OR(ISNUMBER(SEARCH("duplicate",G57)), ISNUMBER(SEARCH("previously",G57)), ISNUMBER(SEARCH("previously approved",G57))), "Duplicate Application", IF(OR(ISNUMBER(SEARCH("incorrect",G57)), ISNUMBER(SEARCH("remove", G57))), "Incorrect Details", IF(ISNUMBER(SEARCH("incomplete",G57)), "Incomplete Details", IF(ISNUMBER(SEARCH("overdue",G57)), "Overdue Bill", IF(OR(ISNUMBER(SEARCH("resubmit as", G57)), ISNUMBER(SEARCH("re-submit as", G57))), "Incorrect Queue", IF(OR(ISNUMBER(SEARCH("100",G57)), ISNUMBER(SEARCH("correct", G57)), ISNUMBER(SEARCH("email", G57)), ISNUMBER(SEARCH("please submit", G57)), ISNUMBER(SEARCH("please resubmit",G57)), ISNUMBER(SEARCH("please re-submit", G57)), ISNUMBER(SEARCH("please send", G57))), "Incomplete Details", IF(ISNUMBER(SEARCH("error", G57)), "System Error", "Reason Unknown"))))))) -> Reason Unknown | I57: =(tbl_raw_data[[#This Row],[Date Actioned]])-(tbl_raw_data[[#This Row],[Date Tagged]]) -> 0.011967593 | J57: =HOUR(tbl_raw_data[[#This Row],[time_taken]])*60+MINUTE(tbl_raw_data[[#This Row],[time_taken]])+SECOND(tbl_raw_data[[#This Row],[time_taken]])/60 -> 17.233333 | K57: =DATE(YEAR(tbl_raw_data[[#This Row],[Date Actioned]]),MONTH(tbl_raw_data[[#This Row],[Date Actioned]]),DAY(tbl_raw_data[[#This Row],[Date Actioned]])) -> 45137 | L57: =UPPER(TEXT(tbl_raw_data[[#This Row],[updated_date]],"MMMM")) -> JULY | M57: ="WEEK "&IF(ROUNDUP(DAY(tbl_raw_data[[#This Row],[updated_date]])/7,0)=5,4,ROUNDUP(DAY(tbl_raw_data[[#This Row],[updated_date]])/7,0)) -> WEEK 4 | N57: =UPPER(VLOOKUP(tbl_raw_data[[#This Row],[Analyst]],settings!$A$1:$B$15,2,0)) -> NAVED | O57: =TRIM(UPPER(tbl_raw_data[[#This Row],[Outcome]])) -> APPROVE | P57: =TRIM(UPPER(tbl_raw_data[[#This Row],[Queue Name]])) -> CONSUMER EXISTING | Q57: =IF(tbl_raw_data[[#This Row],[time_taken_in_min]]<=settings!$D$2,"SLA_MET","SLA_NOT_MET") -> SLA_MET
A58: 57 | B58: 45137.587 | C58: 45137.597 | D58: APPROVE | E58: Consumer Existing | F58: CDcosta | G58: Approve | H58: =IF(OR(ISNUMBER(SEARCH("duplicate",G58)), ISNUMBER(SEARCH("previously",G58)), ISNUMBER(SEARCH("previously approved",G58))), "Duplicate Application", IF(OR(ISNUMBER(SEARCH("incorrect",G58)), ISNUMBER(SEARCH("remove", G58))), "Incorrect Details", IF(ISNUMBER(SEARCH("incomplete",G58)), "Incomplete Details", IF(ISNUMBER(SEARCH("overdue",G58)), "Overdue Bill", IF(OR(ISNUMBER(SEARCH("resubmit as", G58)), ISNUMBER(SEARCH("re-submit as", G58))), "Incorrect Queue", IF(OR(ISNUMBER(SEARCH("100",G58)), ISNUMBER(SEARCH("correct", G58)), ISNUMBER(SEARCH("email", G58)), ISNUMBER(SEARCH("please submit", G58)), ISNUMBER(SEARCH("please resubmit",G58)), ISNUMBER(SEARCH("please re-submit", G58)), ISNUMBER(SEARCH("please send", G58))), "Incomplete Details", IF(ISNUMBER(SEARCH("error", G58)), "System Error", "Reason Unknown"))))))) -> Reason Unknown | I58: =(tbl_raw_data[[#This Row],[Date Actioned]])-(tbl_raw_data[[#This Row],[Date Tagged]]) -> 0.010196759 | J58: =HOUR(tbl_raw_data[[#This Row],[time_taken]])*60+MINUTE(tbl_raw_data[[#This Row],[time_taken]])+SECOND(tbl_raw_data[[#This Row],[time_taken]])/60 -> 14.683333 | K58: =DATE(YEAR(tbl_raw_data[[#This Row],[Date Actioned]]),MONTH(tbl_raw_data[[#This Row],[Date Actioned]]),DAY(tbl_raw_data[[#This Row],[Date Actioned]])) -> 45137 | L58: =UPPER(TEXT(tbl_raw_data[[#This Row],[updated_date]],"MMMM")) -> JULY | M58: ="WEEK "&IF(ROUNDUP(DAY(tbl_raw_data[[#This Row],[updated_date]])/7,0)=5,4,ROUNDUP(DAY(tbl_raw_data[[#This Row],[updated_date]])/7,0)) -> WEEK 4 | N58: =UPPER(VLOOKUP(tbl_raw_data[[#This Row],[Analyst]],settings!$A$1:$B$15,2,0)) -> CAMROON | O58: =TRIM(UPPER(tbl_raw_data[[#This Row],[Outcome]])) -> APPROVE | P58: =TRIM(UPPER(tbl_raw_data[[#This Row],[Queue Name]])) -> CONSUMER EXISTING | Q58: =IF(tbl_raw_data[[#This Row],[time_taken_in_min]]<=settings!$D$2,"SLA_MET","SLA_NOT_MET") -> SLA_MET
A59: 58 | B59: 45137.594 | C59: 45137.603 | D59: APPROVE | E59: Consumer Post Bureau | F59: NBhatia | G59: Approve | H59: =IF(OR(ISNUMBER(SEARCH("duplicate",G59)), ISNUMBER(SEARCH("previously",G59)), ISNUMBER(SEARCH("previously approved",G59))), "Duplicate Application", IF(OR(ISNUMBER(SEARCH("incorrect",G59)), ISNUMBER(SEARCH("remove", G59))), "Incorrect Details", IF(ISNUMBER(SEARCH("incomplete",G59)), "Incomplete Details", IF(ISNUMBER(SEARCH("overdue",G59)), "Overdue Bill", IF(OR(ISNUMBER(SEARCH("resubmit as", G59)), ISNUMBER(SEARCH("re-submit as", G59))), "Incorrect Queue", IF(OR(ISNUMBER(SEARCH("100",G59)), ISNUMBER(SEARCH("correct", G59)), ISNUMBER(SEARCH("email", G59)), ISNUMBER(SEARCH("please submit", G59)), ISNUMBER(SEARCH("please resubmit",G59)), ISNUMBER(SEARCH("please re-submit", G59)), ISNUMBER(SEARCH("please send", G59))), "Incomplete Details", IF(ISNUMBER(SEARCH("error", G59)), "System Error", "Reason Unknown"))))))) -> Reason Unknown | I59: =(tbl_raw_data[[#This Row],[Date Actioned]])-(tbl_raw_data[[#This Row],[Date Tagged]]) -> 0.0095949074 | J59: =HOUR(tbl_raw_data[[#This Row],[time_taken]])*60+MINUTE(tbl_raw_data[[#This Row],[time_taken]])+SECOND(tbl_raw_data[[#This Row],[time_taken]])/60 -> 13.816667 | K59: =DATE(YEAR(tbl_raw_data[[#This Row],[Date Actioned]]),MONTH(tbl_raw_data[[#This Row],[Date Actioned]]),DAY(tbl_raw_data[[#This Row],[Date Actioned]])) -> 45137 | L59: =UPPER(TEXT(tbl_raw_data[[#This Row],[updated_date]],"MMMM")) -> JULY | M59: ="WEEK "&IF(ROUNDUP(DAY(tbl_raw_data[[#This Row],[updated_date]])/7,0)=5,4,ROUNDUP(DAY(tbl_raw_data[[#This Row],[updated_date]])/7,0)) -> WEEK 4 | N59: =UPPER(VLOOKUP(tbl_raw_data[[#This Row],[Analyst]],settings!$A$1:$B$15,2,0)) -> NITESH | O59: =TRIM(UPPER(tbl_raw_data[[#This Row],[Outcome]])) -> APPROVE | P59: =TRIM(UPPER(tbl_raw_data[[#This Row],[Queue Name]])) -> CONSUMER POST BUREAU | Q59: =IF(tbl_raw_data[[#This Row],[time_taken_in_min]]<=settings!$D$2,"SLA_MET","SLA_NOT_MET") -> SLA_MET
A60: 59 | B60: 45137.597 | C60: 45137.601 | D60: APPROVE | E60: Consumer Post Bureau | F60: SBambaras | G60: Approved only with outright purchase of handset or USIM only | H60: =IF(OR(ISNUMBER(SEARCH("duplicate",G60)), ISNUMBER(SEARCH("previously",G60)), ISNUMBER(SEARCH("previously approved",G60))), "Duplicate Application", IF(OR(ISNUMBER(SEARCH("incorrect",G60)), ISNUMBER(SEARCH("remove", G60))), "Incorrect Details", IF(ISNUMBER(SEARCH("incomplete",G60)), "Incomplete Details", IF(ISNUMBER(SEARCH("overdue",G60)), "Overdue Bill", IF(OR(ISNUMBER(SEARCH("resubmit as", G60)), ISNUMBER(SEARCH("re-submit as", G60))), "Incorrect Queue", IF(OR(ISNUMBER(SEARCH("100",G60)), ISNUMBER(SEARCH("correct", G60)), ISNUMBER(SEARCH("email", G60)), ISNUMBER(SEARCH("please submit", G60)), ISNUMBER(SEARCH("please resubmit",G60)), ISNUMBER(SEARCH("please re-submit", G60)), ISNUMBER(SEARCH("please send", G60))), "Incomplete Details", IF(ISNUMBER(SEARCH("error", G60)), "System Error", "Reason Unknown"))))))) -> Reason Unknown | I60: =(tbl_raw_data[[#This Row],[Date Actioned]])-(tbl_raw_data[[#This Row],[Date Tagged]]) -> 0.0040277778 | J60: =HOUR(tbl_raw_data[[#This Row],[time_taken]])*60+MINUTE(tbl_raw_data[[#This Row],[time_taken]])+SECOND(tbl_raw_data[[#This Row],[time_taken]])/60 -> 5.8 | K60: =DATE(YEAR(tbl_raw_data[[#This Row],[Date Actioned]]),MONTH(tbl_raw_data[[#This Row],[Date Actioned]]),DAY(tbl_raw_data[[#This Row],[Date Actioned]])) -> 45137 | L60: =UPPER(TEXT(tbl_raw_data[[#This Row],[updated_date]],"MMMM")) -> JULY | M60: ="WEEK "&IF(ROUNDUP(DAY(tbl_raw_data[[#This Row],[updated_date]])/7,0)=5,4,ROUNDUP(DAY(tbl_raw_data[[#This Row],[updated_date]])/7,0)) -> WEEK 4 | N60: =UPPER(VLOOKUP(tbl_raw_data[[#This Row],[Analyst]],settings!$A$1:$B$15,2,0)) -> SAM | O60: =TRIM(UPPER(tbl_raw_data[[#This Row],[Outcome]])) -> APPROVE | P60: =TRIM(UPPER(tbl_raw_data[[#This Row],[Queue Name]])) -> CONSUMER POST BUREAU | Q60: =IF(tbl_raw_data[[#This Row],[time_taken_in_min]]<=settings!$D$2,"SLA_MET","SLA_NOT_MET") -> SLA_MET
A61: 60 | B61: 45137.597 | C61: 45137.612 | D61: APPROVE | E61: Consumer Existing | F61: QMascarenhas | G61: Approve | H61: =IF(OR(ISNUMBER(SEARCH("duplicate",G61)), ISNUMBER(SEARCH("previously",G61)), ISNUMBER(SEARCH("previously approved",G61))), "Duplicate Application", IF(OR(ISNUMBER(SEARCH("incorrect",G61)), ISNUMBER(SEARCH("remove", G61))), "Incorrect Details", IF(ISNUMBER(SEARCH("incomplete",G61)), "Incomplete Details", IF(ISNUMBER(SEARCH("overdue",G61)), "Overdue Bill", IF(OR(ISNUMBER(SEARCH("resubmit as", G61)), ISNUMBER(SEARCH("re-submit as", G61))), "Incorrect Queue", IF(OR(ISNUMBER(SEARCH("100",G61)), ISNUMBER(SEARCH("correct", G61)), ISNUMBER(SEARCH("email", G61)), ISNUMBER(SEARCH("please submit", G61)), ISNUMBER(SEARCH("please resubmit",G61)), ISNUMBER(SEARCH("please re-submit", G61)), ISNUMBER(SEARCH("please send", G61))), "Incomplete Details", IF(ISNUMBER(SEARCH("error", G61)), "System Error", "Reason Unknown"))))))) -> Reason Unknown | I61: =(tbl_raw_data[[#This Row],[Date Actioned]])-(tbl_raw_data[[#This Row],[Date Tagged]]) -> 0.015034722 | J61: =HOUR(tbl_raw_data[[#This Row],[time_taken]])*60+MINUTE(tbl_raw_data[[#This Row],[time_taken]])+SECOND(tbl_raw_data[[#This Row],[time_taken]])/60 -> 21.65 | K61: =DATE(YEAR(tbl_raw_data[[#This Row],[Date Actioned]]),MONTH(tbl_raw_data[[#This Row],[Date Actioned]]),DAY(tbl_raw_data[[#This Row],[Date Actioned]])) -> 45137 | L61: =UPPER(TEXT(tbl_raw_data[[#This Row],[updated_date]],"MMMM")) -> JULY | M61: ="WEEK "&IF(ROUNDUP(DAY(tbl_raw_data[[#This Row],[updated_date]])/7,0)=5,4,ROUNDUP(DAY(tbl_raw_data[[#This Row],[updated_date]])/7,0)) -> WEEK 4 | N61: =UPPER(VLOOKUP(tbl_raw_data[[#This Row],[Analyst]],settings!$A$1:$B$15,2,0)) -> QUADIR | O61: =TRIM(UPPER(tbl_raw_data[[#This Row],[Outcome]])) -> APPROVE | P61: =TRIM(UPPER(tbl_raw_data[[#This Row],[Queue Name]])) -> CONSUMER EXISTING | Q61: =IF(tbl_raw_data[[#This Row],[time_taken_in_min]]<=settings!$D$2,"SLA_MET","SLA_NOT_MET") -> SLA_NOT_MET
A62: 61 | B62: 45137.599 | C62: 45137.603 | D62: APPROVE | E62: Consumer Post Bureau | F62: CDcosta | G62: Approved only with outright purchase of handset or USIM only | H62: =IF(OR(ISNUMBER(SEARCH("duplicate",G62)), ISNUMBER(SEARCH("previously",G62)), ISNUMBER(SEARCH("previously approved",G62))), "Duplicate Application", IF(OR(ISNUMBER(SEARCH("incorrect",G62)), ISNUMBER(SEARCH("remove", G62))), "Incorrect Details", IF(ISNUMBER(SEARCH("incomplete",G62)), "Incomplete Details", IF(ISNUMBER(SEARCH("overdue",G62)), "Overdue Bill", IF(OR(ISNUMBER(SEARCH("resubmit as", G62)), ISNUMBER(SEARCH("re-submit as", G62))), "Incorrect Queue", IF(OR(ISNUMBER(SEARCH("100",G62)), ISNUMBER(SEARCH("correct", G62)), ISNUMBER(SEARCH("email", G62)), ISNUMBER(SEARCH("please submit", G62)), ISNUMBER(SEARCH("please resubmit",G62)), ISNUMBER(SEARCH("please re-submit", G62)), ISNUMBER(SEARCH("please send", G62))), "Incomplete Details", IF(ISNUMBER(SEARCH("error", G62)), "System Error", "Reason Unknown"))))))) -> Reason Unknown | I62: =(tbl_raw_data[[#This Row],[Date Actioned]])-(tbl_raw_data[[#This Row],[Date Tagged]]) -> 0.0041666667 | J62: =HOUR(tbl_raw_data[[#This Row],[time_taken]])*60+MINUTE(tbl_raw_data[[#This Row],[time_taken]])+SECOND(tbl_raw_data[[#This Row],[time_taken]])/60 -> 6 | K62: =DATE(YEAR(tbl_raw_data[[#This Row],[Date Actioned]]),MONTH(tbl_raw_data[[#This Row],[Date Actioned]]),DAY(tbl_raw_data[[#This Row],[Date Actioned]])) -> 45137 | L62: =UPPER(TEXT(tbl_raw_data[[#This Row],[updated_date]],"MMMM")) -> JULY | M62: ="WEEK "&IF(ROUNDUP(DAY(tbl_raw_data[[#This Row],[updated_date]])/7,0)=5,4,ROUNDUP(DAY(tbl_raw_data[[#This Row],[updated_date]])/7,0)) -> WEEK 4 | N62: =UPPER(VLOOKUP(tbl_raw_data[[#This Row],[Analyst]],settings!$A$1:$B$15,2,0)) -> CAMROON | O62: =TRIM(UPPER(tbl_raw_data[[#This Row],[Outcome]])) -> APPROVE | P62: =TRIM(UPPER(tbl_raw_data[[#This Row],[Queue Name]])) -> CONSUMER POST BUREAU | Q62: =IF(tbl_raw_data[[#This Row],[time_taken_in_min]]<=settings!$D$2,"SLA_MET","SLA_NOT_MET") -> SLA_MET
A63: 62 | B63: 45137.6 | C63: 45137.603 | D63: Approve | E63: Consumer Existing | F63: SSyed | H63: =IF(OR(ISNUMBER(SEARCH("duplicate",G63)), ISNUMBER(SEARCH("previously",G63)), ISNUMBER(SEARCH("previously approved",G63))), "Duplicate Application", IF(OR(ISNUMBER(SEARCH("incorrect",G63)), ISNUMBER(SEARCH("remove", G63))), "Incorrect Details", IF(ISNUMBER(SEARCH("incomplete",G63)), "Incomplete Details", IF(ISNUMBER(SEARCH("overdue",G63)), "Overdue Bill", IF(OR(ISNUMBER(SEARCH("resubmit as", G63)), ISNUMBER(SEARCH("re-submit as", G63))), "Incorrect Queue", IF(OR(ISNUMBER(SEARCH("100",G63)), ISNUMBER(SEARCH("correct", G63)), ISNUMBER(SEARCH("email", G63)), ISNUMBER(SEARCH("please submit", G63)), ISNUMBER(SEARCH("please resubmit",G63)), ISNUMBER(SEARCH("please re-submit", G63)), ISNUMBER(SEARCH("please send", G63))), "Incomplete Details", IF(ISNUMBER(SEARCH("error", G63)), "System Error", "Reason Unknown"))))))) -> Reason Unknown | I63: =(tbl_raw_data[[#This Row],[Date Actioned]])-(tbl_raw_data[[#This Row],[Date Tagged]]) -> 0.0031712963 | J63: =HOUR(tbl_raw_data[[#This Row],[time_taken]])*60+MINUTE(tbl_raw_data[[#This Row],[time_taken]])+SECOND(tbl_raw_data[[#This Row],[time_taken]])/60 -> 4.5666667 | K63: =DATE(YEAR(tbl_raw_data[[#This Row],[Date Actioned]]),MONTH(tbl_raw_data[[#This Row],[Date Actioned]]),DAY(tbl_raw_data[[#This Row],[Date Actioned]])) -> 45137 | L63: =UPPER(TEXT(tbl_raw_data[[#This Row],[updated_date]],"MMMM")) -> JULY | M63: ="WEEK "&IF(ROUNDUP(DAY(tbl_raw_data[[#This Row],[updated_date]])/7,0)=5,4,ROUNDUP(DAY(tbl_raw_data[[#This Row],[updated_date]])/7,0)) -> WEEK 4 | N63: =UPPER(VLOOKUP(tbl_raw_data[[#This Row],[Analyst]],settings!$A$1:$B$15,2,0)) -> SHAHID | O63: =TRIM(UPPER(tbl_raw_data[[#This Row],[Outcome]])) -> APPROVE | P63: =TRIM(UPPER(tbl_raw_data[[#This Row],[Queue Name]])) -> CONSUMER EXISTING | Q63: =IF(tbl_raw_data[[#This Row],[time_taken_in_min]]<=settings!$D$2,"SLA_MET","SLA_NOT_MET") -> SLA_MET
A64: 63 | B64: 45137.6 | C64: 45137.607 | D64: APPROVE | E64: Consumer Post Bureau | F64: RBose | G64: Approve | H64: =IF(OR(ISNUMBER(SEARCH("duplicate",G64)), ISNUMBER(SEARCH("previously",G64)), ISNUMBER(SEARCH("previously approved",G64))), "Duplicate Application", IF(OR(ISNUMBER(SEARCH("incorrect",G64)), ISNUMBER(SEARCH("remove", G64))), "Incorrect Details", IF(ISNUMBER(SEARCH("incomplete",G64)), "Incomplete Details", IF(ISNUMBER(SEARCH("overdue",G64)), "Overdue Bill", IF(OR(ISNUMBER(SEARCH("resubmit as", G64)), ISNUMBER(SEARCH("re-submit as", G64))), "Incorrect Queue", IF(OR(ISNUMBER(SEARCH("100",G64)), ISNUMBER(SEARCH("correct", G64)), ISNUMBER(SEARCH("email", G64)), ISNUMBER(SEARCH("please submit", G64)), ISNUMBER(SEARCH("please resubmit",G64)), ISNUMBER(SEARCH("please re-submit", G64)), ISNUMBER(SEARCH("please send", G64))), "Incomplete Details", IF(ISNUMBER(SEARCH("error", G64)), "System Error", "Reason Unknown"))))))) -> Reason Unknown | I64: =(tbl_raw_data[[#This Row],[Date Actioned]])-(tbl_raw_data[[#This Row],[Date Tagged]]) -> 0.0065740741 | J64: =HOUR(tbl_raw_data[[#This Row],[time_taken]])*60+MINUTE(tbl_raw_data[[#This Row],[time_taken]])+SECOND(tbl_raw_data[[#This Row],[time_taken]])/60 -> 9.4666667 | K64: =DATE(YEAR(tbl_raw_data[[#This Row],[Date Actioned]]),MONTH(tbl_raw_data[[#This Row],[Date Actioned]]),DAY(tbl_raw_data[[#This Row],[Date Actioned]])) -> 45137 | L64: =UPPER(TEXT(tbl_raw_data[[#This Row],[updated_date]],"MMMM")) -> JULY | M64: ="WEEK "&IF(ROUNDUP(DAY(tbl_raw_data[[#This Row],[updated_date]])/7,0)=5,4,ROUNDUP(DAY(tbl_raw_data[[#This Row],[updated_date]])/7,0)) -> WEEK 4 | N64: =UPPER(VLOOKUP(tbl_raw_data[[#This Row],[Analyst]],settings!$A$1:$B$15,2,0)) -> ROHAN | O64: =TRIM(UPPER(tbl_raw_data[[#This Row],[Outcome]])) -> APPROVE | P64: =TRIM(UPPER(tbl_raw_data[[#This Row],[Queue Name]])) -> CONSUMER POST BUREAU | Q64: =IF(tbl_raw_data[[#This Row],[time_taken_in_min]]<=settings!$D$2,"SLA_MET","SLA_NOT_MET") -> SLA_MET
A65: 64 | B65: 45137.601 | C65: 45137.608 | D65: APPROVE | E65: Consumer Existing | F65: SBambaras | G65: Approve | H65: =IF(OR(ISNUMBER(SEARCH("duplicate",G65)), ISNUMBER(SEARCH("previously",G65)), ISNUMBER(SEARCH("previously approved",G65))), "Duplicate Application", IF(OR(ISNUMBER(SEARCH("incorrect",G65)), ISNUMBER(SEARCH("remove", G65))), "Incorrect Details", IF(ISNUMBER(SEARCH("incomplete",G65)), "Incomplete Details", IF(ISNUMBER(SEARCH("overdue",G65)), "Overdue Bill", IF(OR(ISNUMBER(SEARCH("resubmit as", G65)), ISNUMBER(SEARCH("re-submit as", G65))), "Incorrect Queue", IF(OR(ISNUMBER(SEARCH("100",G65)), ISNUMBER(SEARCH("correct", G65)), ISNUMBER(SEARCH("email", G65)), ISNUMBER(SEARCH("please submit", G65)), ISNUMBER(SEARCH("please resubmit",G65)), ISNUMBER(SEARCH("please re-submit", G65)), ISNUMBER(SEARCH("please send", G65))), "Incomplete Details", IF(ISNUMBER(SEARCH("error", G65)), "System Error", "Reason Unknown"))))))) -> Reason Unknown | I65: =(tbl_raw_data[[#This Row],[Date Actioned]])-(tbl_raw_data[[#This Row],[Date Tagged]]) -> 0.0071296296 | J65: =HOUR(tbl_raw_data[[#This Row],[time_taken]])*60+MINUTE(tbl_raw_data[[#This Row],[time_taken]])+SECOND(tbl_raw_data[[#This Row],[time_taken]])/60 -> 10.266667 | K65: =DATE(YEAR(tbl_raw_data[[#This Row],[Date Actioned]]),MONTH(tbl_raw_data[[#This Row],[Date Actioned]]),DAY(tbl_raw_data[[#This Row],[Date Actioned]])) -> 45137 | L65: =UPPER(TEXT(tbl_raw_data[[#This Row],[updated_date]],"MMMM")) -> JULY | M65: ="WEEK "&IF(ROUNDUP(DAY(tbl_raw_data[[#This Row],[updated_date]])/7,0)=5,4,ROUNDUP(DAY(tbl_raw_data[[#This Row],[updated_date]])/7,0)) -> WEEK 4 | N65: =UPPER(VLOOKUP(tbl_raw_data[[#This Row],[Analyst]],settings!$A$1:$B$15,2,0)) -> SAM | O65: =TRIM(UPPER(tbl_raw_data[[#This Row],[Outcome]])) -> APPROVE | P65: =TRIM(UPPER(tbl_raw_data[[#This Row],[Queue Name]])) -> CONSUMER EXISTING | Q65: =IF(tbl_raw_data[[#This Row],[time_taken_in_min]]<=settings!$D$2,"SLA_MET","SLA_NOT_MET") -> SLA_MET
A66: 65 | B66: 45137.605 | C66: 45137.609 | D66: APPROVE | E66: Consumer Pre Bureau | F66: NVaid | G66: Direct debit to credit card / bank account only | H66: =IF(OR(ISNUMBER(SEARCH("duplicate",G66)), ISNUMBER(SEARCH("previously",G66)), ISNUMBER(SEARCH("previously approved",G66))), "Duplicate Application", IF(OR(ISNUMBER(SEARCH("incorrect",G66)), ISNUMBER(SEARCH("remove", G66))), "Incorrect Details", IF(ISNUMBER(SEARCH("incomplete",G66)), "Incomplete Details", IF(ISNUMBER(SEARCH("overdue",G66)), "Overdue Bill", IF(OR(ISNUMBER(SEARCH("resubmit as", G66)), ISNUMBER(SEARCH("re-submit as", G66))), "Incorrect Queue", IF(OR(ISNUMBER(SEARCH("100",G66)), ISNUMBER(SEARCH("correct", G66)), ISNUMBER(SEARCH("email", G66)), ISNUMBER(SEARCH("please submit", G66)), ISNUMBER(SEARCH("please resubmit",G66)), ISNUMBER(SEARCH("please re-submit", G66)), ISNUMBER(SEARCH("please send", G66))), "Incomplete Details", IF(ISNUMBER(SEARCH("error", G66)), "System Error", "Reason Unknown"))))))) -> Reason Unknown | I66: =(tbl_raw_data[[#This Row],[Date Actioned]])-(tbl_raw_data[[#This Row],[Date Tagged]]) -> 0.0045138889 | J66: =HOUR(tbl_raw_data[[#This Row],[time_taken]])*60+MINUTE(tbl_raw_data[[#This Row],[time_taken]])+SECOND(tbl_raw_data[[#This Row],[time_taken]])/60 -> 6.5 | K66: =DATE(YEAR(tbl_raw_data[[#This Row],[Date Actioned]]),MONTH(tbl_raw_data[[#This Row],[Date Actioned]]),DAY(tbl_raw_data[[#This Row],[Date Actioned]])) -> 45137 | L66: =UPPER(TEXT(tbl_raw_data[[#This Row],[updated_date]],"MMMM")) -> JULY | M66: ="WEEK "&IF(ROUNDUP(DAY(tbl_raw_data[[#This Row],[updated_date]])/7,0)=5,4,ROUNDUP(DAY(tbl_raw_data[[#This Row],[updated_date]])/7,0)) -> WEEK 4 | N66: =UPPER(VLOOKUP(tbl_raw_data[[#This Row],[Analyst]],settings!$A$1:$B$15,2,0)) -> NAVED | O66: =TRIM(UPPER(tbl_raw_data[[#This Row],[Outcome]])) -> APPROVE | P66: =TRIM(UPPER(tbl_raw_data[[#This Row],[Queue Name]])) -> CONSUMER PRE BUREAU | Q66: =IF(tbl_raw_data[[#This Row],[time_taken_in_min]]<=settings!$D$2,"SLA_MET","SLA_NOT_MET") -> SLA_MET
A67: 66 | B67: 45137.605 | C67: 45137.612 | D67: APPROVE | E67: Consumer Existing | F67: CDcosta | G67: Approved for 2 sim-only services (1 voice + 1 MBB) | H67: =IF(OR(ISNUMBER(SEARCH("duplicate",G67)), ISNUMBER(SEARCH("previously",G67)), ISNUMBER(SEARCH("previously approved",G67))), "Duplicate Application", IF(OR(ISNUMBER(SEARCH("incorrect",G67)), ISNUMBER(SEARCH("remove", G67))), "Incorrect Details", IF(ISNUMBER(SEARCH("incomplete",G67)), "Incomplete Details", IF(ISNUMBER(SEARCH("overdue",G67)), "Overdue Bill", IF(OR(ISNUMBER(SEARCH("resubmit as", G67)), ISNUMBER(SEARCH("re-submit as", G67))), "Incorrect Queue", IF(OR(ISNUMBER(SEARCH("100",G67)), ISNUMBER(SEARCH("correct", G67)), ISNUMBER(SEARCH("email", G67)), ISNUMBER(SEARCH("please submit", G67)), ISNUMBER(SEARCH("please resubmit",G67)), ISNUMBER(SEARCH("please re-submit", G67)), ISNUMBER(SEARCH("please send", G67))), "Incomplete Details", IF(ISNUMBER(SEARCH("error", G67)), "System Error", "Reason Unknown"))))))) -> Reason Unknown | I67: =(tbl_raw_data[[#This Row],[Date Actioned]])-(tbl_raw_data[[#This Row],[Date Tagged]]) -> 0.0064814815 | J67: =HOUR(tbl_raw_data[[#This Row],[time_taken]])*60+MINUTE(tbl_raw_data[[#This Row],[time_taken]])+SECOND(tbl_raw_data[[#This Row],[time_taken]])/60 -> 9.3333333 | K67: =DATE(YEAR(tbl_raw_data[[#This Row],[Date Actioned]]),MONTH(tbl_raw_data[[#This Row],[Date Actioned]]),DAY(tbl_raw_data[[#This Row],[Date Actioned]])) -> 45137 | L67: =UPPER(TEXT(tbl_raw_data[[#This Row],[updated_date]],"MMMM")) -> JULY | M67: ="WEEK "&IF(ROUNDUP(DAY(tbl_raw_data[[#This Row],[updated_date]])/7,0)=5,4,ROUNDUP(DAY(tbl_raw_data[[#This Row],[updated_date]])/7,0)) -> WEEK 4 | N67: =UPPER(VLOOKUP(tbl_raw_data[[#This Row],[Analyst]],settings!$A$1:$B$15,2,0)) -> CAMROON | O67: =TRIM(UPPER(tbl_raw_data[[#This Row],[Outcome]])) -> APPROVE | P67: =TRIM(UPPER(tbl_raw_data[[#This Row],[Queue Name]])) -> CONSUMER EXISTING | Q67: =IF(tbl_raw_data[[#This Row],[time_taken_in_min]]<=settings!$D$2,"SLA_MET","SLA_NOT_MET") -> SLA_MET
A68: 67 | B68: 45137.607 | C68: 45137.609 | D68: APPROVE | E68: Consumer Post Bureau | F68: AAkhundpur | G68: Approved only with outright purchase of handset or USIM only | H68: =IF(OR(ISNUMBER(SEARCH("duplicate",G68)), ISNUMBER(SEARCH("previously",G68)), ISNUMBER(SEARCH("previously approved",G68))), "Duplicate Application", IF(OR(ISNUMBER(SEARCH("incorrect",G68)), ISNUMBER(SEARCH("remove", G68))), "Incorrect Details", IF(ISNUMBER(SEARCH("incomplete",G68)), "Incomplete Details", IF(ISNUMBER(SEARCH("overdue",G68)), "Overdue Bill", IF(OR(ISNUMBER(SEARCH("resubmit as", G68)), ISNUMBER(SEARCH("re-submit as", G68))), "Incorrect Queue", IF(OR(ISNUMBER(SEARCH("100",G68)), ISNUMBER(SEARCH("correct", G68)), ISNUMBER(SEARCH("email", G68)), ISNUMBER(SEARCH("please submit", G68)), ISNUMBER(SEARCH("please resubmit",G68)), ISNUMBER(SEARCH("please re-submit", G68)), ISNUMBER(SEARCH("please send", G68))), "Incomplete Details", IF(ISNUMBER(SEARCH("error", G68)), "System Error", "Reason Unknown"))))))) -> Reason Unknown | I68: =(tbl_raw_data[[#This Row],[Date Actioned]])-(tbl_raw_data[[#This Row],[Date Tagged]]) -> 0.0021180556 | J68: =HOUR(tbl_raw_data[[#This Row],[time_taken]])*60+MINUTE(tbl_raw_data[[#This Row],[time_taken]])+SECOND(tbl_raw_data[[#This Row],[time_taken]])/60 -> 3.05 | K68: =DATE(YEAR(tbl_raw_data[[#This Row],[Date Actioned]]),MONTH(tbl_raw_data[[#This Row],[Date Actioned]]),DAY(tbl_raw_data[[#This Row],[Date Actioned]])) -> 45137 | L68: =UPPER(TEXT(tbl_raw_data[[#This Row],[updated_date]],"MMMM")) -> JULY | M68: ="WEEK "&IF(ROUNDUP(DAY(tbl_raw_data[[#This Row],[updated_date]])/7,0)=5,4,ROUNDUP(DAY(tbl_raw_data[[#This Row],[updated_date]])/7,0)) -> WEEK 4 | N68: =UPPER(VLOOKUP(tbl_raw_data[[#This Row],[Analyst]],settings!$A$1:$B$15,2,0)) -> ASIF | O68: =TRIM(UPPER(tbl_raw_data[[#This Row],[Outcome]])) -> APPROVE | P68: =TRIM(UPPER(tbl_raw_data[[#This Row],[Queue Name]])) -> CONSUMER POST BUREAU | Q68: =IF(tbl_raw_data[[#This Row],[time_taken_in_min]]<=settings!$D$2,"SLA_MET","SLA_NOT_MET") -> SLA_MET
A69: 68 | B69: 45137.608 | C69: 45137.612 | D69: Approve | E69: Consumer Post Bureau | F69: SSyed | H69: =IF(OR(ISNUMBER(SEARCH("duplicate",G69)), ISNUMBER(SEARCH("previously",G69)), ISNUMBER(SEARCH("previously approved",G69))), "Duplicate Application", IF(OR(ISNUMBER(SEARCH("incorrect",G69)), ISNUMBER(SEARCH("remove", G69))), "Incorrect Details", IF(ISNUMBER(SEARCH("incomplete",G69)), "Incomplete Details", IF(ISNUMBER(SEARCH("overdue",G69)), "Overdue Bill", IF(OR(ISNUMBER(SEARCH("resubmit as", G69)), ISNUMBER(SEARCH("re-submit as", G69))), "Incorrect Queue", IF(OR(ISNUMBER(SEARCH("100",G69)), ISNUMBER(SEARCH("correct", G69)), ISNUMBER(SEARCH("email", G69)), ISNUMBER(SEARCH("please submit", G69)), ISNUMBER(SEARCH("please resubmit",G69)), ISNUMBER(SEARCH("please re-submit", G69)), ISNUMBER(SEARCH("please send", G69))), "Incomplete Details", IF(ISNUMBER(SEARCH("error", G69)), "System Error", "Reason Unknown"))))))) -> Reason Unknown | I69: =(tbl_raw_data[[#This Row],[Date Actioned]])-(tbl_raw_data[[#This Row],[Date Tagged]]) -> 0.0041550926 | J69: =HOUR(tbl_raw_data[[#This Row],[time_taken]])*60+MINUTE(tbl_raw_data[[#This Row],[time_taken]])+SECOND(tbl_raw_data[[#This Row],[time_taken]])/60 -> 5.9833333 | K69: =DATE(YEAR(tbl_raw_data[[#This Row],[Date Actioned]]),MONTH(tbl_raw_data[[#This Row],[Date Actioned]]),DAY(tbl_raw_data[[#This Row],[Date Actioned]])) -> 45137 | L69: =UPPER(TEXT(tbl_raw_data[[#This Row],[updated_date]],"MMMM")) -> JULY | M69: ="WEEK "&IF(ROUNDUP(DAY(tbl_raw_data[[#This Row],[updated_date]])/7,0)=5,4,ROUNDUP(DAY(tbl_raw_data[[#This Row],[updated_date]])/7,0)) -> WEEK 4 | N69: =UPPER(VLOOKUP(tbl_raw_data[[#This Row],[Analyst]],settings!$A$1:$B$15,2,0)) -> SHAHID | O69: =TRIM(UPPER(tbl_raw_data[[#This Row],[Outcome]])) -> APPROVE | P69: =TRIM(UPPER(tbl_raw_data[[#This Row],[Queue Name]])) -> CONSUMER POST BUREAU | Q69: =IF(tbl_raw_data[[#This Row],[time_taken_in_min]]<=settings!$D$2,"SLA_MET","SLA_NOT_MET") -> SLA_MET
A70: 69 | B70: 45137.609 | C70: 45137.621 | D70: APPROVE | E70: Consumer Existing | F70: NBhatia | G70: Approve | H70: =IF(OR(ISNUMBER(SEARCH("duplicate",G70)), ISNUMBER(SEARCH("previously",G70)), ISNUMBER(SEARCH("previously approved",G70))), "Duplicate Application", IF(OR(ISNUMBER(SEARCH("incorrect",G70)), ISNUMBER(SEARCH("remove", G70))), "Incorrect Details", IF(ISNUMBER(SEARCH("incomplete",G70)), "Incomplete Details", IF(ISNUMBER(SEARCH("overdue",G70)), "Overdue Bill", IF(OR(ISNUMBER(SEARCH("resubmit as", G70)), ISNUMBER(SEARCH("re-submit as", G70))), "Incorrect Queue", IF(OR(ISNUMBER(SEARCH("100",G70)), ISNUMBER(SEARCH("correct", G70)), ISNUMBER(SEARCH("email", G70)), ISNUMBER(SEARCH("please submit", G70)), ISNUMBER(SEARCH("please resubmit",G70)), ISNUMBER(SEARCH("please re-submit", G70)), ISNUMBER(SEARCH("please send", G70))), "Incomplete Details", IF(ISNUMBER(SEARCH("error", G70)), "System Error", "Reason Unknown"))))))) -> Reason Unknown | I70: =(tbl_raw_data[[#This Row],[Date Actioned]])-(tbl_raw_data[[#This Row],[Date Tagged]]) -> 0.011793981 | J70: =HOUR(tbl_raw_data[[#This Row],[time_taken]])*60+MINUTE(tbl_raw_data[[#This Row],[time_taken]])+SECOND(tbl_raw_data[[#This Row],[time_taken]])/60 -> 16.983333 | K70: =DATE(YEAR(tbl_raw_data[[#This Row],[Date Actioned]]),MONTH(tbl_raw_data[[#This Row],[Date Actioned]]),DAY(tbl_raw_data[[#This Row],[Date Actioned]])) -> 45137 | L70: =UPPER(TEXT(tbl_raw_data[[#This Row],[updated_date]],"MMMM")) -> JULY | M70: ="WEEK "&IF(ROUNDUP(DAY(tbl_raw_data[[#This Row],[updated_date]])/7,0)=5,4,ROUNDUP(DAY(tbl_raw_data[[#This Row],[updated_date]])/7,0)) -> WEEK 4 | N70: =UPPER(VLOOKUP(tbl_raw_data[[#This Row],[Analyst]],settings!$A$1:$B$15,2,0)) -> NITESH | O70: =TRIM(UPPER(tbl_raw_data[[#This Row],[Outcome]])) -> APPROVE | P70: =TRIM(UPPER(tbl_raw_data[[#This Row],[Queue Name]])) -> CONSUMER EXISTING | Q70: =IF(tbl_raw_data[[#This Row],[time_taken_in_min]]<=settings!$D$2,"SLA_MET","SLA_NOT_MET") -> SLA_MET
A71: 70 | B71: 45137.612 | C71: 45137.618 | D71: APPROVE | E71: Consumer Pre Bureau | F71: NVaid | G71: Approve | H71: =IF(OR(ISNUMBER(SEARCH("duplicate",G71)), ISNUMBER(SEARCH("previously",G71)), ISNUMBER(SEARCH("previously approved",G71))), "Duplicate Application", IF(OR(ISNUMBER(SEARCH("incorrect",G71)), ISNUMBER(SEARCH("remove", G71))), "Incorrect Details", IF(ISNUMBER(SEARCH("incomplete",G71)), "Incomplete Details", IF(ISNUMBER(SEARCH("overdue",G71)), "Overdue Bill", IF(OR(ISNUMBER(SEARCH("resubmit as", G71)), ISNUMBER(SEARCH("re-submit as", G71))), "Incorrect Queue", IF(OR(ISNUMBER(SEARCH("100",G71)), ISNUMBER(SEARCH("correct", G71)), ISNUMBER(SEARCH("email", G71)), ISNUMBER(SEARCH("please submit", G71)), ISNUMBER(SEARCH("please resubmit",G71)), ISNUMBER(SEARCH("please re-submit", G71)), ISNUMBER(SEARCH("please send", G71))), "Incomplete Details", IF(ISNUMBER(SEARCH("error", G71)), "System Error", "Reason Unknown"))))))) -> Reason Unknown | I71: =(tbl_raw_data[[#This Row],[Date Actioned]])-(tbl_raw_data[[#This Row],[Date Tagged]]) -> 0.0057060185 | J71: =HOUR(tbl_raw_data[[#This Row],[time_taken]])*60+MINUTE(tbl_raw_data[[#This Row],[time_taken]])+SECOND(tbl_raw_data[[#This Row],[time_taken]])/60 -> 8.2166667 | K71: =DATE(YEAR(tbl_raw_data[[#This Row],[Date Actioned]]),MONTH(tbl_raw_data[[#This Row],[Date Actioned]]),DAY(tbl_raw_data[[#This Row],[Date Actioned]])) -> 45137 | L71: =UPPER(TEXT(tbl_raw_data[[#This Row],[updated_date]],"MMMM")) -> JULY | M71: ="WEEK "&IF(ROUNDUP(DAY(tbl_raw_data[[#This Row],[updated_date]])/7,0)=5,4,ROUNDUP(DAY(tbl_raw_data[[#This Row],[updated_date]])/7,0)) -> WEEK 4 | N71: =UPPER(VLOOKUP(tbl_raw_data[[#This Row],[Analyst]],settings!$A$1:$B$15,2,0)) -> NAVED | O71: =TRIM(UPPER(tbl_raw_data[[#This Row],[Outcome]])) -> APPROVE | P71: =TRIM(UPPER(tbl_raw_data[[#This Row],[Queue Name]])) -> CONSUMER PRE BUREAU | Q71: =IF(tbl_raw_data[[#This Row],[time_taken_in_min]]<=settings!$D$2,"SLA_MET","SLA_NOT_MET") -> SLA_MET
A72: 71 | B72: 45137.612 | C72: 45137.615 | D72: APPROVE | E72: Consumer Existing | F72: CDcosta | G72: Approved for MBB only | H72: =IF(OR(ISNUMBER(SEARCH("duplicate",G72)), ISNUMBER(SEARCH("previously",G72)), ISNUMBER(SEARCH("previously approved",G72))), "Duplicate Application", IF(OR(ISNUMBER(SEARCH("incorrect",G72)), ISNUMBER(SEARCH("remove", G72))), "Incorrect Details", IF(ISNUMBER(SEARCH("incomplete",G72)), "Incomplete Details", IF(ISNUMBER(SEARCH("overdue",G72)), "Overdue Bill", IF(OR(ISNUMBER(SEARCH("resubmit as", G72)), ISNUMBER(SEARCH("re-submit as", G72))), "Incorrect Queue", IF(OR(ISNUMBER(SEARCH("100",G72)), ISNUMBER(SEARCH("correct", G72)), ISNUMBER(SEARCH("email", G72)), ISNUMBER(SEARCH("please submit", G72)), ISNUMBER(SEARCH("please resubmit",G72)), ISNUMBER(SEARCH("please re-submit", G72)), ISNUMBER(SEARCH("please send", G72))), "Incomplete Details", IF(ISNUMBER(SEARCH("error", G72)), "System Error", "Reason Unknown"))))))) -> Reason Unknown | I72: =(tbl_raw_data[[#This Row],[Date Actioned]])-(tbl_raw_data[[#This Row],[Date Tagged]]) -> 0.003125 | J72: =HOUR(tbl_raw_data[[#This Row],[time_taken]])*60+MINUTE(tbl_raw_data[[#This Row],[time_taken]])+SECOND(tbl_raw_data[[#This Row],[time_taken]])/60 -> 4.5 | K72: =DATE(YEAR(tbl_raw_data[[#This Row],[Date Actioned]]),MONTH(tbl_raw_data[[#This Row],[Date Actioned]]),DAY(tbl_raw_data[[#This Row],[Date Actioned]])) -> 45137 | L72: =UPPER(TEXT(tbl_raw_data[[#This Row],[updated_date]],"MMMM")) -> JULY | M72: ="WEEK "&IF(ROUNDUP(DAY(tbl_raw_data[[#This Row],[updated_date]])/7,0)=5,4,ROUNDUP(DAY(tbl_raw_data[[#This Row],[updated_date]])/7,0)) -> WEEK 4 | N72: =UPPER(VLOOKUP(tbl_raw_data[[#This Row],[Analyst]],settings!$A$1:$B$15,2,0)) -> CAMROON | O72: =TRIM(UPPER(tbl_raw_data[[#This Row],[Outcome]])) -> APPROVE | P72: =TRIM(UPPER(tbl_raw_data[[#This Row],[Queue Name]])) -> CONSUMER EXISTING | Q72: =IF(tbl_raw_data[[#This Row],[time_taken_in_min]]<=settings!$D$2,"SLA_MET","SLA_NOT_MET") -> SLA_MET
A73: 72 | B73: 45137.612 | C73: 45137.617 | D73: APPROVE | E73: Consumer Post Bureau | F73: AAkhundpur | G73: Approve | H73: =IF(OR(ISNUMBER(SEARCH("duplicate",G73)), ISNUMBER(SEARCH("previously",G73)), ISNUMBER(SEARCH("previously approved",G73))), "Duplicate Application", IF(OR(ISNUMBER(SEARCH("incorrect",G73)), ISNUMBER(SEARCH("remove", G73))), "Incorrect Details", IF(ISNUMBER(SEARCH("incomplete",G73)), "Incomplete Details", IF(ISNUMBER(SEARCH("overdue",G73)), "Overdue Bill", IF(OR(ISNUMBER(SEARCH("resubmit as", G73)), ISNUMBER(SEARCH("re-submit as", G73))), "Incorrect Queue", IF(OR(ISNUMBER(SEARCH("100",G73)), ISNUMBER(SEARCH("correct", G73)), ISNUMBER(SEARCH("email", G73)), ISNUMBER(SEARCH("please submit", G73)), ISNUMBER(SEARCH("please resubmit",G73)), ISNUMBER(SEARCH("please re-submit", G73)), ISNUMBER(SEARCH("please send", G73))), "Incomplete Details", IF(ISNUMBER(SEARCH("error", G73)), "System Error", "Reason Unknown"))))))) -> Reason Unknown | I73: =(tbl_raw_data[[#This Row],[Date Actioned]])-(tbl_raw_data[[#This Row],[Date Tagged]]) -> 0.0044675926 | J73: =HOUR(tbl_raw_data[[#This Row],[time_taken]])*60+MINUTE(tbl_raw_data[[#This Row],[time_taken]])+SECOND(tbl_raw_data[[#This Row],[time_taken]])/60 -> 6.4333333 | K73: =DATE(YEAR(tbl_raw_data[[#This Row],[Date Actioned]]),MONTH(tbl_raw_data[[#This Row],[Date Actioned]]),DAY(tbl_raw_data[[#This Row],[Date Actioned]])) -> 45137 | L73: =UPPER(TEXT(tbl_raw_data[[#This Row],[updated_date]],"MMMM")) -> JULY | M73: ="WEEK "&IF(ROUNDUP(DAY(tbl_raw_data[[#This Row],[updated_date]])/7,0)=5,4,ROUNDUP(DAY(tbl_raw_data[[#This Row],[updated_date]])/7,0)) -> WEEK 4 | N73: =UPPER(VLOOKUP(tbl_raw_data[[#This Row],[Analyst]],settings!$A$1:$B$15,2,0)) -> ASIF | O73: =TRIM(UPPER(tbl_raw_data[[#This Row],[Outcome]])) -> APPROVE | P73: =TRIM(UPPER(tbl_raw_data[[#This Row],[Queue Name]])) -> CONSUMER POST BUREAU | Q73: =IF(tbl_raw_data[[#This Row],[time_taken_in_min]]<=settings!$D$2,"SLA_MET","SLA_NOT_MET") -> SLA_MET
A74: 73 | B74: 45137.614 | C74: 45137.622 | D74: APPROVE | E74: Consumer Pre Bureau | F74: QMascarenhas | G74: Approve | H74: =IF(OR(ISNUMBER(SEARCH("duplicate",G74)), ISNUMBER(SEARCH("previously",G74)), ISNUMBER(SEARCH("previously approved",G74))), "Duplicate Application", IF(OR(ISNUMBER(SEARCH("incorrect",G74)), ISNUMBER(SEARCH("remove", G74))), "Incorrect Details", IF(ISNUMBER(SEARCH("incomplete",G74)), "Incomplete Details", IF(ISNUMBER(SEARCH("overdue",G74)), "Overdue Bill", IF(OR(ISNUMBER(SEARCH("resubmit as", G74)), ISNUMBER(SEARCH("re-submit as", G74))), "Incorrect Queue", IF(OR(ISNUMBER(SEARCH("100",G74)), ISNUMBER(SEARCH("correct", G74)), ISNUMBER(SEARCH("email", G74)), ISNUMBER(SEARCH("please submit", G74)), ISNUMBER(SEARCH("please resubmit",G74)), ISNUMBER(SEARCH("please re-submit", G74)), ISNUMBER(SEARCH("please send", G74))), "Incomplete Details", IF(ISNUMBER(SEARCH("error", G74)), "System Error", "Reason Unknown"))))))) -> Reason Unknown | I74: =(tbl_raw_data[[#This Row],[Date Actioned]])-(tbl_raw_data[[#This Row],[Date Tagged]]) -> 0.0078819444 | J74: =HOUR(tbl_raw_data[[#This Row],[time_taken]])*60+MINUTE(tbl_raw_data[[#This Row],[time_taken]])+SECOND(tbl_raw_data[[#This Row],[time_taken]])/60 -> 11.35 | K74: =DATE(YEAR(tbl_raw_data[[#This Row],[Date Actioned]]),MONTH(tbl_raw_data[[#This Row],[Date Actioned]]),DAY(tbl_raw_data[[#This Row],[Date Actioned]])) -> 45137 | L74: =UPPER(TEXT(tbl_raw_data[[#This Row],[updated_date]],"MMMM")) -> JULY | M74: ="WEEK "&IF(ROUNDUP(DAY(tbl_raw_data[[#This Row],[updated_date]])/7,0)=5,4,ROUNDUP(DAY(tbl_raw_data[[#This Row],[updated_date]])/7,0)) -> WEEK 4 | N74: =UPPER(VLOOKUP(tbl_raw_data[[#This Row],[Analyst]],settings!$A$1:$B$15,2,0)) -> QUADIR | O74: =TRIM(UPPER(tbl_raw_data[[#This Row],[Outcome]])) -> APPROVE | P74: =TRIM(UPPER(tbl_raw_data[[#This Row],[Queue Name]])) -> CONSUMER PRE BUREAU | Q74: =IF(tbl_raw_data[[#This Row],[time_taken_in_min]]<=settings!$D$2,"SLA_MET","SLA_NOT_MET") -> SLA_MET
A75: 74 | B75: 45137.614 | C75: 45137.625 | D75: APPROVE | E75: Consumer Post Bureau | F75: RBose | G75: Approved only with outright purchase of handset or USIM only | H75: =IF(OR(ISNUMBER(SEARCH("duplicate",G75)), ISNUMBER(SEARCH("previously",G75)), ISNUMBER(SEARCH("previously approved",G75))), "Duplicate Application", IF(OR(ISNUMBER(SEARCH("incorrect",G75)), ISNUMBER(SEARCH("remove", G75))), "Incorrect Details", IF(ISNUMBER(SEARCH("incomplete",G75)), "Incomplete Details", IF(ISNUMBER(SEARCH("overdue",G75)), "Overdue Bill", IF(OR(ISNUMBER(SEARCH("resubmit as", G75)), ISNUMBER(SEARCH("re-submit as", G75))), "Incorrect Queue", IF(OR(ISNUMBER(SEARCH("100",G75)), ISNUMBER(SEARCH("correct", G75)), ISNUMBER(SEARCH("email", G75)), ISNUMBER(SEARCH("please submit", G75)), ISNUMBER(SEARCH("please resubmit",G75)), ISNUMBER(SEARCH("please re-submit", G75)), ISNUMBER(SEARCH("please send", G75))), "Incomplete Details", IF(ISNUMBER(SEARCH("error", G75)), "System Error", "Reason Unknown"))))))) -> Reason Unknown | I75: =(tbl_raw_data[[#This Row],[Date Actioned]])-(tbl_raw_data[[#This Row],[Date Tagged]]) -> 0.011643519 | J75: =HOUR(tbl_raw_data[[#This Row],[time_taken]])*60+MINUTE(tbl_raw_data[[#This Row],[time_taken]])+SECOND(tbl_raw_data[[#This Row],[time_taken]])/60 -> 16.766667 | K75: =DATE(YEAR(tbl_raw_data[[#This Row],[Date Actioned]]),MONTH(tbl_raw_data[[#This Row],[Date Actioned]]),DAY(tbl_raw_data[[#This Row],[Date Actioned]])) -> 45137 | L75: =UPPER(TEXT(tbl_raw_data[[#This Row],[updated_date]],"MMMM")) -> JULY | M75: ="WEEK "&IF(ROUNDUP(DAY(tbl_raw_data[[#This Row],[updated_date]])/7,0)=5,4,ROUNDUP(DAY(tbl_raw_data[[#This Row],[updated_date]])/7,0)) -> WEEK 4 | N75: =UPPER(VLOOKUP(tbl_raw_data[[#This Row],[Analyst]],settings!$A$1:$B$15,2,0)) -> ROHAN | O75: =TRIM(UPPER(tbl_raw_data[[#This Row],[Outcome]])) -> APPROVE | P75: =TRIM(UPPER(tbl_raw_data[[#This Row],[Queue Name]])) -> CONSUMER POST BUREAU | Q75: =IF(tbl_raw_data[[#This Row],[time_taken_in_min]]<=settings!$D$2,"SLA_MET","SLA_NOT_MET") -> SLA_MET
A76: 75 | B76: 45137.617 | C76: 45137.623 | D76: Approve | E76: Consumer Post Bureau | F76: SSyed | H76: =IF(OR(ISNUMBER(SEARCH("duplicate",G76)), ISNUMBER(SEARCH("previously",G76)), ISNUMBER(SEARCH("previously approved",G76))), "Duplicate Application", IF(OR(ISNUMBER(SEARCH("incorrect",G76)), ISNUMBER(SEARCH("remove", G76))), "Incorrect Details", IF(ISNUMBER(SEARCH("incomplete",G76)), "Incomplete Details", IF(ISNUMBER(SEARCH("overdue",G76)), "Overdue Bill", IF(OR(ISNUMBER(SEARCH("resubmit as", G76)), ISNUMBER(SEARCH("re-submit as", G76))), "Incorrect Queue", IF(OR(ISNUMBER(SEARCH("100",G76)), ISNUMBER(SEARCH("correct", G76)), ISNUMBER(SEARCH("email", G76)), ISNUMBER(SEARCH("please submit", G76)), ISNUMBER(SEARCH("please resubmit",G76)), ISNUMBER(SEARCH("please re-submit", G76)), ISNUMBER(SEARCH("please send", G76))), "Incomplete Details", IF(ISNUMBER(SEARCH("error", G76)), "System Error", "Reason Unknown"))))))) -> Reason Unknown | I76: =(tbl_raw_data[[#This Row],[Date Actioned]])-(tbl_raw_data[[#This Row],[Date Tagged]]) -> 0.0057060185 | J76: =HOUR(tbl_raw_data[[#This Row],[time_taken]])*60+MINUTE(tbl_raw_data[[#This Row],[time_taken]])+SECOND(tbl_raw_data[[#This Row],[time_taken]])/60 -> 8.2166667 | K76: =DATE(YEAR(tbl_raw_data[[#This Row],[Date Actioned]]),MONTH(tbl_raw_data[[#This Row],[Date Actioned]]),DAY(tbl_raw_data[[#This Row],[Date Actioned]])) -> 45137 | L76: =UPPER(TEXT(tbl_raw_data[[#This Row],[updated_date]],"MMMM")) -> JULY | M76: ="WEEK "&IF(ROUNDUP(DAY(tbl_raw_data[[#This Row],[updated_date]])/7,0)=5,4,ROUNDUP(DAY(tbl_raw_data[[#This Row],[updated_date]])/7,0)) -> WEEK 4 | N76: =UPPER(VLOOKUP(tbl_raw_data[[#This Row],[Analyst]],settings!$A$1:$B$15,2,0)) -> SHAHID | O76: =TRIM(UPPER(tbl_raw_data[[#This Row],[Outcome]])) -> APPROVE | P76: =TRIM(UPPER(tbl_raw_data[[#This Row],[Queue Name]])) -> CONSUMER POST BUREAU | Q76: =IF(tbl_raw_data[[#This Row],[time_taken_in_min]]<=settings!$D$2,"SLA_MET","SLA_NOT_MET") -> SLA_MET
A77: 76 | B77: 45137.617 | C77: 45137.626 | D77: APPROVE | E77: Consumer Existing | F77: NVaid | G77: Approve | H77: =IF(OR(ISNUMBER(SEARCH("duplicate",G77)), ISNUMBER(SEARCH("previously",G77)), ISNUMBER(SEARCH("previously approved",G77))), "Duplicate Application", IF(OR(ISNUMBER(SEARCH("incorrect",G77)), ISNUMBER(SEARCH("remove", G77))), "Incorrect Details", IF(ISNUMBER(SEARCH("incomplete",G77)), "Incomplete Details", IF(ISNUMBER(SEARCH("overdue",G77)), "Overdue Bill", IF(OR(ISNUMBER(SEARCH("resubmit as", G77)), ISNUMBER(SEARCH("re-submit as", G77))), "Incorrect Queue", IF(OR(ISNUMBER(SEARCH("100",G77)), ISNUMBER(SEARCH("correct", G77)), ISNUMBER(SEARCH("email", G77)), ISNUMBER(SEARCH("please submit", G77)), ISNUMBER(SEARCH("please resubmit",G77)), ISNUMBER(SEARCH("please re-submit", G77)), ISNUMBER(SEARCH("please send", G77))), "Incomplete Details", IF(ISNUMBER(SEARCH("error", G77)), "System Error", "Reason Unknown"))))))) -> Reason Unknown | I77: =(tbl_raw_data[[#This Row],[Date Actioned]])-(tbl_raw_data[[#This Row],[Date Tagged]]) -> 0.0084606481 | J77: =HOUR(tbl_raw_data[[#This Row],[time_taken]])*60+MINUTE(tbl_raw_data[[#This Row],[time_taken]])+SECOND(tbl_raw_data[[#This Row],[time_taken]])/60 -> 12.183333 | K77: =DATE(YEAR(tbl_raw_data[[#This Row],[Date Actioned]]),MONTH(tbl_raw_data[[#This Row],[Date Actioned]]),DAY(tbl_raw_data[[#This Row],[Date Actioned]])) -> 45137 | L77: =UPPER(TEXT(tbl_raw_data[[#This Row],[updated_date]],"MMMM")) -> JULY | M77: ="WEEK "&IF(ROUNDUP(DAY(tbl_raw_data[[#This Row],[updated_date]])/7,0)=5,4,ROUNDUP(DAY(tbl_raw_data[[#This Row],[updated_date]])/7,0)) -> WEEK 4 | N77: =UPPER(VLOOKUP(tbl_raw_data[[#This Row],[Analyst]],settings!$A$1:$B$15,2,0)) -> NAVED | O77: =TRIM(UPPER(tbl_raw_data[[#This Row],[Outcome]])) -> APPROVE | P77: =TRIM(UPPER(tbl_raw_data[[#This Row],[Queue Name]])) -> CONSUMER EXISTING | Q77: =IF(tbl_raw_data[[#This Row],[time_taken_in_min]]<=settings!$D$2,"SLA_MET","SLA_NOT_MET") -> SLA_MET
A78: 77 | B78: 45137.618 | C78: 45137.623 | D78: APPROVE | E78: Consumer Post Bureau | F78: AAkhundpur | G78: Approved only with outright purchase of handset or USIM only Visa exires- 02/03/2013 | H78: =IF(OR(ISNUMBER(SEARCH("duplicate",G78)), ISNUMBER(SEARCH("previously",G78)), ISNUMBER(SEARCH("previously approved",G78))), "Duplicate Application", IF(OR(ISNUMBER(SEARCH("incorrect",G78)), ISNUMBER(SEARCH("remove", G78))), "Incorrect Details", IF(ISNUMBER(SEARCH("incomplete",G78)), "Incomplete Details", IF(ISNUMBER(SEARCH("overdue",G78)), "Overdue Bill", IF(OR(ISNUMBER(SEARCH("resubmit as", G78)), ISNUMBER(SEARCH("re-submit as", G78))), "Incorrect Queue", IF(OR(ISNUMBER(SEARCH("100",G78)), ISNUMBER(SEARCH("correct", G78)), ISNUMBER(SEARCH("email", G78)), ISNUMBER(SEARCH("please submit", G78)), ISNUMBER(SEARCH("please resubmit",G78)), ISNUMBER(SEARCH("please re-submit", G78)), ISNUMBER(SEARCH("please send", G78))), "Incomplete Details", IF(ISNUMBER(SEARCH("error", G78)), "System Error", "Reason Unknown"))))))) -> Reason Unknown | I78: =(tbl_raw_data[[#This Row],[Date Actioned]])-(tbl_raw_data[[#This Row],[Date Tagged]]) -> 0.0050231482 | J78: =HOUR(tbl_raw_data[[#This Row],[time_taken]])*60+MINUTE(tbl_raw_data[[#This Row],[time_taken]])+SECOND(tbl_raw_data[[#This Row],[time_taken]])/60 -> 7.2333333 | K78: =DATE(YEAR(tbl_raw_data[[#This Row],[Date Actioned]]),MONTH(tbl_raw_data[[#This Row],[Date Actioned]]),DAY(tbl_raw_data[[#This Row],[Date Actioned]])) -> 45137 | L78: =UPPER(TEXT(tbl_raw_data[[#This Row],[updated_date]],"MMMM")) -> JULY | M78: ="WEEK "&IF(ROUNDUP(DAY(tbl_raw_data[[#This Row],[updated_date]])/7,0)=5,4,ROUNDUP(DAY(tbl_raw_data[[#This Row],[updated_date]])/7,0)) -> WEEK 4 | N78: =UPPER(VLOOKUP(tbl_raw_data[[#This Row],[Analyst]],settings!$A$1:$B$15,2,0)) -> ASIF | O78: =TRIM(UPPER(tbl_raw_data[[#This Row],[Outcome]])) -> APPROVE | P78: =TRIM(UPPER(tbl_raw_data[[#This Row],[Queue Name]])) -> CONSUMER POST BUREAU | Q78: =IF(tbl_raw_data[[#This Row],[time_taken_in_min]]<=settings!$D$2,"SLA_MET","SLA_NOT_MET") -> SLA_MET
A79: 78 | B79: 45137.619 | C79: 45137.624 | D79: APPROVE | E79: Consumer Existing | F79: SBambaras | G79: Approved only with outright purchase of handset or USIM only | H79: =IF(OR(ISNUMBER(SEARCH("duplicate",G79)), ISNUMBER(SEARCH("previously",G79)), ISNUMBER(SEARCH("previously approved",G79))), "Duplicate Application", IF(OR(ISNUMBER(SEARCH("incorrect",G79)), ISNUMBER(SEARCH("remove", G79))), "Incorrect Details", IF(ISNUMBER(SEARCH("incomplete",G79)), "Incomplete Details", IF(ISNUMBER(SEARCH("overdue",G79)), "Overdue Bill", IF(OR(ISNUMBER(SEARCH("resubmit as", G79)), ISNUMBER(SEARCH("re-submit as", G79))), "Incorrect Queue", IF(OR(ISNUMBER(SEARCH("100",G79)), ISNUMBER(SEARCH("correct", G79)), ISNUMBER(SEARCH("email", G79)), ISNUMBER(SEARCH("please submit", G79)), ISNUMBER(SEARCH("please resubmit",G79)), ISNUMBER(SEARCH("please re-submit", G79)), ISNUMBER(SEARCH("please send", G79))), "Incomplete Details", IF(ISNUMBER(SEARCH("error", G79)), "System Error", "Reason Unknown"))))))) -> Reason Unknown | I79: =(tbl_raw_data[[#This Row],[Date Actioned]])-(tbl_raw_data[[#This Row],[Date Tagged]]) -> 0.0050694445 | J79: =HOUR(tbl_raw_data[[#This Row],[time_taken]])*60+MINUTE(tbl_raw_data[[#This Row],[time_taken]])+SECOND(tbl_raw_data[[#This Row],[time_taken]])/60 -> 7.3 | K79: =DATE(YEAR(tbl_raw_data[[#This Row],[Date Actioned]]),MONTH(tbl_raw_data[[#This Row],[Date Actioned]]),DAY(tbl_raw_data[[#This Row],[Date Actioned]])) -> 45137 | L79: =UPPER(TEXT(tbl_raw_data[[#This Row],[updated_date]],"MMMM")) -> JULY | M79: ="WEEK "&IF(ROUNDUP(DAY(tbl_raw_data[[#This Row],[updated_date]])/7,0)=5,4,ROUNDUP(DAY(tbl_raw_data[[#This Row],[updated_date]])/7,0)) -> WEEK 4 | N79: =UPPER(VLOOKUP(tbl_raw_data[[#This Row],[Analyst]],settings!$A$1:$B$15,2,0)) -> SAM | O79: =TRIM(UPPER(tbl_raw_data[[#This Row],[Outcome]])) -> APPROVE | P79: =TRIM(UPPER(tbl_raw_data[[#This Row],[Queue Name]])) -> CONSUMER EXISTING | Q79: =IF(tbl_raw_data[[#This Row],[time_taken_in_min]]<=settings!$D$2,"SLA_MET","SLA_NOT_MET") -> SLA_MET
A80: 79 | B80: 45137.62 | C80: 45137.626 | D80: Approve | E80: Consumer Existing | F80: SSyed | H80: =IF(OR(ISNUMBER(SEARCH("duplicate",G80)), ISNUMBER(SEARCH("previously",G80)), ISNUMBER(SEARCH("previously approved",G80))), "Duplicate Application", IF(OR(ISNUMBER(SEARCH("incorrect",G80)), ISNUMBER(SEARCH("remove", G80))), "Incorrect Details", IF(ISNUMBER(SEARCH("incomplete",G80)), "Incomplete Details", IF(ISNUMBER(SEARCH("overdue",G80)), "Overdue Bill", IF(OR(ISNUMBER(SEARCH("resubmit as", G80)), ISNUMBER(SEARCH("re-submit as", G80))), "Incorrect Queue", IF(OR(ISNUMBER(SEARCH("100",G80)), ISNUMBER(SEARCH("correct", G80)), ISNUMBER(SEARCH("email", G80)), ISNUMBER(SEARCH("please submit", G80)), ISNUMBER(SEARCH("please resubmit",G80)), ISNUMBER(SEARCH("please re-submit", G80)), ISNUMBER(SEARCH("please send", G80))), "Incomplete Details", IF(ISNUMBER(SEARCH("error", G80)), "System Error", "Reason Unknown"))))))) -> Reason Unknown | I80: =(tbl_raw_data[[#This Row],[Date Actioned]])-(tbl_raw_data[[#This Row],[Date Tagged]]) -> 0.0054513889 | J80: =HOUR(tbl_raw_data[[#This Row],[time_taken]])*60+MINUTE(tbl_raw_data[[#This Row],[time_taken]])+SECOND(tbl_raw_data[[#This Row],[time_taken]])/60 -> 7.85 | K80: =DATE(YEAR(tbl_raw_data[[#This Row],[Date Actioned]]),MONTH(tbl_raw_data[[#This Row],[Date Actioned]]),DAY(tbl_raw_data[[#This Row],[Date Actioned]])) -> 45137 | L80: =UPPER(TEXT(tbl_raw_data[[#This Row],[updated_date]],"MMMM")) -> JULY | M80: ="WEEK "&IF(ROUNDUP(DAY(tbl_raw_data[[#This Row],[updated_date]])/7,0)=5,4,ROUNDUP(DAY(tbl_raw_data[[#This Row],[updated_date]])/7,0)) -> WEEK 4 | N80: =UPPER(VLOOKUP(tbl_raw_data[[#This Row],[Analyst]],settings!$A$1:$B$15,2,0)) -> SHAHID | O80: =TRIM(UPPER(tbl_raw_data[[#This Row],[Outcome]])) -> APPROVE | P80: =TRIM(UPPER(tbl_raw_data[[#This Row],[Queue Name]])) -> CONSUMER EXISTING | Q80: =IF(tbl_raw_data[[#This Row],[time_taken_in_min]]<=settings!$D$2,"SLA_MET","SLA_NOT_MET") -> SLA_MET
A81: 80 | B81: 45137.62 | C81: 45137.632 | D81: Approve | E81: Consumer Post Bureau | F81: SSyed | H81: =IF(OR(ISNUMBER(SEARCH("duplicate",G81)), ISNUMBER(SEARCH("previously",G81)), ISNUMBER(SEARCH("previously approved",G81))), "Duplicate Application", IF(OR(ISNUMBER(SEARCH("incorrect",G81)), ISNUMBER(SEARCH("remove", G81))), "Incorrect Details", IF(ISNUMBER(SEARCH("incomplete",G81)), "Incomplete Details", IF(ISNUMBER(SEARCH("overdue",G81)), "Overdue Bill", IF(OR(ISNUMBER(SEARCH("resubmit as", G81)), ISNUMBER(SEARCH("re-submit as", G81))), "Incorrect Queue", IF(OR(ISNUMBER(SEARCH("100",G81)), ISNUMBER(SEARCH("correct", G81)), ISNUMBER(SEARCH("email", G81)), ISNUMBER(SEARCH("please submit", G81)), ISNUMBER(SEARCH("please resubmit",G81)), ISNUMBER(SEARCH("please re-submit", G81)), ISNUMBER(SEARCH("please send", G81))), "Incomplete Details", IF(ISNUMBER(SEARCH("error", G81)), "System Error", "Reason Unknown"))))))) -> Reason Unknown | I81: =(tbl_raw_data[[#This Row],[Date Actioned]])-(tbl_raw_data[[#This Row],[Date Tagged]]) -> 0.01125 | J81: =HOUR(tbl_raw_data[[#This Row],[time_taken]])*60+MINUTE(tbl_raw_data[[#This Row],[time_taken]])+SECOND(tbl_raw_data[[#This Row],[time_taken]])/60 -> 16.2 | K81: =DATE(YEAR(tbl_raw_data[[#This Row],[Date Actioned]]),MONTH(tbl_raw_data[[#This Row],[Date Actioned]]),DAY(tbl_raw_data[[#This Row],[Date Actioned]])) -> 45137 | L81: =UPPER(TEXT(tbl_raw_data[[#This Row],[updated_date]],"MMMM")) -> JULY | M81: ="WEEK "&IF(ROUNDUP(DAY(tbl_raw_data[[#This Row],[updated_date]])/7,0)=5,4,ROUNDUP(DAY(tbl_raw_data[[#This Row],[updated_date]])/7,0)) -> WEEK 4 | N81: =UPPER(VLOOKUP(tbl_raw_data[[#This Row],[Analyst]],settings!$A$1:$B$15,2,0)) -> SHAHID | O81: =TRIM(UPPER(tbl_raw_data[[#This Row],[Outcome]])) -> APPROVE | P81: =TRIM(UPPER(tbl_raw_data[[#This Row],[Queue Name]])) -> CONSUMER POST BUREAU | Q81: =IF(tbl_raw_data[[#This Row],[time_taken_in_min]]<=settings!$D$2,"SLA_MET","SLA_NOT_MET") -> SLA_MET
A82: 81 | B82: 45137.623 | C82: 45137.626 | D82: APPROVE | E82: Consumer Post Bureau | F82: QMascarenhas | G82: Approved only with outright purchase of handset or USIM only | H82: =IF(OR(ISNUMBER(SEARCH("duplicate",G82)), ISNUMBER(SEARCH("previously",G82)), ISNUMBER(SEARCH("previously approved",G82))), "Duplicate Application", IF(OR(ISNUMBER(SEARCH("incorrect",G82)), ISNUMBER(SEARCH("remove", G82))), "Incorrect Details", IF(ISNUMBER(SEARCH("incomplete",G82)), "Incomplete Details", IF(ISNUMBER(SEARCH("overdue",G82)), "Overdue Bill", IF(OR(ISNUMBER(SEARCH("resubmit as", G82)), ISNUMBER(SEARCH("re-submit as", G82))), "Incorrect Queue", IF(OR(ISNUMBER(SEARCH("100",G82)), ISNUMBER(SEARCH("correct", G82)), ISNUMBER(SEARCH("email", G82)), ISNUMBER(SEARCH("please submit", G82)), ISNUMBER(SEARCH("please resubmit",G82)), ISNUMBER(SEARCH("please re-submit", G82)), ISNUMBER(SEARCH("please send", G82))), "Incomplete Details", IF(ISNUMBER(SEARCH("error", G82)), "System Error", "Reason Unknown"))))))) -> Reason Unknown | I82: =(tbl_raw_data[[#This Row],[Date Actioned]])-(tbl_raw_data[[#This Row],[Date Tagged]]) -> 0.0027662037 | J82: =HOUR(tbl_raw_data[[#This Row],[time_taken]])*60+MINUTE(tbl_raw_data[[#This Row],[time_taken]])+SECOND(tbl_raw_data[[#This Row],[time_taken]])/60 -> 3.9833333 | K82: =DATE(YEAR(tbl_raw_data[[#This Row],[Date Actioned]]),MONTH(tbl_raw_data[[#This Row],[Date Actioned]]),DAY(tbl_raw_data[[#This Row],[Date Actioned]])) -> 45137 | L82: =UPPER(TEXT(tbl_raw_data[[#This Row],[updated_date]],"MMMM")) -> JULY | M82: ="WEEK "&IF(ROUNDUP(DAY(tbl_raw_data[[#This Row],[updated_date]])/7,0)=5,4,ROUNDUP(DAY(tbl_raw_data[[#This Row],[updated_date]])/7,0)) -> WEEK 4 | N82: =UPPER(VLOOKUP(tbl_raw_data[[#This Row],[Analyst]],settings!$A$1:$B$15,2,0)) -> QUADIR | O82: =TRIM(UPPER(tbl_raw_data[[#This Row],[Outcome]])) -> APPROVE | P82: =TRIM(UPPER(tbl_raw_data[[#This Row],[Queue Name]])) -> CONSUMER POST BUREAU | Q82: =IF(tbl_raw_data[[#This Row],[time_taken_in_min]]<=settings!$D$2,"SLA_MET","SLA_NOT_MET") -> SLA_MET
A83: 82 | B83: 45137.624 | C83: 45137.626 | D83: APPROVE | E83: Consumer Existing | F83: SBambaras | G83: Approved for MBB only | H83: =IF(OR(ISNUMBER(SEARCH("duplicate",G83)), ISNUMBER(SEARCH("previously",G83)), ISNUMBER(SEARCH("previously approved",G83))), "Duplicate Application", IF(OR(ISNUMBER(SEARCH("incorrect",G83)), ISNUMBER(SEARCH("remove", G83))), "Incorrect Details", IF(ISNUMBER(SEARCH("incomplete",G83)), "Incomplete Details", IF(ISNUMBER(SEARCH("overdue",G83)), "Overdue Bill", IF(OR(ISNUMBER(SEARCH("resubmit as", G83)), ISNUMBER(SEARCH("re-submit as", G83))), "Incorrect Queue", IF(OR(ISNUMBER(SEARCH("100",G83)), ISNUMBER(SEARCH("correct", G83)), ISNUMBER(SEARCH("email", G83)), ISNUMBER(SEARCH("please submit", G83)), ISNUMBER(SEARCH("please resubmit",G83)), ISNUMBER(SEARCH("please re-submit", G83)), ISNUMBER(SEARCH("please send", G83))), "Incomplete Details", IF(ISNUMBER(SEARCH("error", G83)), "System Error", "Reason Unknown"))))))) -> Reason Unknown | I83: =(tbl_raw_data[[#This Row],[Date Actioned]])-(tbl_raw_data[[#This Row],[Date Tagged]]) -> 0.0021759259 | J83: =HOUR(tbl_raw_data[[#This Row],[time_taken]])*60+MINUTE(tbl_raw_data[[#This Row],[time_taken]])+SECOND(tbl_raw_data[[#This Row],[time_taken]])/60 -> 3.1333333 | K83: =DATE(YEAR(tbl_raw_data[[#This Row],[Date Actioned]]),MONTH(tbl_raw_data[[#This Row],[Date Actioned]]),DAY(tbl_raw_data[[#This Row],[Date Actioned]])) -> 45137 | L83: =UPPER(TEXT(tbl_raw_data[[#This Row],[updated_date]],"MMMM")) -> JULY | M83: ="WEEK "&IF(ROUNDUP(DAY(tbl_raw_data[[#This Row],[updated_date]])/7,0)=5,4,ROUNDUP(DAY(tbl_raw_data[[#This Row],[updated_date]])/7,0)) -> WEEK 4 | N83: =UPPER(VLOOKUP(tbl_raw_data[[#This Row],[Analyst]],settings!$A$1:$B$15,2,0)) -> SAM | O83: =TRIM(UPPER(tbl_raw_data[[#This Row],[Outcome]])) -> APPROVE | P83: =TRIM(UPPER(tbl_raw_data[[#This Row],[Queue Name]])) -> CONSUMER EXISTING | Q83: =IF(tbl_raw_data[[#This Row],[time_taken_in_min]]<=settings!$D$2,"SLA_MET","SLA_NOT_MET") -> SLA_MET
A84: 83 | B84: 45137.628 | C84: 45137.631 | D84: APPROVE | E84: Consumer Post Bureau | F84: SBambaras | G84: Approved only with outright purchase of handset or USIM only | H84: =IF(OR(ISNUMBER(SEARCH("duplicate",G84)), ISNUMBER(SEARCH("previously",G84)), ISNUMBER(SEARCH("previously approved",G84))), "Duplicate Application", IF(OR(ISNUMBER(SEARCH("incorrect",G84)), ISNUMBER(SEARCH("remove", G84))), "Incorrect Details", IF(ISNUMBER(SEARCH("incomplete",G84)), "Incomplete Details", IF(ISNUMBER(SEARCH("overdue",G84)), "Overdue Bill", IF(OR(ISNUMBER(SEARCH("resubmit as", G84)), ISNUMBER(SEARCH("re-submit as", G84))), "Incorrect Queue", IF(OR(ISNUMBER(SEARCH("100",G84)), ISNUMBER(SEARCH("correct", G84)), ISNUMBER(SEARCH("email", G84)), ISNUMBER(SEARCH("please submit", G84)), ISNUMBER(SEARCH("please resubmit",G84)), ISNUMBER(SEARCH("please re-submit", G84)), ISNUMBER(SEARCH("please send", G84))), "Incomplete Details", IF(ISNUMBER(SEARCH("error", G84)), "System Error", "Reason Unknown"))))))) -> Reason Unknown | I84: =(tbl_raw_data[[#This Row],[Date Actioned]])-(tbl_raw_data[[#This Row],[Date Tagged]]) -> 0.0036921296 | J84: =HOUR(tbl_raw_data[[#This Row],[time_taken]])*60+MINUTE(tbl_raw_data[[#This Row],[time_taken]])+SECOND(tbl_raw_data[[#This Row],[time_taken]])/60 -> 5.3166667 | K84: =DATE(YEAR(tbl_raw_data[[#This Row],[Date Actioned]]),MONTH(tbl_raw_data[[#This Row],[Date Actioned]]),DAY(tbl_raw_data[[#This Row],[Date Actioned]])) -> 45137 | L84: =UPPER(TEXT(tbl_raw_data[[#This Row],[updated_date]],"MMMM")) -> JULY | M84: ="WEEK "&IF(ROUNDUP(DAY(tbl_raw_data[[#This Row],[updated_date]])/7,0)=5,4,ROUNDUP(DAY(tbl_raw_data[[#This Row],[updated_date]])/7,0)) -> WEEK 4 | N84: =UPPER(VLOOKUP(tbl_raw_data[[#This Row],[Analyst]],settings!$A$1:$B$15,2,0)) -> SAM | O84: =TRIM(UPPER(tbl_raw_data[[#This Row],[Outcome]])) -> APPROVE | P84: =TRIM(UPPER(tbl_raw_data[[#This Row],[Queue Name]])) -> CONSUMER POST BUREAU | Q84: =IF(tbl_raw_data[[#This Row],[time_taken_in_min]]<=settings!$D$2,"SLA_MET","SLA_NOT_MET") -> SLA_MET
A85: 84 | B85: 45137.629 | C85: 45137.638 | D85: APPROVE | E85: Consumer Pre Bureau | F85: NVaid | G85: Approved for 1 handset and 1 MBB | H85: =IF(OR(ISNUMBER(SEARCH("duplicate",G85)), ISNUMBER(SEARCH("previously",G85)), ISNUMBER(SEARCH("previously approved",G85))), "Duplicate Application", IF(OR(ISNUMBER(SEARCH("incorrect",G85)), ISNUMBER(SEARCH("remove", G85))), "Incorrect Details", IF(ISNUMBER(SEARCH("incomplete",G85)), "Incomplete Details", IF(ISNUMBER(SEARCH("overdue",G85)), "Overdue Bill", IF(OR(ISNUMBER(SEARCH("resubmit as", G85)), ISNUMBER(SEARCH("re-submit as", G85))), "Incorrect Queue", IF(OR(ISNUMBER(SEARCH("100",G85)), ISNUMBER(SEARCH("correct", G85)), ISNUMBER(SEARCH("email", G85)), ISNUMBER(SEARCH("please submit", G85)), ISNUMBER(SEARCH("please resubmit",G85)), ISNUMBER(SEARCH("please re-submit", G85)), ISNUMBER(SEARCH("please send", G85))), "Incomplete Details", IF(ISNUMBER(SEARCH("error", G85)), "System Error", "Reason Unknown"))))))) -> Reason Unknown | I85: =(tbl_raw_data[[#This Row],[Date Actioned]])-(tbl_raw_data[[#This Row],[Date Tagged]]) -> 0.008587963 | J85: =HOUR(tbl_raw_data[[#This Row],[time_taken]])*60+MINUTE(tbl_raw_data[[#This Row],[time_taken]])+SECOND(tbl_raw_data[[#This Row],[time_taken]])/60 -> 12.366667 | K85: =DATE(YEAR(tbl_raw_data[[#This Row],[Date Actioned]]),MONTH(tbl_raw_data[[#This Row],[Date Actioned]]),DAY(tbl_raw_data[[#This Row],[Date Actioned]])) -> 45137 | L85: =UPPER(TEXT(tbl_raw_data[[#This Row],[updated_date]],"MMMM")) -> JULY | M85: ="WEEK "&IF(ROUNDUP(DAY(tbl_raw_data[[#This Row],[updated_date]])/7,0)=5,4,ROUNDUP(DAY(tbl_raw_data[[#This Row],[updated_date]])/7,0)) -> WEEK 4 | N85: =UPPER(VLOOKUP(tbl_raw_data[[#This Row],[Analyst]],settings!$A$1:$B$15,2,0)) -> NAVED | O85: =TRIM(UPPER(tbl_raw_data[[#This Row],[Outcome]])) -> APPROVE | P85: =TRIM(UPPER(tbl_raw_data[[#This Row],[Queue Name]])) -> CONSUMER PRE BUREAU | Q85: =IF(tbl_raw_data[[#This Row],[time_taken_in_min]]<=settings!$D$2,"SLA_MET","SLA_NOT_MET") -> SLA_MET
A86: 85 | B86: 45137.63 | C86: 45137.636 | D86: APPROVE | E86: Consumer Existing | F86: SBambaras | G86: Approve | H86: =IF(OR(ISNUMBER(SEARCH("duplicate",G86)), ISNUMBER(SEARCH("previously",G86)), ISNUMBER(SEARCH("previously approved",G86))), "Duplicate Application", IF(OR(ISNUMBER(SEARCH("incorrect",G86)), ISNUMBER(SEARCH("remove", G86))), "Incorrect Details", IF(ISNUMBER(SEARCH("incomplete",G86)), "Incomplete Details", IF(ISNUMBER(SEARCH("overdue",G86)), "Overdue Bill", IF(OR(ISNUMBER(SEARCH("resubmit as", G86)), ISNUMBER(SEARCH("re-submit as", G86))), "Incorrect Queue", IF(OR(ISNUMBER(SEARCH("100",G86)), ISNUMBER(SEARCH("correct", G86)), ISNUMBER(SEARCH("email", G86)), ISNUMBER(SEARCH("please submit", G86)), ISNUMBER(SEARCH("please resubmit",G86)), ISNUMBER(SEARCH("please re-submit", G86)), ISNUMBER(SEARCH("please send", G86))), "Incomplete Details", IF(ISNUMBER(SEARCH("error", G86)), "System Error", "Reason Unknown"))))))) -> Reason Unknown | I86: =(tbl_raw_data[[#This Row],[Date Actioned]])-(tbl_raw_data[[#This Row],[Date Tagged]]) -> 0.0064699074 | J86: =HOUR(tbl_raw_data[[#This Row],[time_taken]])*60+MINUTE(tbl_raw_data[[#This Row],[time_taken]])+SECOND(tbl_raw_data[[#This Row],[time_taken]])/60 -> 9.3166667 | K86: =DATE(YEAR(tbl_raw_data[[#This Row],[Date Actioned]]),MONTH(tbl_raw_data[[#This Row],[Date Actioned]]),DAY(tbl_raw_data[[#This Row],[Date Actioned]])) -> 45137 | L86: =UPPER(TEXT(tbl_raw_data[[#This Row],[updated_date]],"MMMM")) -> JULY | M86: ="WEEK "&IF(ROUNDUP(DAY(tbl_raw_data[[#This Row],[updated_date]])/7,0)=5,4,ROUNDUP(DAY(tbl_raw_data[[#This Row],[updated_date]])/7,0)) -> WEEK 4 | N86: =UPPER(VLOOKUP(tbl_raw_data[[#This Row],[Analyst]],settings!$A$1:$B$15,2,0)) -> SAM | O86: =TRIM(UPPER(tbl_raw_data[[#This Row],[Outcome]])) -> APPROVE | P86: =TRIM(UPPER(tbl_raw_data[[#This Row],[Queue Name]])) -> CONSUMER EXISTING | Q86: =IF(tbl_raw_data[[#This Row],[time_taken_in_min]]<=settings!$D$2,"SLA_MET","SLA_NOT_MET") -> SLA_MET
A87: 86 | B87: 45137.63 | C87: 45137.642 | D87: APPROVE | E87: Consumer Pre Bureau | F87: QMascarenhas | G87: Approve | H87: =IF(OR(ISNUMBER(SEARCH("duplicate",G87)), ISNUMBER(SEARCH("previously",G87)), ISNUMBER(SEARCH("previously approved",G87))), "Duplicate Application", IF(OR(ISNUMBER(SEARCH("incorrect",G87)), ISNUMBER(SEARCH("remove", G87))), "Incorrect Details", IF(ISNUMBER(SEARCH("incomplete",G87)), "Incomplete Details", IF(ISNUMBER(SEARCH("overdue",G87)), "Overdue Bill", IF(OR(ISNUMBER(SEARCH("resubmit as", G87)), ISNUMBER(SEARCH("re-submit as", G87))), "Incorrect Queue", IF(OR(ISNUMBER(SEARCH("100",G87)), ISNUMBER(SEARCH("correct", G87)), ISNUMBER(SEARCH("email", G87)), ISNUMBER(SEARCH("please submit", G87)), ISNUMBER(SEARCH("please resubmit",G87)), ISNUMBER(SEARCH("please re-submit", G87)), ISNUMBER(SEARCH("please send", G87))), "Incomplete Details", IF(ISNUMBER(SEARCH("error", G87)), "System Error", "Reason Unknown"))))))) -> Reason Unknown | I87: =(tbl_raw_data[[#This Row],[Date Actioned]])-(tbl_raw_data[[#This Row],[Date Tagged]]) -> 0.011689815 | J87: =HOUR(tbl_raw_data[[#This Row],[time_taken]])*60+MINUTE(tbl_raw_data[[#This Row],[time_taken]])+SECOND(tbl_raw_data[[#This Row],[time_taken]])/60 -> 16.833333 | K87: =DATE(YEAR(tbl_raw_data[[#This Row],[Date Actioned]]),MONTH(tbl_raw_data[[#This Row],[Date Actioned]]),DAY(tbl_raw_data[[#This Row],[Date Actioned]])) -> 45137 | L87: =UPPER(TEXT(tbl_raw_data[[#This Row],[updated_date]],"MMMM")) -> JULY | M87: ="WEEK "&IF(ROUNDUP(DAY(tbl_raw_data[[#This Row],[updated_date]])/7,0)=5,4,ROUNDUP(DAY(tbl_raw_data[[#This Row],[updated_date]])/7,0)) -> WEEK 4 | N87: =UPPER(VLOOKUP(tbl_raw_data[[#This Row],[Analyst]],settings!$A$1:$B$15,2,0)) -> QUADIR | O87: =TRIM(UPPER(tbl_raw_data[[#This Row],[Outcome]])) -> APPROVE | P87: =TRIM(UPPER(tbl_raw_data[[#This Row],[Queue Name]])) -> CONSUMER PRE BUREAU | Q87: =IF(tbl_raw_data[[#This Row],[time_taken_in_min]]<=settings!$D$2,"SLA_MET","SLA_NOT_MET") -> SLA_MET
A88: 87 | B88: 45137.63 | C88: 45137.64 | D88: APPROVE | E88: Consumer Post Bureau | F88: AAkhundpur | G88: Approved only with outright purchase of handset or USIM only | H88: =IF(OR(ISNUMBER(SEARCH("duplicate",G88)), ISNUMBER(SEARCH("previously",G88)), ISNUMBER(SEARCH("previously approved",G88))), "Duplicate Application", IF(OR(ISNUMBER(SEARCH("incorrect",G88)), ISNUMBER(SEARCH("remove", G88))), "Incorrect Details", IF(ISNUMBER(SEARCH("incomplete",G88)), "Incomplete Details", IF(ISNUMBER(SEARCH("overdue",G88)), "Overdue Bill", IF(OR(ISNUMBER(SEARCH("resubmit as", G88)), ISNUMBER(SEARCH("re-submit as", G88))), "Incorrect Queue", IF(OR(ISNUMBER(SEARCH("100",G88)), ISNUMBER(SEARCH("correct", G88)), ISNUMBER(SEARCH("email", G88)), ISNUMBER(SEARCH("please submit", G88)), ISNUMBER(SEARCH("please resubmit",G88)), ISNUMBER(SEARCH("please re-submit", G88)), ISNUMBER(SEARCH("please send", G88))), "Incomplete Details", IF(ISNUMBER(SEARCH("error", G88)), "System Error", "Reason Unknown"))))))) -> Reason Unknown | I88: =(tbl_raw_data[[#This Row],[Date Actioned]])-(tbl_raw_data[[#This Row],[Date Tagged]]) -> 0.0093518519 | J88: =HOUR(tbl_raw_data[[#This Row],[time_taken]])*60+MINUTE(tbl_raw_data[[#This Row],[time_taken]])+SECOND(tbl_raw_data[[#This Row],[time_taken]])/60 -> 13.466667 | K88: =DATE(YEAR(tbl_raw_data[[#This Row],[Date Actioned]]),MONTH(tbl_raw_data[[#This Row],[Date Actioned]]),DAY(tbl_raw_data[[#This Row],[Date Actioned]])) -> 45137 | L88: =UPPER(TEXT(tbl_raw_data[[#This Row],[updated_date]],"MMMM")) -> JULY | M88: ="WEEK "&IF(ROUNDUP(DAY(tbl_raw_data[[#This Row],[updated_date]])/7,0)=5,4,ROUNDUP(DAY(tbl_raw_data[[#This Row],[updated_date]])/7,0)) -> WEEK 4 | N88: =UPPER(VLOOKUP(tbl_raw_data[[#This Row],[Analyst]],settings!$A$1:$B$15,2,0)) -> ASIF | O88: =TRIM(UPPER(tbl_raw_data[[#This Row],[Outcome]])) -> APPROVE | P88: =TRIM(UPPER(tbl_raw_data[[#This Row],[Queue Name]])) -> CONSUMER POST BUREAU | Q88: =IF(tbl_raw_data[[#This Row],[time_taken_in_min]]<=settings!$D$2,"SLA_MET","SLA_NOT_MET") -> SLA_MET
A89: 88 | B89: 45137.632 | C89: 45137.638 | D89: APPROVE | E89: Consumer Existing | F89: CDcosta | G89: Approved for MBB only | H89: =IF(OR(ISNUMBER(SEARCH("duplicate",G89)), ISNUMBER(SEARCH("previously",G89)), ISNUMBER(SEARCH("previously approved",G89))), "Duplicate Application", IF(OR(ISNUMBER(SEARCH("incorrect",G89)), ISNUMBER(SEARCH("remove", G89))), "Incorrect Details", IF(ISNUMBER(SEARCH("incomplete",G89)), "Incomplete Details", IF(ISNUMBER(SEARCH("overdue",G89)), "Overdue Bill", IF(OR(ISNUMBER(SEARCH("resubmit as", G89)), ISNUMBER(SEARCH("re-submit as", G89))), "Incorrect Queue", IF(OR(ISNUMBER(SEARCH("100",G89)), ISNUMBER(SEARCH("correct", G89)), ISNUMBER(SEARCH("email", G89)), ISNUMBER(SEARCH("please submit", G89)), ISNUMBER(SEARCH("please resubmit",G89)), ISNUMBER(SEARCH("please re-submit", G89)), ISNUMBER(SEARCH("please send", G89))), "Incomplete Details", IF(ISNUMBER(SEARCH("error", G89)), "System Error", "Reason Unknown"))))))) -> Reason Unknown | I89: =(tbl_raw_data[[#This Row],[Date Actioned]])-(tbl_raw_data[[#This Row],[Date Tagged]]) -> 0.0060300926 | J89: =HOUR(tbl_raw_data[[#This Row],[time_taken]])*60+MINUTE(tbl_raw_data[[#This Row],[time_taken]])+SECOND(tbl_raw_data[[#This Row],[time_taken]])/60 -> 8.6833333 | K89: =DATE(YEAR(tbl_raw_data[[#This Row],[Date Actioned]]),MONTH(tbl_raw_data[[#This Row],[Date Actioned]]),DAY(tbl_raw_data[[#This Row],[Date Actioned]])) -> 45137 | L89: =UPPER(TEXT(tbl_raw_data[[#This Row],[updated_date]],"MMMM")) -> JULY | M89: ="WEEK "&IF(ROUNDUP(DAY(tbl_raw_data[[#This Row],[updated_date]])/7,0)=5,4,ROUNDUP(DAY(tbl_raw_data[[#This Row],[updated_date]])/7,0)) -> WEEK 4 | N89: =UPPER(VLOOKUP(tbl_raw_data[[#This Row],[Analyst]],settings!$A$1:$B$15,2,0)) -> CAMROON | O89: =TRIM(UPPER(tbl_raw_data[[#This Row],[Outcome]])) -> APPROVE | P89: =TRIM(UPPER(tbl_raw_data[[#This Row],[Queue Name]])) -> CONSUMER EXISTING | Q89: =IF(tbl_raw_data[[#This Row],[time_taken_in_min]]<=settings!$D$2,"SLA_MET","SLA_NOT_MET") -> SLA_MET
A90: 89 | B90: 45137.636 | C90: 45137.642 | D90: APPROVE | E90: Consumer Existing | F90: SBambaras | G90: Approved only with outright purchase of handset or USIM only | H90: =IF(OR(ISNUMBER(SEARCH("duplicate",G90)), ISNUMBER(SEARCH("previously",G90)), ISNUMBER(SEARCH("previously approved",G90))), "Duplicate Application", IF(OR(ISNUMBER(SEARCH("incorrect",G90)), ISNUMBER(SEARCH("remove", G90))), "Incorrect Details", IF(ISNUMBER(SEARCH("incomplete",G90)), "Incomplete Details", IF(ISNUMBER(SEARCH("overdue",G90)), "Overdue Bill", IF(OR(ISNUMBER(SEARCH("resubmit as", G90)), ISNUMBER(SEARCH("re-submit as", G90))), "Incorrect Queue", IF(OR(ISNUMBER(SEARCH("100",G90)), ISNUMBER(SEARCH("correct", G90)), ISNUMBER(SEARCH("email", G90)), ISNUMBER(SEARCH("please submit", G90)), ISNUMBER(SEARCH("please resubmit",G90)), ISNUMBER(SEARCH("please re-submit", G90)), ISNUMBER(SEARCH("please send", G90))), "Incomplete Details", IF(ISNUMBER(SEARCH("error", G90)), "System Error", "Reason Unknown"))))))) -> Reason Unknown | I90: =(tbl_raw_data[[#This Row],[Date Actioned]])-(tbl_raw_data[[#This Row],[Date Tagged]]) -> 0.0055092593 | J90: =HOUR(tbl_raw_data[[#This Row],[time_taken]])*60+MINUTE(tbl_raw_data[[#This Row],[time_taken]])+SECOND(tbl_raw_data[[#This Row],[time_taken]])/60 -> 7.9333333 | K90: =DATE(YEAR(tbl_raw_data[[#This Row],[Date Actioned]]),MONTH(tbl_raw_data[[#This Row],[Date Actioned]]),DAY(tbl_raw_data[[#This Row],[Date Actioned]])) -> 45137 | L90: =UPPER(TEXT(tbl_raw_data[[#This Row],[updated_date]],"MMMM")) -> JULY | M90: ="WEEK "&IF(ROUNDUP(DAY(tbl_raw_data[[#This Row],[updated_date]])/7,0)=5,4,ROUNDUP(DAY(tbl_raw_data[[#This Row],[updated_date]])/7,0)) -> WEEK 4 | N90: =UPPER(VLOOKUP(tbl_raw_data[[#This Row],[Analyst]],settings!$A$1:$B$15,2,0)) -> SAM | O90: =TRIM(UPPER(tbl_raw_data[[#This Row],[Outcome]])) -> APPROVE | P90: =TRIM(UPPER(tbl_raw_data[[#This Row],[Queue Name]])) -> CONSUMER EXISTING | Q90: =IF(tbl_raw_data[[#This Row],[time_taken_in_min]]<=settings!$D$2,"SLA_MET","SLA_NOT_MET") -> SLA_MET
A91: 90 | B91: 45137.636 | C91: 45137.643 | D91: APPROVE | E91: Consumer Existing | F91: RBose | G91: Approve | H91: =IF(OR(ISNUMBER(SEARCH("duplicate",G91)), ISNUMBER(SEARCH("previously",G91)), ISNUMBER(SEARCH("previously approved",G91))), "Duplicate Application", IF(OR(ISNUMBER(SEARCH("incorrect",G91)), ISNUMBER(SEARCH("remove", G91))), "Incorrect Details", IF(ISNUMBER(SEARCH("incomplete",G91)), "Incomplete Details", IF(ISNUMBER(SEARCH("overdue",G91)), "Overdue Bill", IF(OR(ISNUMBER(SEARCH("resubmit as", G91)), ISNUMBER(SEARCH("re-submit as", G91))), "Incorrect Queue", IF(OR(ISNUMBER(SEARCH("100",G91)), ISNUMBER(SEARCH("correct", G91)), ISNUMBER(SEARCH("email", G91)), ISNUMBER(SEARCH("please submit", G91)), ISNUMBER(SEARCH("please resubmit",G91)), ISNUMBER(SEARCH("please re-submit", G91)), ISNUMBER(SEARCH("please send", G91))), "Incomplete Details", IF(ISNUMBER(SEARCH("error", G91)), "System Error", "Reason Unknown"))))))) -> Reason Unknown | I91: =(tbl_raw_data[[#This Row],[Date Actioned]])-(tbl_raw_data[[#This Row],[Date Tagged]]) -> 0.0063657407 | J91: =HOUR(tbl_raw_data[[#This Row],[time_taken]])*60+MINUTE(tbl_raw_data[[#This Row],[time_taken]])+SECOND(tbl_raw_data[[#This Row],[time_taken]])/60 -> 9.1666667 | K91: =DATE(YEAR(tbl_raw_data[[#This Row],[Date Actioned]]),MONTH(tbl_raw_data[[#This Row],[Date Actioned]]),DAY(tbl_raw_data[[#This Row],[Date Actioned]])) -> 45137 | L91: =UPPER(TEXT(tbl_raw_data[[#This Row],[updated_date]],"MMMM")) -> JULY | M91: ="WEEK "&IF(ROUNDUP(DAY(tbl_raw_data[[#This Row],[updated_date]])/7,0)=5,4,ROUNDUP(DAY(tbl_raw_data[[#This Row],[updated_date]])/7,0)) -> WEEK 4 | N91: =UPPER(VLOOKUP(tbl_raw_data[[#This Row],[Analyst]],settings!$A$1:$B$15,2,0)) -> ROHAN | O91: =TRIM(UPPER(tbl_raw_data[[#This Row],[Outcome]])) -> APPROVE | P91: =TRIM(UPPER(tbl_raw_data[[#This Row],[Queue Name]])) -> CONSUMER EXISTING | Q91: =IF(tbl_raw_data[[#This Row],[time_taken_in_min]]<=settings!$D$2,"SLA_MET","SLA_NOT_MET") -> SLA_MET
A92: 91 | B92: 45137.638 | C92: 45137.643 | D92: APPROVE | E92: Consumer Pre Bureau | F92: NVaid | G92: Approve | H92: =IF(OR(ISNUMBER(SEARCH("duplicate",G92)), ISNUMBER(SEARCH("previously",G92)), ISNUMBER(SEARCH("previously approved",G92))), "Duplicate Application", IF(OR(ISNUMBER(SEARCH("incorrect",G92)), ISNUMBER(SEARCH("remove", G92))), "Incorrect Details", IF(ISNUMBER(SEARCH("incomplete",G92)), "Incomplete Details", IF(ISNUMBER(SEARCH("overdue",G92)), "Overdue Bill", IF(OR(ISNUMBER(SEARCH("resubmit as", G92)), ISNUMBER(SEARCH("re-submit as", G92))), "Incorrect Queue", IF(OR(ISNUMBER(SEARCH("100",G92)), ISNUMBER(SEARCH("correct", G92)), ISNUMBER(SEARCH("email", G92)), ISNUMBER(SEARCH("please submit", G92)), ISNUMBER(SEARCH("please resubmit",G92)), ISNUMBER(SEARCH("please re-submit", G92)), ISNUMBER(SEARCH("please send", G92))), "Incomplete Details", IF(ISNUMBER(SEARCH("error", G92)), "System Error", "Reason Unknown"))))))) -> Reason Unknown | I92: =(tbl_raw_data[[#This Row],[Date Actioned]])-(tbl_raw_data[[#This Row],[Date Tagged]]) -> 0.0045138889 | J92: =HOUR(tbl_raw_data[[#This Row],[time_taken]])*60+MINUTE(tbl_raw_data[[#This Row],[time_taken]])+SECOND(tbl_raw_data[[#This Row],[time_taken]])/60 -> 6.5 | K92: =DATE(YEAR(tbl_raw_data[[#This Row],[Date Actioned]]),MONTH(tbl_raw_data[[#This Row],[Date Actioned]]),DAY(tbl_raw_data[[#This Row],[Date Actioned]])) -> 45137 | L92: =UPPER(TEXT(tbl_raw_data[[#This Row],[updated_date]],"MMMM")) -> JULY | M92: ="WEEK "&IF(ROUNDUP(DAY(tbl_raw_data[[#This Row],[updated_date]])/7,0)=5,4,ROUNDUP(DAY(tbl_raw_data[[#This Row],[updated_date]])/7,0)) -> WEEK 4 | N92: =UPPER(VLOOKUP(tbl_raw_data[[#This Row],[Analyst]],settings!$A$1:$B$15,2,0)) -> NAVED | O92: =TRIM(UPPER(tbl_raw_data[[#This Row],[Outcome]])) -> APPROVE | P92: =TRIM(UPPER(tbl_raw_data[[#This Row],[Queue Name]])) -> CONSUMER PRE BUREAU | Q92: =IF(tbl_raw_data[[#This Row],[time_taken_in_min]]<=settings!$D$2,"SLA_MET","SLA_NOT_MET") -> SLA_MET
A93: 92 | B93: 45137.639 | C93: 45137.644 | D93: APPROVE | E93: Consumer Post Bureau | F93: AAkhundpur | G93: Approved only with outright purchase of handset or USIM only | H93: =IF(OR(ISNUMBER(SEARCH("duplicate",G93)), ISNUMBER(SEARCH("previously",G93)), ISNUMBER(SEARCH("previously approved",G93))), "Duplicate Application", IF(OR(ISNUMBER(SEARCH("incorrect",G93)), ISNUMBER(SEARCH("remove", G93))), "Incorrect Details", IF(ISNUMBER(SEARCH("incomplete",G93)), "Incomplete Details", IF(ISNUMBER(SEARCH("overdue",G93)), "Overdue Bill", IF(OR(ISNUMBER(SEARCH("resubmit as", G93)), ISNUMBER(SEARCH("re-submit as", G93))), "Incorrect Queue", IF(OR(ISNUMBER(SEARCH("100",G93)), ISNUMBER(SEARCH("correct", G93)), ISNUMBER(SEARCH("email", G93)), ISNUMBER(SEARCH("please submit", G93)), ISNUMBER(SEARCH("please resubmit",G93)), ISNUMBER(SEARCH("please re-submit", G93)), ISNUMBER(SEARCH("please send", G93))), "Incomplete Details", IF(ISNUMBER(SEARCH("error", G93)), "System Error", "Reason Unknown"))))))) -> Reason Unknown | I93: =(tbl_raw_data[[#This Row],[Date Actioned]])-(tbl_raw_data[[#This Row],[Date Tagged]]) -> 0.0046875 | J93: =HOUR(tbl_raw_data[[#This Row],[time_taken]])*60+MINUTE(tbl_raw_data[[#This Row],[time_taken]])+SECOND(tbl_raw_data[[#This Row],[time_taken]])/60 -> 6.75 | K93: =DATE(YEAR(tbl_raw_data[[#This Row],[Date Actioned]]),MONTH(tbl_raw_data[[#This Row],[Date Actioned]]),DAY(tbl_raw_data[[#This Row],[Date Actioned]])) -> 45137 | L93: =UPPER(TEXT(tbl_raw_data[[#This Row],[updated_date]],"MMMM")) -> JULY | M93: ="WEEK "&IF(ROUNDUP(DAY(tbl_raw_data[[#This Row],[updated_date]])/7,0)=5,4,ROUNDUP(DAY(tbl_raw_data[[#This Row],[updated_date]])/7,0)) -> WEEK 4 | N93: =UPPER(VLOOKUP(tbl_raw_data[[#This Row],[Analyst]],settings!$A$1:$B$15,2,0)) -> ASIF | O93: =TRIM(UPPER(tbl_raw_data[[#This Row],[Outcome]])) -> APPROVE | P93: =TRIM(UPPER(tbl_raw_data[[#This Row],[Queue Name]])) -> CONSUMER POST BUREAU | Q93: =IF(tbl_raw_data[[#This Row],[time_taken_in_min]]<=settings!$D$2,"SLA_MET","SLA_NOT_MET") -> SLA_MET
... A106: 105 | B106: 45137.667 | C106: 45137.679 | D106: APPROVE | E106: Consumer Pre Bureau | F106: AAkhundpur | G106: Approved for 1 Handset/Tablet + 1 MBB | H106: =IF(OR(ISNUMBER(SEARCH("duplicate",G106)), ISNUMBER(SEARCH("previously",G106)), ISNUMBER(SEARCH("previously approved",G106))), "Duplicate Application", IF(OR(ISNUMBER(SEARCH("incorrect",G106)), ISNUMBER(SEARCH("remove", G106))), "Incorrect Details", IF(ISNUMBER(SEARCH("incomplete",G106)), "Incomplete Details", IF(ISNUMBER(SEARCH("overdue",G106)), "Overdue Bill", IF(OR(ISNUMBER(SEARCH("resubmit as", G106)), ISNUMBER(SEARCH("re-submit as", G106))), "Incorrect Queue", IF(OR(ISNUMBER(SEARCH("100",G106)), ISNUMBER(SEARCH("correct", G106)), ISNUMBER(SEARCH("email", G106)), ISNUMBER(SEARCH("please submit", G106)), ISNUMBER(SEARCH("please resubmit",G106)), ISNUMBER(SEARCH("please re-submit", G106)), ISNUMBER(SEARCH("please send", G106))), "Incomplete Details", IF(ISNUMBER(SEARCH("error", G106)), "System Error", "Reason Unknown"))))))) -> Reason Unknown | I106: =(tbl_raw_data[[#This Row],[Date Actioned]])-(tbl_raw_data[[#This Row],[Date Tagged]]) -> 0.012118056 | J106: =HOUR(tbl_raw_data[[#This Row],[time_taken]])*60+MINUTE(tbl_raw_data[[#This Row],[time_taken]])+SECOND(tbl_raw_data[[#This Row],[time_taken]])/60 -> 17.45 | K106: =DATE(YEAR(tbl_raw_data[[#This Row],[Date Actioned]]),MONTH(tbl_raw_data[[#This Row],[Date Actioned]]),DAY(tbl_raw_data[[#This Row],[Date Actioned]])) -> 45137 | L106: =UPPER(TEXT(tbl_raw_data[[#This Row],[updated_date]],"MMMM")) -> JULY | M106: ="WEEK "&IF(ROUNDUP(DAY(tbl_raw_data[[#This Row],[updated_date]])/7,0)=5,4,ROUNDUP(DAY(tbl_raw_data[[#This Row],[updated_date]])/7,0)) -> WEEK 4 | N106: =UPPER(VLOOKUP(tbl_raw_data[[#This Row],[Analyst]],settings!$A$1:$B$15,2,0)) -> ASIF | O106: =TRIM(UPPER(tbl_raw_data[[#This Row],[Outcome]])) -> APPROVE | P106: =TRIM(UPPER(tbl_raw_data[[#This Row],[Queue Name]])) -> CONSUMER PRE BUREAU | Q106: =IF(tbl_raw_data[[#This Row],[time_taken_in_min]]<=settings!$D$2,"SLA_MET","SLA_NOT_MET") -> SLA_MET
A107: 106 | B107: 45137.667 | C107: 45137.67 | D107: Approve | E107: Consumer Existing | F107: SSyed | H107: =IF(OR(ISNUMBER(SEARCH("duplicate",G107)), ISNUMBER(SEARCH("previously",G107)), ISNUMBER(SEARCH("previously approved",G107))), "Duplicate Application", IF(OR(ISNUMBER(SEARCH("incorrect",G107)), ISNUMBER(SEARCH("remove", G107))), "Incorrect Details", IF(ISNUMBER(SEARCH("incomplete",G107)), "Incomplete Details", IF(ISNUMBER(SEARCH("overdue",G107)), "Overdue Bill", IF(OR(ISNUMBER(SEARCH("resubmit as", G107)), ISNUMBER(SEARCH("re-submit as", G107))), "Incorrect Queue", IF(OR(ISNUMBER(SEARCH("100",G107)), ISNUMBER(SEARCH("correct", G107)), ISNUMBER(SEARCH("email", G107)), ISNUMBER(SEARCH("please submit", G107)), ISNUMBER(SEARCH("please resubmit",G107)), ISNUMBER(SEARCH("please re-submit", G107)), ISNUMBER(SEARCH("please send", G107))), "Incomplete Details", IF(ISNUMBER(SEARCH("error", G107)), "System Error", "Reason Unknown"))))))) -> Reason Unknown | I107: =(tbl_raw_data[[#This Row],[Date Actioned]])-(tbl_raw_data[[#This Row],[Date Tagged]]) -> 0.0034259259 | J107: =HOUR(tbl_raw_data[[#This Row],[time_taken]])*60+MINUTE(tbl_raw_data[[#This Row],[time_taken]])+SECOND(tbl_raw_data[[#This Row],[time_taken]])/60 -> 4.9333333 | K107: =DATE(YEAR(tbl_raw_data[[#This Row],[Date Actioned]]),MONTH(tbl_raw_data[[#This Row],[Date Actioned]]),DAY(tbl_raw_data[[#This Row],[Date Actioned]])) -> 45137 | L107: =UPPER(TEXT(tbl_raw_data[[#This Row],[updated_date]],"MMMM")) -> JULY | M107: ="WEEK "&IF(ROUNDUP(DAY(tbl_raw_data[[#This Row],[updated_date]])/7,0)=5,4,ROUNDUP(DAY(tbl_raw_data[[#This Row],[updated_date]])/7,0)) -> WEEK 4 | N107: =UPPER(VLOOKUP(tbl_raw_data[[#This Row],[Analyst]],settings!$A$1:$B$15,2,0)) -> SHAHID | O107: =TRIM(UPPER(tbl_raw_data[[#This Row],[Outcome]])) -> APPROVE | P107: =TRIM(UPPER(tbl_raw_data[[#This Row],[Queue Name]])) -> CONSUMER EXISTING | Q107: =IF(tbl_raw_data[[#This Row],[time_taken_in_min]]<=settings!$D$2,"SLA_MET","SLA_NOT_MET") -> SLA_MET
A108: 107 | B108: 45137.667 | C108: 45137.674 | D108: Approve | E108: Consumer Existing | F108: SSyed | H108: =IF(OR(ISNUMBER(SEARCH("duplicate",G108)), ISNUMBER(SEARCH("previously",G108)), ISNUMBER(SEARCH("previously approved",G108))), "Duplicate Application", IF(OR(ISNUMBER(SEARCH("incorrect",G108)), ISNUMBER(SEARCH("remove", G108))), "Incorrect Details", IF(ISNUMBER(SEARCH("incomplete",G108)), "Incomplete Details", IF(ISNUMBER(SEARCH("overdue",G108)), "Overdue Bill", IF(OR(ISNUMBER(SEARCH("resubmit as", G108)), ISNUMBER(SEARCH("re-submit as", G108))), "Incorrect Queue", IF(OR(ISNUMBER(SEARCH("100",G108)), ISNUMBER(SEARCH("correct", G108)), ISNUMBER(SEARCH("email", G108)), ISNUMBER(SEARCH("please submit", G108)), ISNUMBER(SEARCH("please resubmit",G108)), ISNUMBER(SEARCH("please re-submit", G108)), ISNUMBER(SEARCH("please send", G108))), "Incomplete Details", IF(ISNUMBER(SEARCH("error", G108)), "System Error", "Reason Unknown"))))))) -> Reason Unknown | I108: =(tbl_raw_data[[#This Row],[Date Actioned]])-(tbl_raw_data[[#This Row],[Date Tagged]]) -> 0.0067824074 | J108: =HOUR(tbl_raw_data[[#This Row],[time_taken]])*60+MINUTE(tbl_raw_data[[#This Row],[time_taken]])+SECOND(tbl_raw_data[[#This Row],[time_taken]])/60 -> 9.7666667 | K108: =DATE(YEAR(tbl_raw_data[[#This Row],[Date Actioned]]),MONTH(tbl_raw_data[[#This Row],[Date Actioned]]),DAY(tbl_raw_data[[#This Row],[Date Actioned]])) -> 45137 | L108: =UPPER(TEXT(tbl_raw_data[[#This Row],[updated_date]],"MMMM")) -> JULY | M108: ="WEEK "&IF(ROUNDUP(DAY(tbl_raw_data[[#This Row],[updated_date]])/7,0)=5,4,ROUNDUP(DAY(tbl_raw_data[[#This Row],[updated_date]])/7,0)) -> WEEK 4 | N108: =UPPER(VLOOKUP(tbl_raw_data[[#This Row],[Analyst]],settings!$A$1:$B$15,2,0)) -> SHAHID | O108: =TRIM(UPPER(tbl_raw_data[[#This Row],[Outcome]])) -> APPROVE | P108: =TRIM(UPPER(tbl_raw_data[[#This Row],[Queue Name]])) -> CONSUMER EXISTING | Q108: =IF(tbl_raw_data[[#This Row],[time_taken_in_min]]<=settings!$D$2,"SLA_MET","SLA_NOT_MET") -> SLA_MET
A109: 108 | B109: 45137.675 | C109: 45137.684 | D109: APPROVE | E109: Consumer Post Bureau | F109: CDcosta | G109: Approved only with outright purchase of handset or USIM only | H109: =IF(OR(ISNUMBER(SEARCH("duplicate",G109)), ISNUMBER(SEARCH("previously",G109)), ISNUMBER(SEARCH("previously approved",G109))), "Duplicate Application", IF(OR(ISNUMBER(SEARCH("incorrect",G109)), ISNUMBER(SEARCH("remove", G109))), "Incorrect Details", IF(ISNUMBER(SEARCH("incomplete",G109)), "Incomplete Details", IF(ISNUMBER(SEARCH("overdue",G109)), "Overdue Bill", IF(OR(ISNUMBER(SEARCH("resubmit as", G109)), ISNUMBER(SEARCH("re-submit as", G109))), "Incorrect Queue", IF(OR(ISNUMBER(SEARCH("100",G109)), ISNUMBER(SEARCH("correct", G109)), ISNUMBER(SEARCH("email", G109)), ISNUMBER(SEARCH("please submit", G109)), ISNUMBER(SEARCH("please resubmit",G109)), ISNUMBER(SEARCH("please re-submit", G109)), ISNUMBER(SEARCH("please send", G109))), "Incomplete Details", IF(ISNUMBER(SEARCH("error", G109)), "System Error", "Reason Unknown"))))))) -> Reason Unknown | I109: =(tbl_raw_data[[#This Row],[Date Actioned]])-(tbl_raw_data[[#This Row],[Date Tagged]]) -> 0.0082407407 | J109: =HOUR(tbl_raw_data[[#This Row],[time_taken]])*60+MINUTE(tbl_raw_data[[#This Row],[time_taken]])+SECOND(tbl_raw_data[[#This Row],[time_taken]])/60 -> 11.866667 | K109: =DATE(YEAR(tbl_raw_data[[#This Row],[Date Actioned]]),MONTH(tbl_raw_data[[#This Row],[Date Actioned]]),DAY(tbl_raw_data[[#This Row],[Date Actioned]])) -> 45137 | L109: =UPPER(TEXT(tbl_raw_data[[#This Row],[updated_date]],"MMMM")) -> JULY | M109: ="WEEK "&IF(ROUNDUP(DAY(tbl_raw_data[[#This Row],[updated_date]])/7,0)=5,4,ROUNDUP(DAY(tbl_raw_data[[#This Row],[updated_date]])/7,0)) -> WEEK 4 | N109: =UPPER(VLOOKUP(tbl_raw_data[[#This Row],[Analyst]],settings!$A$1:$B$15,2,0)) -> CAMROON | O109: =TRIM(UPPER(tbl_raw_data[[#This Row],[Outcome]])) -> APPROVE | P109: =TRIM(UPPER(tbl_raw_data[[#This Row],[Queue Name]])) -> CONSUMER POST BUREAU | Q109: =IF(tbl_raw_data[[#This Row],[time_taken_in_min]]<=settings!$D$2,"SLA_MET","SLA_NOT_MET") -> SLA_MET
A110: 109 | B110: 45137.676 | C110: 45137.684 | D110: APPROVE | E110: Consumer Post Bureau | F110: SBambaras | G110: Approved only with outright purchase of handset or USIM only | H110: =IF(OR(ISNUMBER(SEARCH("duplicate",G110)), ISNUMBER(SEARCH("previously",G110)), ISNUMBER(SEARCH("previously approved",G110))), "Duplicate Application", IF(OR(ISNUMBER(SEARCH("incorrect",G110)), ISNUMBER(SEARCH("remove", G110))), "Incorrect Details", IF(ISNUMBER(SEARCH("incomplete",G110)), "Incomplete Details", IF(ISNUMBER(SEARCH("overdue",G110)), "Overdue Bill", IF(OR(ISNUMBER(SEARCH("resubmit as", G110)), ISNUMBER(SEARCH("re-submit as", G110))), "Incorrect Queue", IF(OR(ISNUMBER(SEARCH("100",G110)), ISNUMBER(SEARCH("correct", G110)), ISNUMBER(SEARCH("email", G110)), ISNUMBER(SEARCH("please submit", G110)), ISNUMBER(SEARCH("please resubmit",G110)), ISNUMBER(SEARCH("please re-submit", G110)), ISNUMBER(SEARCH("please send", G110))), "Incomplete Details", IF(ISNUMBER(SEARCH("error", G110)), "System Error", "Reason Unknown"))))))) -> Reason Unknown | I110: =(tbl_raw_data[[#This Row],[Date Actioned]])-(tbl_raw_data[[#This Row],[Date Tagged]]) -> 0.0074074074 | J110: =HOUR(tbl_raw_data[[#This Row],[time_taken]])*60+MINUTE(tbl_raw_data[[#This Row],[time_taken]])+SECOND(tbl_raw_data[[#This Row],[time_taken]])/60 -> 10.666667 | K110: =DATE(YEAR(tbl_raw_data[[#This Row],[Date Actioned]]),MONTH(tbl_raw_data[[#This Row],[Date Actioned]]),DAY(tbl_raw_data[[#This Row],[Date Actioned]])) -> 45137 | L110: =UPPER(TEXT(tbl_raw_data[[#This Row],[updated_date]],"MMMM")) -> JULY | M110: ="WEEK "&IF(ROUNDUP(DAY(tbl_raw_data[[#This Row],[updated_date]])/7,0)=5,4,ROUNDUP(DAY(tbl_raw_data[[#This Row],[updated_date]])/7,0)) -> WEEK 4 | N110: =UPPER(VLOOKUP(tbl_raw_data[[#This Row],[Analyst]],settings!$A$1:$B$15,2,0)) -> SAM | O110: =TRIM(UPPER(tbl_raw_data[[#This Row],[Outcome]])) -> APPROVE | P110: =TRIM(UPPER(tbl_raw_data[[#This Row],[Queue Name]])) -> CONSUMER POST BUREAU | Q110: =IF(tbl_raw_data[[#This Row],[time_taken_in_min]]<=settings!$D$2,"SLA_MET","SLA_NOT_MET") -> SLA_MET
A111: 110 | B111: 45137.679 | C111: 45137.685 | D111: APPROVE | E111: Consumer Pre Bureau | F111: AAkhundpur | G111: Approved only with outright purchase of handset or USIM only | H111: =IF(OR(ISNUMBER(SEARCH("duplicate",G111)), ISNUMBER(SEARCH("previously",G111)), ISNUMBER(SEARCH("previously approved",G111))), "Duplicate Application", IF(OR(ISNUMBER(SEARCH("incorrect",G111)), ISNUMBER(SEARCH("remove", G111))), "Incorrect Details", IF(ISNUMBER(SEARCH("incomplete",G111)), "Incomplete Details", IF(ISNUMBER(SEARCH("overdue",G111)), "Overdue Bill", IF(OR(ISNUMBER(SEARCH("resubmit as", G111)), ISNUMBER(SEARCH("re-submit as", G111))), "Incorrect Queue", IF(OR(ISNUMBER(SEARCH("100",G111)), ISNUMBER(SEARCH("correct", G111)), ISNUMBER(SEARCH("email", G111)), ISNUMBER(SEARCH("please submit", G111)), ISNUMBER(SEARCH("please resubmit",G111)), ISNUMBER(SEARCH("please re-submit", G111)), ISNUMBER(SEARCH("please send", G111))), "Incomplete Details", IF(ISNUMBER(SEARCH("error", G111)), "System Error", "Reason Unknown"))))))) -> Reason Unknown | I111: =(tbl_raw_data[[#This Row],[Date Actioned]])-(tbl_raw_data[[#This Row],[Date Tagged]]) -> 0.006412037 | J111: =HOUR(tbl_raw_data[[#This Row],[time_taken]])*60+MINUTE(tbl_raw_data[[#This Row],[time_taken]])+SECOND(tbl_raw_data[[#This Row],[time_taken]])/60 -> 9.2333333 | K111: =DATE(YEAR(tbl_raw_data[[#This Row],[Date Actioned]]),MONTH(tbl_raw_data[[#This Row],[Date Actioned]]),DAY(tbl_raw_data[[#This Row],[Date Actioned]])) -> 45137 | L111: =UPPER(TEXT(tbl_raw_data[[#This Row],[updated_date]],"MMMM")) -> JULY | M111: ="WEEK "&IF(ROUNDUP(DAY(tbl_raw_data[[#This Row],[updated_date]])/7,0)=5,4,ROUNDUP(DAY(tbl_raw_data[[#This Row],[updated_date]])/7,0)) -> WEEK 4 | N111: =UPPER(VLOOKUP(tbl_raw_data[[#This Row],[Analyst]],settings!$A$1:$B$15,2,0)) -> ASIF | O111: =TRIM(UPPER(tbl_raw_data[[#This Row],[Outcome]])) -> APPROVE | P111: =TRIM(UPPER(tbl_raw_data[[#This Row],[Queue Name]])) -> CONSUMER PRE BUREAU | Q111: =IF(tbl_raw_data[[#This Row],[time_taken_in_min]]<=settings!$D$2,"SLA_MET","SLA_NOT_MET") -> SLA_MET
